Workbook

Sheet Pipeline_Control
A1: Pipeline Row | B1: Deal ID | C1: Product / Project | D1: Customer | E1: Category | F1: Quarter | G1: Sales Rep | H1: Deal Status | I1: Include in Forecast | J1: Expected Close Date | K1: Pipeline Amount | L1: Probability | M1: Weighted Forecast | N1: Approved SO Number(s) | O1: Approved SO Amount | P1: SO Approved Date | Q1: Remaining Pipeline After SO | R1: SO Conversion % | S1: Forecast Status | T1: Stale Deal Flag | U1: Notes | V1: Dashboard Notes | W1: Data Quality Check | X1: Expected Ship/Invoice Date | Y1: Expected Cash Date | Z1: Deposit % | AA1: Deposit Cash Date | AB1: Balance Cash Date | AC1: SO Match Status | AD1: Converted Amount | AE1: Remaining Forecast Amount | AF1: Timing Confidence | AG1: Last Reviewed Date | AH1: Manual Override Reason | AI1: Pipeline Visibility | AJ1: Cash Forecast Eligibility | AK1: Liquidity Feed Eligible | AL1: Mapped SO Amount | AM1: SO Mapping Review Required | AN1: Remaining Pipeline - Mapping Safe | AO1: Eligibility Reason | AP1: Cash Timing Bucket | AQ1: App Control Notes
A2: 2 | B2: DPS-0002 | C2: SDJ GEN Z BAGS | D2: SDJ | E2: SOFT GOODS | F2: Q4 | G2: Danny Park | H2: Won | I2: Y | J2: 2026-04-30 | K2: 3000000 | L2: 1 | M2: 3000000 | N2: SO2599, SO2597, SO2598, 2608, 2609, 2610, 2611, 2612, 2613 | O2: 2672706 | P2: 2026-04-30 | Q2: 327294 | R2: 89.1% | S2: Partially Converted | U2: based on invoice date | W2: OK | X2: 2026-04-30 | Y2: 2026-05-30 | Z2: 0 | AB2: 2026-05-30 | AC2: SO Linked | AD2: 2672706 | AE2: 327294 | AF2: High - SO Supported | AG2: 2026-05-23 | AI2: =IF(OR($H2="Lost",$H2="Dead"),"Lost",IF($I2<>"Y","Excluded",IF($N2<>"","Converted/Partially Converted",IF($J2="","Watchlist","Active")))) -> Converted/Partially Converted | AJ2: =IF($I2<>"Y","Not Eligible - Excluded",IF(OR($H2="Lost",$H2="Dead"),"Not Eligible - Lost",IF($J2="","Scenario Only - No Close Date",IF($X2="","Scenario Only - No Ship Date",IF($Y2="","Scenario Only - No Cash Date",IF($AM2="Y","Not Eligible - SO Mapping Review","Eligible")))))) -> Not Eligible - SO Mapping Review | AK2: =IF($AJ2="Eligible","Y","N") -> N | AL2: =SUMIFS(SO_Mapping!$F:$F,SO_Mapping!$A:$A,$B2) -> 0 | AM2: =IF(AND($N2<>"",$AL2=0),"Y",IF(ABS($O2-$AL2)>1,"Y","N")) -> Y | AN2: =MAX(0,$K2-$AL2) -> 3000000 | AO2: =IF($AK2="Y","Cash eligible",IF($I2<>"Y","Excluded by control flag",IF($J2="","No expected close date",IF($X2="","No ship/invoice timing",IF($Y2="","No cash timing",IF($AM2="Y","SO mapping must be resolved","Review required")))))) -> SO mapping must be resolved | AP2: =IF($AK2="Y",TEXT($Y2,"yyyy-mm-dd"),"")
A3: 4 | B3: DPS-0004 | C3: SDJ JET BAGS | D3: SDJ | E3: SOFT GOODS | F3: Q3 | G3: Danny Park | H3: Won | I3: Y | J3: 2026-05-06 | K3: 1560000 | L3: 0.75 | M3: 1170000 | N3: SO2601, SO2602 | O3: 290080 | P3: 2026-05-06 | Q3: 1269920 | R3: 18.6% | S3: Partially Converted | U3: based on invoice date | W3: OK | X3: 2026-05-06 | Y3: 2026-06-05 | Z3: 0 | AB3: 2026-06-05 | AC3: SO Linked | AD3: 290080 | AE3: 1269920 | AF3: High - SO Supported | AG3: 2026-05-23 | AI3: =IF(OR($H3="Lost",$H3="Dead"),"Lost",IF($I3<>"Y","Excluded",IF($N3<>"","Converted/Partially Converted",IF($J3="","Watchlist","Active")))) -> Converted/Partially Converted | AJ3: =IF($I3<>"Y","Not Eligible - Excluded",IF(OR($H3="Lost",$H3="Dead"),"Not Eligible - Lost",IF($J3="","Scenario Only - No Close Date",IF($X3="","Scenario Only - No Ship Date",IF($Y3="","Scenario Only - No Cash Date",IF($AM3="Y","Not Eligible - SO Mapping Review","Eligible")))))) -> Not Eligible - SO Mapping Review | AK3: =IF($AJ3="Eligible","Y","N") -> N | AL3: =SUMIFS(SO_Mapping!$F:$F,SO_Mapping!$A:$A,$B3) -> 0 | AM3: =IF(AND($N3<>"",$AL3=0),"Y",IF(ABS($O3-$AL3)>1,"Y","N")) -> Y | AN3: =MAX(0,$K3-$AL3) -> 1560000 | AO3: =IF($AK3="Y","Cash eligible",IF($I3<>"Y","Excluded by control flag",IF($J3="","No expected close date",IF($X3="","No ship/invoice timing",IF($Y3="","No cash timing",IF($AM3="Y","SO mapping must be resolved","Review required")))))) -> SO mapping must be resolved | AP3: =IF($AK3="Y",TEXT($Y3,"yyyy-mm-dd"),"")
A4: 5 | B4: DPS-0005 | C4: SDJ GEN Z BAGS | D4: SDJ | E4: SOFT GOODS | F4: Q2 | G4: Danny Park | H4: Won | I4: Y | J4: 2026-02-25 | K4: 1500000 | L4: 0.75 | M4: 1125000 | N4: open: SO2563, 2564, 2562, invoiced: 2561 | O4: 1114750 | P4: 2026-02-25 | Q4: 385250 | R4: 74.3% | S4: Partially Converted | U4: 2561 is still open, based on invoice date | W4: OK | X4: 2026-02-25 | Y4: 2026-03-27 | Z4: 0 | AB4: 2026-03-27 | AC4: SO Linked | AD4: 1114750 | AE4: 385250 | AF4: High - SO Supported | AG4: 2026-05-23 | AI4: =IF(OR($H4="Lost",$H4="Dead"),"Lost",IF($I4<>"Y","Excluded",IF($N4<>"","Converted/Partially Converted",IF($J4="","Watchlist","Active")))) -> Converted/Partially Converted | AJ4: =IF($I4<>"Y","Not Eligible - Excluded",IF(OR($H4="Lost",$H4="Dead"),"Not Eligible - Lost",IF($J4="","Scenario Only - No Close Date",IF($X4="","Scenario Only - No Ship Date",IF($Y4="","Scenario Only - No Cash Date",IF($AM4="Y","Not Eligible - SO Mapping Review","Eligible")))))) -> Not Eligible - SO Mapping Review | AK4: =IF($AJ4="Eligible","Y","N") -> N | AL4: =SUMIFS(SO_Mapping!$F:$F,SO_Mapping!$A:$A,$B4) -> 0 | AM4: =IF(AND($N4<>"",$AL4=0),"Y",IF(ABS($O4-$AL4)>1,"Y","N")) -> Y | AN4: =MAX(0,$K4-$AL4) -> 1500000 | AO4: =IF($AK4="Y","Cash eligible",IF($I4<>"Y","Excluded by control flag",IF($J4="","No expected close date",IF($X4="","No ship/invoice timing",IF($Y4="","No cash timing",IF($AM4="Y","SO mapping must be resolved","Review required")))))) -> SO mapping must be resolved | AP4: =IF($AK4="Y",TEXT($Y4,"yyyy-mm-dd"),"")
A5: 6 | B5: DPS-0006 | C5: SDJ JET BAGS | D5: SDJ | E5: SOFT GOODS | F5: Q2 | G5: Danny Park | H5: Won | I5: Y | J5: 2026-01-15 | K5: 1150000 | L5: 0.75 | M5: 862500 | N5: SO2531, 2532 | O5: 259000 | P5: 2026-01-15 | Q5: 891000 | R5: 22.5% | S5: Partially Converted | U5: based on invoice date | W5: OK | X5: 2026-01-15 | Y5: 2026-02-14 | Z5: 0 | AB5: 2026-02-14 | AC5: SO Linked | AD5: 259000 | AE5: 891000 | AF5: High - SO Supported | AG5: 2026-05-23 | AI5: =IF(OR($H5="Lost",$H5="Dead"),"Lost",IF($I5<>"Y","Excluded",IF($N5<>"","Converted/Partially Converted",IF($J5="","Watchlist","Active")))) -> Converted/Partially Converted | AJ5: =IF($I5<>"Y","Not Eligible - Excluded",IF(OR($H5="Lost",$H5="Dead"),"Not Eligible - Lost",IF($J5="","Scenario Only - No Close Date",IF($X5="","Scenario Only - No Ship Date",IF($Y5="","Scenario Only - No Cash Date",IF($AM5="Y","Not Eligible - SO Mapping Review","Eligible")))))) -> Not Eligible - SO Mapping Review | AK5: =IF($AJ5="Eligible","Y","N") -> N | AL5: =SUMIFS(SO_Mapping!$F:$F,SO_Mapping!$A:$A,$B5) -> 0 | AM5: =IF(AND($N5<>"",$AL5=0),"Y",IF(ABS($O5-$AL5)>1,"Y","N")) -> Y | AN5: =MAX(0,$K5-$AL5) -> 1150000 | AO5: =IF($AK5="Y","Cash eligible",IF($I5<>"Y","Excluded by control flag",IF($J5="","No expected close date",IF($X5="","No ship/invoice timing",IF($Y5="","No cash timing",IF($AM5="Y","SO mapping must be resolved","Review required")))))) -> SO mapping must be resolved | AP5: =IF($AK5="Y",TEXT($Y5,"yyyy-mm-dd"),"")
A6: 7 | B6: DPS-0007 | C6: SDJ JET BAGS | D6: SDJ | E6: SOFT GOODS | F6: Q4 | G6: Danny Park | H6: Open | I6: Y | K6: 1100000 | L6: 0.75 | M6: 825000 | Q6: 1100000 | R6: 0.0% | S6: Open | W6: OK | Z6: 0 | AC6: No SO Yet | AD6: 0 | AE6: 1100000 | AF6: Low - Missing Timing | AG6: 2026-05-23 | AI6: =IF(OR($H6="Lost",$H6="Dead"),"Lost",IF($I6<>"Y","Excluded",IF($N6<>"","Converted/Partially Converted",IF($J6="","Watchlist","Active")))) -> Watchlist | AJ6: =IF($I6<>"Y","Not Eligible - Excluded",IF(OR($H6="Lost",$H6="Dead"),"Not Eligible - Lost",IF($J6="","Scenario Only - No Close Date",IF($X6="","Scenario Only - No Ship Date",IF($Y6="","Scenario Only - No Cash Date",IF($AM6="Y","Not Eligible - SO Mapping Review","Eligible")))))) -> Scenario Only - No Close Date | AK6: =IF($AJ6="Eligible","Y","N") -> N | AL6: =SUMIFS(SO_Mapping!$F:$F,SO_Mapping!$A:$A,$B6) -> 0 | AM6: =IF(AND($N6<>"",$AL6=0),"Y",IF(ABS($O6-$AL6)>1,"Y","N")) -> N | AN6: =MAX(0,$K6-$AL6) -> 1100000 | AO6: =IF($AK6="Y","Cash eligible",IF($I6<>"Y","Excluded by control flag",IF($J6="","No expected close date",IF($X6="","No ship/invoice timing",IF($Y6="","No cash timing",IF($AM6="Y","SO mapping must be resolved","Review required")))))) -> No expected close date | AP6: =IF($AK6="Y",TEXT($Y6,"yyyy-mm-dd"),"")
A7: 9 | B7: DPS-0009 | C7: GEN Z - Spring bag | D7: SDJ | E7: SOFT GOODS | F7: Q3 | G7: Danny Park | H7: Open | I7: Y | K7: 500000 | L7: 0.9 | M7: 450000 | Q7: 500000 | R7: 0.0% | S7: Open | W7: OK | Z7: 0 | AC7: No SO Yet | AD7: 0 | AE7: 500000 | AF7: Low - Missing Timing | AG7: 2026-05-23 | AI7: =IF(OR($H7="Lost",$H7="Dead"),"Lost",IF($I7<>"Y","Excluded",IF($N7<>"","Converted/Partially Converted",IF($J7="","Watchlist","Active")))) -> Watchlist | AJ7: =IF($I7<>"Y","Not Eligible - Excluded",IF(OR($H7="Lost",$H7="Dead"),"Not Eligible - Lost",IF($J7="","Scenario Only - No Close Date",IF($X7="","Scenario Only - No Ship Date",IF($Y7="","Scenario Only - No Cash Date",IF($AM7="Y","Not Eligible - SO Mapping Review","Eligible")))))) -> Scenario Only - No Close Date | AK7: =IF($AJ7="Eligible","Y","N") -> N | AL7: =SUMIFS(SO_Mapping!$F:$F,SO_Mapping!$A:$A,$B7) -> 0 | AM7: =IF(AND($N7<>"",$AL7=0),"Y",IF(ABS($O7-$AL7)>1,"Y","N")) -> N | AN7: =MAX(0,$K7-$AL7) -> 500000 | AO7: =IF($AK7="Y","Cash eligible",IF($I7<>"Y","Excluded by control flag",IF($J7="","No expected close date",IF($X7="","No ship/invoice timing",IF($Y7="","No cash timing",IF($AM7="Y","SO mapping must be resolved","Review required")))))) -> No expected close date | AP7: =IF($AK7="Y",TEXT($Y7,"yyyy-mm-dd"),"")
A8: 11 | B8: DPS-0011 | C8: SDJ JET BAGS | D8: SDJ | E8: SOFT GOODS | F8: Q2 | G8: Danny Park | H8: Won | I8: Y | J8: 2026-04-28 | K8: 500000 | L8: 0.75 | M8: 375000 | N8: SO2547, 2548, 2549; open: 2545, 2546, 2550, 2551, various | O8: 65518 | P8: 2026-04-28 | Q8: 434482 | R8: 13.1% | S8: Partially Converted | U8: CARDS ONLY - invoiced and open | W8: OK | X8: 2026-04-28 | Y8: 2026-05-28 | Z8: 0 | AB8: 2026-05-28 | AC8: SO Linked | AD8: 65518 | AE8: 434482 | AF8: High - SO Supported | AG8: 2026-05-23 | AI8: =IF(OR($H8="Lost",$H8="Dead"),"Lost",IF($I8<>"Y","Excluded",IF($N8<>"","Converted/Partially Converted",IF($J8="","Watchlist","Active")))) -> Converted/Partially Converted | AJ8: =IF($I8<>"Y","Not Eligible - Excluded",IF(OR($H8="Lost",$H8="Dead"),"Not Eligible - Lost",IF($J8="","Scenario Only - No Close Date",IF($X8="","Scenario Only - No Ship Date",IF($Y8="","Scenario Only - No Cash Date",IF($AM8="Y","Not Eligible - SO Mapping Review","Eligible")))))) -> Not Eligible - SO Mapping Review | AK8: =IF($AJ8="Eligible","Y","N") -> N | AL8: =SUMIFS(SO_Mapping!$F:$F,SO_Mapping!$A:$A,$B8) -> 0 | AM8: =IF(AND($N8<>"",$AL8=0),"Y",IF(ABS($O8-$AL8)>1,"Y","N")) -> Y | AN8: =MAX(0,$K8-$AL8) -> 500000 | AO8: =IF($AK8="Y","Cash eligible",IF($I8<>"Y","Excluded by control flag",IF($J8="","No expected close date",IF($X8="","No ship/invoice timing",IF($Y8="","No cash timing",IF($AM8="Y","SO mapping must be resolved","Review required")))))) -> SO mapping must be resolved | AP8: =IF($AK8="Y",TEXT($Y8,"yyyy-mm-dd"),"")
A9: 12 | B9: DPS-0012 | C9: Foundation Sample Packets | D9: TOWER 28 | E9: COPACKING | F9: Q2 | G9: Jackie King | H9: Won | I9: Y | J9: 2026-02-09 | K9: 275000 | L9: 1 | M9: 275000 | N9: SO2554 | O9: 280000 | P9: 2026-02-09 | R9: 101.8% | S9: Fully Converted | W9: OK | X9: 2026-02-09 | Y9: 2026-03-11 | Z9: 0 | AB9: 2026-03-11 | AC9: SO Linked | AD9: 280000 | AE9: 0 | AF9: High - SO Supported | AG9: 2026-05-23 | AI9: =IF(OR($H9="Lost",$H9="Dead"),"Lost",IF($I9<>"Y","Excluded",IF($N9<>"","Converted/Partially Converted",IF($J9="","Watchlist","Active")))) -> Converted/Partially Converted | AJ9: =IF($I9<>"Y","Not Eligible - Excluded",IF(OR($H9="Lost",$H9="Dead"),"Not Eligible - Lost",IF($J9="","Scenario Only - No Close Date",IF($X9="","Scenario Only - No Ship Date",IF($Y9="","Scenario Only - No Cash Date",IF($AM9="Y","Not Eligible - SO Mapping Review","Eligible")))))) -> Eligible | AK9: =IF($AJ9="Eligible","Y","N") -> Y | AL9: =SUMIFS(SO_Mapping!$F:$F,SO_Mapping!$A:$A,$B9) -> 280000 | AM9: =IF(AND($N9<>"",$AL9=0),"Y",IF(ABS($O9-$AL9)>1,"Y","N")) -> N | AN9: =MAX(0,$K9-$AL9) -> 0 | AO9: =IF($AK9="Y","Cash eligible",IF($I9<>"Y","Excluded by control flag",IF($J9="","No expected close date",IF($X9="","No ship/invoice timing",IF($Y9="","No cash timing",IF($AM9="Y","SO mapping must be resolved","Review required")))))) -> Cash eligible | AP9: =IF($AK9="Y",TEXT($Y9,"yyyy-mm-dd"),"") -> 2026-03-11
A10: 13 | B10: DPS-0013 | C10: RO - Replenishment | D10: RO | E10: PRIMARY | F10: Q1 | G10: Jing Santos | H10: Won | I10: Y | J10: 2026-01-08 | K10: 300000 | L10: 0.9 | M10: 270000 | N10: SO2528, SO2492, SO2508 | O10: 380572 | P10: 2026-01-08 | R10: 126.9% | S10: Fully Converted | W10: Review SO over pipeline | X10: 2026-01-08 | Y10: 2026-02-07 | Z10: 0 | AB10: 2026-02-07 | AC10: SO Linked | AD10: 380572 | AE10: 0 | AF10: Do Not Use - Data Issue | AG10: 2026-05-23 | AI10: =IF(OR($H10="Lost",$H10="Dead"),"Lost",IF($I10<>"Y","Excluded",IF($N10<>"","Converted/Partially Converted",IF($J10="","Watchlist","Active")))) -> Converted/Partially Converted | AJ10: =IF($I10<>"Y","Not Eligible - Excluded",IF(OR($H10="Lost",$H10="Dead"),"Not Eligible - Lost",IF($J10="","Scenario Only - No Close Date",IF($X10="","Scenario Only - No Ship Date",IF($Y10="","Scenario Only - No Cash Date",IF($AM10="Y","Not Eligible - SO Mapping Review","Eligible")))))) -> Not Eligible - SO Mapping Review | AK10: =IF($AJ10="Eligible","Y","N") -> N | AL10: =SUMIFS(SO_Mapping!$F:$F,SO_Mapping!$A:$A,$B10) -> 0 | AM10: =IF(AND($N10<>"",$AL10=0),"Y",IF(ABS($O10-$AL10)>1,"Y","N")) -> Y | AN10: =MAX(0,$K10-$AL10) -> 300000 | AO10: =IF($AK10="Y","Cash eligible",IF($I10<>"Y","Excluded by control flag",IF($J10="","No expected close date",IF($X10="","No ship/invoice timing",IF($Y10="","No cash timing",IF($AM10="Y","SO mapping must be resolved","Review required")))))) -> SO mapping must be resolved | AP10: =IF($AK10="Y",TEXT($Y10,"yyyy-mm-dd"),"")
A11: 14 | B11: DPS-0014 | C11: Pelvic Health (3 SKUs) | D11: HAVEN HEALTH | E11: TURNKEY | F11: Q3 | G11: Jackie King | H11: Open | I11: Y | K11: 340000 | L11: 0.75 | M11: 255000 | Q11: 340000 | R11: 0.0% | S11: Open | W11: OK | Z11: 0 | AC11: No SO Yet | AD11: 0 | AE11: 340000 | AF11: Low - Missing Timing | AG11: 2026-05-23 | AI11: =IF(OR($H11="Lost",$H11="Dead"),"Lost",IF($I11<>"Y","Excluded",IF($N11<>"","Converted/Partially Converted",IF($J11="","Watchlist","Active")))) -> Watchlist | AJ11: =IF($I11<>"Y","Not Eligible - Excluded",IF(OR($H11="Lost",$H11="Dead"),"Not Eligible - Lost",IF($J11="","Scenario Only - No Close Date",IF($X11="","Scenario Only - No Ship Date",IF($Y11="","Scenario Only - No Cash Date",IF($AM11="Y","Not Eligible - SO Mapping Review","Eligible")))))) -> Scenario Only - No Close Date | AK11: =IF($AJ11="Eligible","Y","N") -> N | AL11: =SUMIFS(SO_Mapping!$F:$F,SO_Mapping!$A:$A,$B11) -> 0 | AM11: =IF(AND($N11<>"",$AL11=0),"Y",IF(ABS($O11-$AL11)>1,"Y","N")) -> N | AN11: =MAX(0,$K11-$AL11) -> 340000 | AO11: =IF($AK11="Y","Cash eligible",IF($I11<>"Y","Excluded by control flag",IF($J11="","No expected close date",IF($X11="","No ship/invoice timing",IF($Y11="","No cash timing",IF($AM11="Y","SO mapping must be resolved","Review required")))))) -> No expected close date | AP11: =IF($AK11="Y",TEXT($Y11,"yyyy-mm-dd"),"")
A12: 15 | B12: DPS-0015 | C12: SDJ GEN Z BAGS | D12: SDJ | E12: SOFT GOODS | F12: Q4 | G12: Danny Park | H12: Open | I12: Y | K12: 300000 | L12: 0.8 | M12: 240000 | Q12: 300000 | R12: 0.0% | S12: Open | W12: OK | Z12: 0 | AC12: No SO Yet | AD12: 0 | AE12: 300000 | AF12: Low - Missing Timing | AG12: 2026-05-23 | AI12: =IF(OR($H12="Lost",$H12="Dead"),"Lost",IF($I12<>"Y","Excluded",IF($N12<>"","Converted/Partially Converted",IF($J12="","Watchlist","Active")))) -> Watchlist | AJ12: =IF($I12<>"Y","Not Eligible - Excluded",IF(OR($H12="Lost",$H12="Dead"),"Not Eligible - Lost",IF($J12="","Scenario Only - No Close Date",IF($X12="","Scenario Only - No Ship Date",IF($Y12="","Scenario Only - No Cash Date",IF($AM12="Y","Not Eligible - SO Mapping Review","Eligible")))))) -> Scenario Only - No Close Date | AK12: =IF($AJ12="Eligible","Y","N") -> N | AL12: =SUMIFS(SO_Mapping!$F:$F,SO_Mapping!$A:$A,$B12) -> 0 | AM12: =IF(AND($N12<>"",$AL12=0),"Y",IF(ABS($O12-$AL12)>1,"Y","N")) -> N | AN12: =MAX(0,$K12-$AL12) -> 300000 | AO12: =IF($AK12="Y","Cash eligible",IF($I12<>"Y","Excluded by control flag",IF($J12="","No expected close date",IF($X12="","No ship/invoice timing",IF($Y12="","No cash timing",IF($AM12="Y","SO mapping must be resolved","Review required")))))) -> No expected close date | AP12: =IF($AK12="Y",TEXT($Y12,"yyyy-mm-dd"),"")
A13: 16 | B13: DPS-0016 | C13: Pattern Hair Care Line | D13: PATTERN | E13: PRIMARY | F13: Q4 | G13: Jing Santos | H13: Open | I13: Y | K13: 300000 | L13: 0.75 | M13: 225000 | Q13: 300000 | R13: 0.0% | S13: Open | W13: OK | Z13: 0 | AC13: No SO Yet | AD13: 0 | AE13: 300000 | AF13: Low - Missing Timing | AG13: 2026-05-23 | AI13: =IF(OR($H13="Lost",$H13="Dead"),"Lost",IF($I13<>"Y","Excluded",IF($N13<>"","Converted/Partially Converted",IF($J13="","Watchlist","Active")))) -> Watchlist | AJ13: =IF($I13<>"Y","Not Eligible - Excluded",IF(OR($H13="Lost",$H13="Dead"),"Not Eligible - Lost",IF($J13="","Scenario Only - No Close Date",IF($X13="","Scenario Only - No Ship Date",IF($Y13="","Scenario Only - No Cash Date",IF($AM13="Y","Not Eligible - SO Mapping Review","Eligible")))))) -> Scenario Only - No Close Date | AK13: =IF($AJ13="Eligible","Y","N") -> N | AL13: =SUMIFS(SO_Mapping!$F:$F,SO_Mapping!$A:$A,$B13) -> 0 | AM13: =IF(AND($N13<>"",$AL13=0),"Y",IF(ABS($O13-$AL13)>1,"Y","N")) -> N | AN13: =MAX(0,$K13-$AL13) -> 300000 | AO13: =IF($AK13="Y","Cash eligible",IF($I13<>"Y","Excluded by control flag",IF($J13="","No expected close date",IF($X13="","No ship/invoice timing",IF($Y13="","No cash timing",IF($AM13="Y","SO mapping must be resolved","Review required")))))) -> No expected close date | AP13: =IF($AK13="Y",TEXT($Y13,"yyyy-mm-dd"),"")
A14: 17 | B14: DPS-0017 | C14: COLOGNE BOXES - Replenishment | D14: DRSQ | E14: SECONDARY | F14: Q4 | G14: Danny Park | H14: Won | I14: Y | J14: 2026-05-13 | K14: 241000 | L14: 0.75 | M14: 180750 | N14: SO2605 | O14: 104760 | P14: 2026-05-13 | Q14: 136240 | R14: 43.5% | S14: Partially Converted | W14: OK | X14: 2026-05-13 | Y14: 2026-06-12 | Z14: 0 | AB14: 2026-06-12 | AC14: SO Linked | AD14: 104760 | AE14: 136240 | AF14: High - SO Supported | AG14: 2026-05-23 | AI14: =IF(OR($H14="Lost",$H14="Dead"),"Lost",IF($I14<>"Y","Excluded",IF($N14<>"","Converted/Partially Converted",IF($J14="","Watchlist","Active")))) -> Converted/Partially Converted | AJ14: =IF($I14<>"Y","Not Eligible - Excluded",IF(OR($H14="Lost",$H14="Dead"),"Not Eligible - Lost",IF($J14="","Scenario Only - No Close Date",IF($X14="","Scenario Only - No Ship Date",IF($Y14="","Scenario Only - No Cash Date",IF($AM14="Y","Not Eligible - SO Mapping Review","Eligible")))))) -> Eligible | AK14: =IF($AJ14="Eligible","Y","N") -> Y | AL14: =SUMIFS(SO_Mapping!$F:$F,SO_Mapping!$A:$A,$B14) -> 104760 | AM14: =IF(AND($N14<>"",$AL14=0),"Y",IF(ABS($O14-$AL14)>1,"Y","N")) -> N | AN14: =MAX(0,$K14-$AL14) -> 136240 | AO14: =IF($AK14="Y","Cash eligible",IF($I14<>"Y","Excluded by control flag",IF($J14="","No expected close date",IF($X14="","No ship/invoice timing",IF($Y14="","No cash timing",IF($AM14="Y","SO mapping must be resolved","Review required")))))) -> Cash eligible | AP14: =IF($AK14="Y",TEXT($Y14,"yyyy-mm-dd"),"") -> 2026-06-12
A15: 18 | B15: DPS-0018 | C15: RO - Replenishment | D15: RO | E15: PRIMARY | F15: Q2 | G15: Jing Santos | H15: Won | I15: Y | J15: 2026-04-16 | K15: 200000 | L15: 0.9 | M15: 180000 | N15: SO2588 | O15: 88161 | P15: 2026-04-16 | Q15: 111839 | R15: 44.1% | S15: Partially Converted | W15: OK | X15: 2026-04-16 | Y15: 2026-05-16 | Z15: 0 | AB15: 2026-05-16 | AC15: SO Linked | AD15: 88161 | AE15: 111839 | AF15: High - SO Supported | AG15: 2026-05-23 | AI15: =IF(OR($H15="Lost",$H15="Dead"),"Lost",IF($I15<>"Y","Excluded",IF($N15<>"","Converted/Partially Converted",IF($J15="","Watchlist","Active")))) -> Converted/Partially Converted | AJ15: =IF($I15<>"Y","Not Eligible - Excluded",IF(OR($H15="Lost",$H15="Dead"),"Not Eligible - Lost",IF($J15="","Scenario Only - No Close Date",IF($X15="","Scenario Only - No Ship Date",IF($Y15="","Scenario Only - No Cash Date",IF($AM15="Y","Not Eligible - SO Mapping Review","Eligible")))))) -> Eligible | AK15: =IF($AJ15="Eligible","Y","N") -> Y | AL15: =SUMIFS(SO_Mapping!$F:$F,SO_Mapping!$A:$A,$B15) -> 88161 | AM15: =IF(AND($N15<>"",$AL15=0),"Y",IF(ABS($O15-$AL15)>1,"Y","N")) -> N | AN15: =MAX(0,$K15-$AL15) -> 111839 | AO15: =IF($AK15="Y","Cash eligible",IF($I15<>"Y","Excluded by control flag",IF($J15="","No expected close date",IF($X15="","No ship/invoice timing",IF($Y15="","No cash timing",IF($AM15="Y","SO mapping must be resolved","Review required")))))) -> Cash eligible | AP15: =IF($AK15="Y",TEXT($Y15,"yyyy-mm-dd"),"") -> 2026-05-16
A16: 19 | B16: DPS-0019 | C16: RO - Replenishment | D16: RO | E16: PRIMARY | F16: Q3 | G16: Jing Santos | H16: Open | I16: Y | K16: 200000 | L16: 0.9 | M16: 180000 | Q16: 200000 | R16: 0.0% | S16: Open | W16: OK | Z16: 0 | AC16: No SO Yet | AD16: 0 | AE16: 200000 | AF16: Low - Missing Timing | AG16: 2026-05-23 | AI16: =IF(OR($H16="Lost",$H16="Dead"),"Lost",IF($I16<>"Y","Excluded",IF($N16<>"","Converted/Partially Converted",IF($J16="","Watchlist","Active")))) -> Watchlist | AJ16: =IF($I16<>"Y","Not Eligible - Excluded",IF(OR($H16="Lost",$H16="Dead"),"Not Eligible - Lost",IF($J16="","Scenario Only - No Close Date",IF($X16="","Scenario Only - No Ship Date",IF($Y16="","Scenario Only - No Cash Date",IF($AM16="Y","Not Eligible - SO Mapping Review","Eligible")))))) -> Scenario Only - No Close Date | AK16: =IF($AJ16="Eligible","Y","N") -> N | AL16: =SUMIFS(SO_Mapping!$F:$F,SO_Mapping!$A:$A,$B16) -> 0 | AM16: =IF(AND($N16<>"",$AL16=0),"Y",IF(ABS($O16-$AL16)>1,"Y","N")) -> N | AN16: =MAX(0,$K16-$AL16) -> 200000 | AO16: =IF($AK16="Y","Cash eligible",IF($I16<>"Y","Excluded by control flag",IF($J16="","No expected close date",IF($X16="","No ship/invoice timing",IF($Y16="","No cash timing",IF($AM16="Y","SO mapping must be resolved","Review required")))))) -> No expected close date | AP16: =IF($AK16="Y",TEXT($Y16,"yyyy-mm-dd"),"")
A17: 20 | B17: DPS-0020 | C17: Pattern Hair Care Line | D17: PATTERN | E17: PRIMARY | F17: Q3 | G17: Jing Santos | H17: Open | I17: Y | K17: 300000 | L17: 0.5 | M17: 150000 | Q17: 300000 | R17: 0.0% | S17: Open | W17: OK | Z17: 0 | AC17: No SO Yet | AD17: 0 | AE17: 300000 | AF17: Low - Missing Timing | AG17: 2026-05-23 | AI17: =IF(OR($H17="Lost",$H17="Dead"),"Lost",IF($I17<>"Y","Excluded",IF($N17<>"","Converted/Partially Converted",IF($J17="","Watchlist","Active")))) -> Watchlist | AJ17: =IF($I17<>"Y","Not Eligible - Excluded",IF(OR($H17="Lost",$H17="Dead"),"Not Eligible - Lost",IF($J17="","Scenario Only - No Close Date",IF($X17="","Scenario Only - No Ship Date",IF($Y17="","Scenario Only - No Cash Date",IF($AM17="Y","Not Eligible - SO Mapping Review","Eligible")))))) -> Scenario Only - No Close Date | AK17: =IF($AJ17="Eligible","Y","N") -> N | AL17: =SUMIFS(SO_Mapping!$F:$F,SO_Mapping!$A:$A,$B17) -> 0 | AM17: =IF(AND($N17<>"",$AL17=0),"Y",IF(ABS($O17-$AL17)>1,"Y","N")) -> N | AN17: =MAX(0,$K17-$AL17) -> 300000 | AO17: =IF($AK17="Y","Cash eligible",IF($I17<>"Y","Excluded by control flag",IF($J17="","No expected close date",IF($X17="","No ship/invoice timing",IF($Y17="","No cash timing",IF($AM17="Y","SO mapping must be resolved","Review required")))))) -> No expected close date | AP17: =IF($AK17="Y",TEXT($Y17,"yyyy-mm-dd"),"")
A18: 22 | B18: DPS-0022 | C18: SWW - Replenishment | D18: SWW | E18: COPACKING | F18: Q3 | G18: Jackie King | H18: Won | I18: Y | J18: 2026-05-15 | K18: 135000 | L18: 0.9 | M18: 121500 | N18: SO2604 | O18: 69832 | P18: 2026-05-15 | Q18: 65168 | R18: 51.7% | S18: Partially Converted | W18: OK | X18: 2026-05-15 | Y18: 2026-06-14 | Z18: 0 | AB18: 2026-06-14 | AC18: SO Linked | AD18: 69832 | AE18: 65168 | AF18: High - SO Supported | AG18: 2026-05-23 | AI18: =IF(OR($H18="Lost",$H18="Dead"),"Lost",IF($I18<>"Y","Excluded",IF($N18<>"","Converted/Partially Converted",IF($J18="","Watchlist","Active")))) -> Converted/Partially Converted | AJ18: =IF($I18<>"Y","Not Eligible - Excluded",IF(OR($H18="Lost",$H18="Dead"),"Not Eligible - Lost",IF($J18="","Scenario Only - No Close Date",IF($X18="","Scenario Only - No Ship Date",IF($Y18="","Scenario Only - No Cash Date",IF($AM18="Y","Not Eligible - SO Mapping Review","Eligible")))))) -> Eligible | AK18: =IF($AJ18="Eligible","Y","N") -> Y | AL18: =SUMIFS(SO_Mapping!$F:$F,SO_Mapping!$A:$A,$B18) -> 69832 | AM18: =IF(AND($N18<>"",$AL18=0),"Y",IF(ABS($O18-$AL18)>1,"Y","N")) -> N | AN18: =MAX(0,$K18-$AL18) -> 65168 | AO18: =IF($AK18="Y","Cash eligible",IF($I18<>"Y","Excluded by control flag",IF($J18="","No expected close date",IF($X18="","No ship/invoice timing",IF($Y18="","No cash timing",IF($AM18="Y","SO mapping must be resolved","Review required")))))) -> Cash eligible | AP18: =IF($AK18="Y",TEXT($Y18,"yyyy-mm-dd"),"") -> 2026-06-14
A19: 23 | B19: DPS-0023 | C19: SWW - Replenishment | D19: SWW | E19: COPACKING | F19: Q4 | G19: Jackie King | H19: Open | I19: Y | K19: 135000 | L19: 0.9 | M19: 121500 | Q19: 135000 | R19: 0.0% | S19: Open | W19: OK | Z19: 0 | AC19: No SO Yet | AD19: 0 | AE19: 135000 | AF19: Low - Missing Timing | AG19: 2026-05-23 | AI19: =IF(OR($H19="Lost",$H19="Dead"),"Lost",IF($I19<>"Y","Excluded",IF($N19<>"","Converted/Partially Converted",IF($J19="","Watchlist","Active")))) -> Watchlist | AJ19: =IF($I19<>"Y","Not Eligible - Excluded",IF(OR($H19="Lost",$H19="Dead"),"Not Eligible - Lost",IF($J19="","Scenario Only - No Close Date",IF($X19="","Scenario Only - No Ship Date",IF($Y19="","Scenario Only - No Cash Date",IF($AM19="Y","Not Eligible - SO Mapping Review","Eligible")))))) -> Scenario Only - No Close Date | AK19: =IF($AJ19="Eligible","Y","N") -> N | AL19: =SUMIFS(SO_Mapping!$F:$F,SO_Mapping!$A:$A,$B19) -> 0 | AM19: =IF(AND($N19<>"",$AL19=0),"Y",IF(ABS($O19-$AL19)>1,"Y","N")) -> N | AN19: =MAX(0,$K19-$AL19) -> 135000 | AO19: =IF($AK19="Y","Cash eligible",IF($I19<>"Y","Excluded by control flag",IF($J19="","No expected close date",IF($X19="","No ship/invoice timing",IF($Y19="","No cash timing",IF($AM19="Y","SO mapping must be resolved","Review required")))))) -> No expected close date | AP19: =IF($AK19="Y",TEXT($Y19,"yyyy-mm-dd"),"")
A20: 24 | B20: DPS-0024 | C20: Ritual Fragrance Mist | D20: CIRQADIAN | E20: TURNKEY | F20: Q3 | G20: Danny Park | H20: Won | I20: Y | J20: 2026-03-25 | K20: 120000 | L20: 1 | M20: 120000 | N20: SO2527, 2578, 2580, 2581, 2582 | O20: 235494 | P20: 2026-03-25 | R20: 196.2% | S20: Fully Converted | W20: Review SO over pipeline | X20: 2026-03-25 | Y20: 2026-04-24 | Z20: 0 | AB20: 2026-04-24 | AC20: SO Linked | AD20: 235494 | AE20: 0 | AF20: Do Not Use - Data Issue | AG20: 2026-05-23 | AI20: =IF(OR($H20="Lost",$H20="Dead"),"Lost",IF($I20<>"Y","Excluded",IF($N20<>"","Converted/Partially Converted",IF($J20="","Watchlist","Active")))) -> Converted/Partially Converted | AJ20: =IF($I20<>"Y","Not Eligible - Excluded",IF(OR($H20="Lost",$H20="Dead"),"Not Eligible - Lost",IF($J20="","Scenario Only - No Close Date",IF($X20="","Scenario Only - No Ship Date",IF($Y20="","Scenario Only - No Cash Date",IF($AM20="Y","Not Eligible - SO Mapping Review","Eligible")))))) -> Not Eligible - SO Mapping Review | AK20: =IF($AJ20="Eligible","Y","N") -> N | AL20: =SUMIFS(SO_Mapping!$F:$F,SO_Mapping!$A:$A,$B20) -> 0 | AM20: =IF(AND($N20<>"",$AL20=0),"Y",IF(ABS($O20-$AL20)>1,"Y","N")) -> Y | AN20: =MAX(0,$K20-$AL20) -> 120000 | AO20: =IF($AK20="Y","Cash eligible",IF($I20<>"Y","Excluded by control flag",IF($J20="","No expected close date",IF($X20="","No ship/invoice timing",IF($Y20="","No cash timing",IF($AM20="Y","SO mapping must be resolved","Review required")))))) -> SO mapping must be resolved | AP20: =IF($AK20="Y",TEXT($Y20,"yyyy-mm-dd"),"")
A21: 25 | B21: DPS-0025 | C21: COLOGNE BOXES - Replenishment | D21: DRSQ | E21: SOFT GOODS | F21: Q2 | G21: Danny Park | H21: Won | I21: Y | J21: 2026-01-16 | K21: 149215 | L21: 0.75 | M21: 111911 | N21: SO2538 | O21: 149215 | P21: 2026-01-16 | R21: 100.0% | S21: Fully Converted | W21: OK | X21: 2026-01-16 | Y21: 2026-02-15 | Z21: 0 | AB21: 2026-02-15 | AC21: SO Linked | AD21: 149215 | AE21: 0 | AF21: High - SO Supported | AG21: 2026-05-23 | AI21: =IF(OR($H21="Lost",$H21="Dead"),"Lost",IF($I21<>"Y","Excluded",IF($N21<>"","Converted/Partially Converted",IF($J21="","Watchlist","Active")))) -> Converted/Partially Converted | AJ21: =IF($I21<>"Y","Not Eligible - Excluded",IF(OR($H21="Lost",$H21="Dead"),"Not Eligible - Lost",IF($J21="","Scenario Only - No Close Date",IF($X21="","Scenario Only - No Ship Date",IF($Y21="","Scenario Only - No Cash Date",IF($AM21="Y","Not Eligible - SO Mapping Review","Eligible")))))) -> Eligible | AK21: =IF($AJ21="Eligible","Y","N") -> Y | AL21: =SUMIFS(SO_Mapping!$F:$F,SO_Mapping!$A:$A,$B21) -> 149215 | AM21: =IF(AND($N21<>"",$AL21=0),"Y",IF(ABS($O21-$AL21)>1,"Y","N")) -> N | AN21: =MAX(0,$K21-$AL21) -> 0 | AO21: =IF($AK21="Y","Cash eligible",IF($I21<>"Y","Excluded by control flag",IF($J21="","No expected close date",IF($X21="","No ship/invoice timing",IF($Y21="","No cash timing",IF($AM21="Y","SO mapping must be resolved","Review required")))))) -> Cash eligible | AP21: =IF($AK21="Y",TEXT($Y21,"yyyy-mm-dd"),"") -> 2026-02-15
A22: 26 | B22: DPS-0026 | C22: KONJAC JELLY | D22: TEVIS | E22: TURNKEY | F22: Q3 | G22: Jackie King | H22: Open | I22: Y | K22: 200000 | L22: 0.5 | M22: 100000 | Q22: 200000 | R22: 0.0% | S22: Open | W22: OK | Z22: 0 | AC22: No SO Yet | AD22: 0 | AE22: 200000 | AF22: Low - Missing Timing | AG22: 2026-05-23 | AI22: =IF(OR($H22="Lost",$H22="Dead"),"Lost",IF($I22<>"Y","Excluded",IF($N22<>"","Converted/Partially Converted",IF($J22="","Watchlist","Active")))) -> Watchlist | AJ22: =IF($I22<>"Y","Not Eligible - Excluded",IF(OR($H22="Lost",$H22="Dead"),"Not Eligible - Lost",IF($J22="","Scenario Only - No Close Date",IF($X22="","Scenario Only - No Ship Date",IF($Y22="","Scenario Only - No Cash Date",IF($AM22="Y","Not Eligible - SO Mapping Review","Eligible")))))) -> Scenario Only - No Close Date | AK22: =IF($AJ22="Eligible","Y","N") -> N | AL22: =SUMIFS(SO_Mapping!$F:$F,SO_Mapping!$A:$A,$B22) -> 0 | AM22: =IF(AND($N22<>"",$AL22=0),"Y",IF(ABS($O22-$AL22)>1,"Y","N")) -> N | AN22: =MAX(0,$K22-$AL22) -> 200000 | AO22: =IF($AK22="Y","Cash eligible",IF($I22<>"Y","Excluded by control flag",IF($J22="","No expected close date",IF($X22="","No ship/invoice timing",IF($Y22="","No cash timing",IF($AM22="Y","SO mapping must be resolved","Review required")))))) -> No expected close date | AP22: =IF($AK22="Y",TEXT($Y22,"yyyy-mm-dd"),"")
A23: 27 | B23: DPS-0027 | C23: BRAIN MD - Replenishment | D23: BRAIN MD | E23: TURNKEY | F23: Q2 | G23: Jackie King | H23: Won | I23: Y | J23: 2026-01-01 | K23: 100000 | L23: 0.9 | M23: 90000 | N23: SO2525, 2511 | O23: 129603 | P23: 2026-01-01 | R23: 129.6% | S23: Fully Converted | W23: Review SO over pipeline | X23: 2026-01-01 | Y23: 2026-01-31 | Z23: 0 | AB23: 2026-01-31 | AC23: SO Linked | AD23: 129603 | AE23: 0 | AF23: Do Not Use - Data Issue | AG23: 2026-05-23 | AI23: =IF(OR($H23="Lost",$H23="Dead"),"Lost",IF($I23<>"Y","Excluded",IF($N23<>"","Converted/Partially Converted",IF($J23="","Watchlist","Active")))) -> Converted/Partially Converted | AJ23: =IF($I23<>"Y","Not Eligible - Excluded",IF(OR($H23="Lost",$H23="Dead"),"Not Eligible - Lost",IF($J23="","Scenario Only - No Close Date",IF($X23="","Scenario Only - No Ship Date",IF($Y23="","Scenario Only - No Cash Date",IF($AM23="Y","Not Eligible - SO Mapping Review","Eligible")))))) -> Not Eligible - SO Mapping Review | AK23: =IF($AJ23="Eligible","Y","N") -> N | AL23: =SUMIFS(SO_Mapping!$F:$F,SO_Mapping!$A:$A,$B23) -> 0 | AM23: =IF(AND($N23<>"",$AL23=0),"Y",IF(ABS($O23-$AL23)>1,"Y","N")) -> Y | AN23: =MAX(0,$K23-$AL23) -> 100000 | AO23: =IF($AK23="Y","Cash eligible",IF($I23<>"Y","Excluded by control flag",IF($J23="","No expected close date",IF($X23="","No ship/invoice timing",IF($Y23="","No cash timing",IF($AM23="Y","SO mapping must be resolved","Review required")))))) -> SO mapping must be resolved | AP23: =IF($AK23="Y",TEXT($Y23,"yyyy-mm-dd"),"")
A24: 28 | B24: DPS-0028 | C24: BRAIN MD - Replenishment | D24: BRAIN MD | E24: TURNKEY | F24: Q3 | G24: Jackie King | H24: Open | I24: Y | K24: 100000 | L24: 0.9 | M24: 90000 | Q24: 100000 | R24: 0.0% | S24: Open | W24: OK | Z24: 0 | AC24: No SO Yet | AD24: 0 | AE24: 100000 | AF24: Low - Missing Timing | AG24: 2026-05-23 | AI24: =IF(OR($H24="Lost",$H24="Dead"),"Lost",IF($I24<>"Y","Excluded",IF($N24<>"","Converted/Partially Converted",IF($J24="","Watchlist","Active")))) -> Watchlist | AJ24: =IF($I24<>"Y","Not Eligible - Excluded",IF(OR($H24="Lost",$H24="Dead"),"Not Eligible - Lost",IF($J24="","Scenario Only - No Close Date",IF($X24="","Scenario Only - No Ship Date",IF($Y24="","Scenario Only - No Cash Date",IF($AM24="Y","Not Eligible - SO Mapping Review","Eligible")))))) -> Scenario Only - No Close Date | AK24: =IF($AJ24="Eligible","Y","N") -> N | AL24: =SUMIFS(SO_Mapping!$F:$F,SO_Mapping!$A:$A,$B24) -> 0 | AM24: =IF(AND($N24<>"",$AL24=0),"Y",IF(ABS($O24-$AL24)>1,"Y","N")) -> N | AN24: =MAX(0,$K24-$AL24) -> 100000 | AO24: =IF($AK24="Y","Cash eligible",IF($I24<>"Y","Excluded by control flag",IF($J24="","No expected close date",IF($X24="","No ship/invoice timing",IF($Y24="","No cash timing",IF($AM24="Y","SO mapping must be resolved","Review required")))))) -> No expected close date | AP24: =IF($AK24="Y",TEXT($Y24,"yyyy-mm-dd"),"")
A25: 29 | B25: DPS-0029 | C25: Pattern - Replenishment | D25: PATTERN | E25: PRIMARY | F25: Q2 | G25: Jing Santos | H25: Open | I25: Y | K25: 90000 | L25: 0.9 | M25: 81000 | Q25: 90000 | R25: 0.0% | S25: Open | W25: OK | Z25: 0 | AC25: No SO Yet | AD25: 0 | AE25: 90000 | AF25: Low - Missing Timing | AG25: 2026-05-23 | AI25: =IF(OR($H25="Lost",$H25="Dead"),"Lost",IF($I25<>"Y","Excluded",IF($N25<>"","Converted/Partially Converted",IF($J25="","Watchlist","Active")))) -> Watchlist | AJ25: =IF($I25<>"Y","Not Eligible - Excluded",IF(OR($H25="Lost",$H25="Dead"),"Not Eligible - Lost",IF($J25="","Scenario Only - No Close Date",IF($X25="","Scenario Only - No Ship Date",IF($Y25="","Scenario Only - No Cash Date",IF($AM25="Y","Not Eligible - SO Mapping Review","Eligible")))))) -> Scenario Only - No Close Date | AK25: =IF($AJ25="Eligible","Y","N") -> N | AL25: =SUMIFS(SO_Mapping!$F:$F,SO_Mapping!$A:$A,$B25) -> 0 | AM25: =IF(AND($N25<>"",$AL25=0),"Y",IF(ABS($O25-$AL25)>1,"Y","N")) -> N | AN25: =MAX(0,$K25-$AL25) -> 90000 | AO25: =IF($AK25="Y","Cash eligible",IF($I25<>"Y","Excluded by control flag",IF($J25="","No expected close date",IF($X25="","No ship/invoice timing",IF($Y25="","No cash timing",IF($AM25="Y","SO mapping must be resolved","Review required")))))) -> No expected close date | AP25: =IF($AK25="Y",TEXT($Y25,"yyyy-mm-dd"),"")
A26: 30 | B26: DPS-0030 | C26: Pattern - Replenishment | D26: PATTERN | E26: PRIMARY | F26: Q3 | G26: Jing Santos | H26: Open | I26: Y | K26: 90000 | L26: 0.9 | M26: 81000 | Q26: 90000 | R26: 0.0% | S26: Open | W26: OK | Z26: 0 | AC26: No SO Yet | AD26: 0 | AE26: 90000 | AF26: Low - Missing Timing | AG26: 2026-05-23 | AI26: =IF(OR($H26="Lost",$H26="Dead"),"Lost",IF($I26<>"Y","Excluded",IF($N26<>"","Converted/Partially Converted",IF($J26="","Watchlist","Active")))) -> Watchlist | AJ26: =IF($I26<>"Y","Not Eligible - Excluded",IF(OR($H26="Lost",$H26="Dead"),"Not Eligible - Lost",IF($J26="","Scenario Only - No Close Date",IF($X26="","Scenario Only - No Ship Date",IF($Y26="","Scenario Only - No Cash Date",IF($AM26="Y","Not Eligible - SO Mapping Review","Eligible")))))) -> Scenario Only - No Close Date | AK26: =IF($AJ26="Eligible","Y","N") -> N | AL26: =SUMIFS(SO_Mapping!$F:$F,SO_Mapping!$A:$A,$B26) -> 0 | AM26: =IF(AND($N26<>"",$AL26=0),"Y",IF(ABS($O26-$AL26)>1,"Y","N")) -> N | AN26: =MAX(0,$K26-$AL26) -> 90000 | AO26: =IF($AK26="Y","Cash eligible",IF($I26<>"Y","Excluded by control flag",IF($J26="","No expected close date",IF($X26="","No ship/invoice timing",IF($Y26="","No cash timing",IF($AM26="Y","SO mapping must be resolved","Review required")))))) -> No expected close date | AP26: =IF($AK26="Y",TEXT($Y26,"yyyy-mm-dd"),"")
A27: 31 | B27: DPS-0031 | C27: Pattern - Replenishment | D27: PATTERN | E27: PRIMARY | F27: Q4 | G27: Jing Santos | H27: Open | I27: Y | K27: 90000 | L27: 0.9 | M27: 81000 | Q27: 90000 | R27: 0.0% | S27: Open | W27: OK | Z27: 0 | AC27: No SO Yet | AD27: 0 | AE27: 90000 | AF27: Low - Missing Timing | AG27: 2026-05-23 | AI27: =IF(OR($H27="Lost",$H27="Dead"),"Lost",IF($I27<>"Y","Excluded",IF($N27<>"","Converted/Partially Converted",IF($J27="","Watchlist","Active")))) -> Watchlist | AJ27: =IF($I27<>"Y","Not Eligible - Excluded",IF(OR($H27="Lost",$H27="Dead"),"Not Eligible - Lost",IF($J27="","Scenario Only - No Close Date",IF($X27="","Scenario Only - No Ship Date",IF($Y27="","Scenario Only - No Cash Date",IF($AM27="Y","Not Eligible - SO Mapping Review","Eligible")))))) -> Scenario Only - No Close Date | AK27: =IF($AJ27="Eligible","Y","N") -> N | AL27: =SUMIFS(SO_Mapping!$F:$F,SO_Mapping!$A:$A,$B27) -> 0 | AM27: =IF(AND($N27<>"",$AL27=0),"Y",IF(ABS($O27-$AL27)>1,"Y","N")) -> N | AN27: =MAX(0,$K27-$AL27) -> 90000 | AO27: =IF($AK27="Y","Cash eligible",IF($I27<>"Y","Excluded by control flag",IF($J27="","No expected close date",IF($X27="","No ship/invoice timing",IF($Y27="","No cash timing",IF($AM27="Y","SO mapping must be resolved","Review required")))))) -> No expected close date | AP27: =IF($AK27="Y",TEXT($Y27,"yyyy-mm-dd"),"")
A28: 32 | B28: DPS-0032 | C28: I&R - Replenishment | D28: I&R | E28: PRIMARY | F28: Q2 | G28: Jing Santos | H28: Won | I28: Y | J28: 2026-01-01 | K28: 90000 | L28: 0.9 | M28: 81000 | N28: SO2509, 2566 | O28: 102846.84 | P28: 2026-01-01 | R28: 114.3% | S28: Fully Converted | W28: OK | X28: 2026-01-01 | Y28: 2026-01-31 | Z28: 0 | AB28: 2026-01-31 | AC28: SO Linked | AD28: 102846.84 | AE28: 0 | AF28: High - SO Supported | AG28: 2026-05-23 | AI28: =IF(OR($H28="Lost",$H28="Dead"),"Lost",IF($I28<>"Y","Excluded",IF($N28<>"","Converted/Partially Converted",IF($J28="","Watchlist","Active")))) -> Converted/Partially Converted | AJ28: =IF($I28<>"Y","Not Eligible - Excluded",IF(OR($H28="Lost",$H28="Dead"),"Not Eligible - Lost",IF($J28="","Scenario Only - No Close Date",IF($X28="","Scenario Only - No Ship Date",IF($Y28="","Scenario Only - No Cash Date",IF($AM28="Y","Not Eligible - SO Mapping Review","Eligible")))))) -> Not Eligible - SO Mapping Review | AK28: =IF($AJ28="Eligible","Y","N") -> N | AL28: =SUMIFS(SO_Mapping!$F:$F,SO_Mapping!$A:$A,$B28) -> 0 | AM28: =IF(AND($N28<>"",$AL28=0),"Y",IF(ABS($O28-$AL28)>1,"Y","N")) -> Y | AN28: =MAX(0,$K28-$AL28) -> 90000 | AO28: =IF($AK28="Y","Cash eligible",IF($I28<>"Y","Excluded by control flag",IF($J28="","No expected close date",IF($X28="","No ship/invoice timing",IF($Y28="","No cash timing",IF($AM28="Y","SO mapping must be resolved","Review required")))))) -> SO mapping must be resolved | AP28: =IF($AK28="Y",TEXT($Y28,"yyyy-mm-dd"),"")
A29: 33 | B29: DPS-0033 | C29: I&R - Replenishment | D29: I&R | E29: PRIMARY | F29: Q2 | G29: Jing Santos | H29: Lost | I29: Y | K29: 90000 | L29: 0.9 | M29: 81000 | Q29: 90000 | R29: 0.0% | S29: Lost | W29: OK | Z29: 0 | AC29: No SO Yet | AD29: 0 | AE29: 90000 | AF29: Low - Missing Timing | AG29: 2026-05-23 | AI29: =IF(OR($H29="Lost",$H29="Dead"),"Lost",IF($I29<>"Y","Excluded",IF($N29<>"","Converted/Partially Converted",IF($J29="","Watchlist","Active")))) -> Lost | AJ29: =IF($I29<>"Y","Not Eligible - Excluded",IF(OR($H29="Lost",$H29="Dead"),"Not Eligible - Lost",IF($J29="","Scenario Only - No Close Date",IF($X29="","Scenario Only - No Ship Date",IF($Y29="","Scenario Only - No Cash Date",IF($AM29="Y","Not Eligible - SO Mapping Review","Eligible")))))) -> Not Eligible - Lost | AK29: =IF($AJ29="Eligible","Y","N") -> N | AL29: =SUMIFS(SO_Mapping!$F:$F,SO_Mapping!$A:$A,$B29) -> 0 | AM29: =IF(AND($N29<>"",$AL29=0),"Y",IF(ABS($O29-$AL29)>1,"Y","N")) -> N | AN29: =MAX(0,$K29-$AL29) -> 90000 | AO29: =IF($AK29="Y","Cash eligible",IF($I29<>"Y","Excluded by control flag",IF($J29="","No expected close date",IF($X29="","No ship/invoice timing",IF($Y29="","No cash timing",IF($AM29="Y","SO mapping must be resolved","Review required")))))) -> No expected close date | AP29: =IF($AK29="Y",TEXT($Y29,"yyyy-mm-dd"),"")
A30: 34 | B30: DPS-0034 | C30: I&R - Replenishment | D30: I&R | E30: PRIMARY | F30: Q3 | G30: Jing Santos | H30: Open | I30: Y | K30: 90000 | L30: 0.9 | M30: 81000 | Q30: 90000 | R30: 0.0% | S30: Open | W30: OK | Z30: 0 | AC30: No SO Yet | AD30: 0 | AE30: 90000 | AF30: Low - Missing Timing | AG30: 2026-05-23 | AI30: =IF(OR($H30="Lost",$H30="Dead"),"Lost",IF($I30<>"Y","Excluded",IF($N30<>"","Converted/Partially Converted",IF($J30="","Watchlist","Active")))) -> Watchlist | AJ30: =IF($I30<>"Y","Not Eligible - Excluded",IF(OR($H30="Lost",$H30="Dead"),"Not Eligible - Lost",IF($J30="","Scenario Only - No Close Date",IF($X30="","Scenario Only - No Ship Date",IF($Y30="","Scenario Only - No Cash Date",IF($AM30="Y","Not Eligible - SO Mapping Review","Eligible")))))) -> Scenario Only - No Close Date | AK30: =IF($AJ30="Eligible","Y","N") -> N | AL30: =SUMIFS(SO_Mapping!$F:$F,SO_Mapping!$A:$A,$B30) -> 0 | AM30: =IF(AND($N30<>"",$AL30=0),"Y",IF(ABS($O30-$AL30)>1,"Y","N")) -> N | AN30: =MAX(0,$K30-$AL30) -> 90000 | AO30: =IF($AK30="Y","Cash eligible",IF($I30<>"Y","Excluded by control flag",IF($J30="","No expected close date",IF($X30="","No ship/invoice timing",IF($Y30="","No cash timing",IF($AM30="Y","SO mapping must be resolved","Review required")))))) -> No expected close date | AP30: =IF($AK30="Y",TEXT($Y30,"yyyy-mm-dd"),"")
A31: 35 | B31: DPS-0035 | C31: I&R - Replenishment | D31: I&R | E31: PRIMARY | F31: Q4 | G31: Jing Santos | H31: Open | I31: Y | K31: 90000 | L31: 0.9 | M31: 81000 | Q31: 90000 | R31: 0.0% | S31: Open | W31: OK | Z31: 0 | AC31: No SO Yet | AD31: 0 | AE31: 90000 | AF31: Low - Missing Timing | AG31: 2026-05-23 | AI31: =IF(OR($H31="Lost",$H31="Dead"),"Lost",IF($I31<>"Y","Excluded",IF($N31<>"","Converted/Partially Converted",IF($J31="","Watchlist","Active")))) -> Watchlist | AJ31: =IF($I31<>"Y","Not Eligible - Excluded",IF(OR($H31="Lost",$H31="Dead"),"Not Eligible - Lost",IF($J31="","Scenario Only - No Close Date",IF($X31="","Scenario Only - No Ship Date",IF($Y31="","Scenario Only - No Cash Date",IF($AM31="Y","Not Eligible - SO Mapping Review","Eligible")))))) -> Scenario Only - No Close Date | AK31: =IF($AJ31="Eligible","Y","N") -> N | AL31: =SUMIFS(SO_Mapping!$F:$F,SO_Mapping!$A:$A,$B31) -> 0 | AM31: =IF(AND($N31<>"",$AL31=0),"Y",IF(ABS($O31-$AL31)>1,"Y","N")) -> N | AN31: =MAX(0,$K31-$AL31) -> 90000 | AO31: =IF($AK31="Y","Cash eligible",IF($I31<>"Y","Excluded by control flag",IF($J31="","No expected close date",IF($X31="","No ship/invoice timing",IF($Y31="","No cash timing",IF($AM31="Y","SO mapping must be resolved","Review required")))))) -> No expected close date | AP31: =IF($AK31="Y",TEXT($Y31,"yyyy-mm-dd"),"")
A32: 36 | B32: DPS-0036 | C32: SWW - Replenishment | D32: SWW | E32: COPACKING | F32: Q2 | G32: Jackie King | H32: Won | I32: Y | J32: 2026-02-11 | K32: 85000 | L32: 0.9 | M32: 76500 | N32: SO2560 | O32: 33908.75 | P32: 2026-02-11 | Q32: 51091 | R32: 39.9% | S32: Partially Converted | W32: OK | X32: 2026-02-11 | Y32: 2026-03-13 | Z32: 0 | AB32: 2026-03-13 | AC32: SO Linked | AD32: 33908.75 | AE32: 51091.25 | AF32: High - SO Supported | AG32: 2026-05-23 | AI32: =IF(OR($H32="Lost",$H32="Dead"),"Lost",IF($I32<>"Y","Excluded",IF($N32<>"","Converted/Partially Converted",IF($J32="","Watchlist","Active")))) -> Converted/Partially Converted | AJ32: =IF($I32<>"Y","Not Eligible - Excluded",IF(OR($H32="Lost",$H32="Dead"),"Not Eligible - Lost",IF($J32="","Scenario Only - No Close Date",IF($X32="","Scenario Only - No Ship Date",IF($Y32="","Scenario Only - No Cash Date",IF($AM32="Y","Not Eligible - SO Mapping Review","Eligible")))))) -> Eligible | AK32: =IF($AJ32="Eligible","Y","N") -> Y | AL32: =SUMIFS(SO_Mapping!$F:$F,SO_Mapping!$A:$A,$B32) -> 33908.75 | AM32: =IF(AND($N32<>"",$AL32=0),"Y",IF(ABS($O32-$AL32)>1,"Y","N")) -> N | AN32: =MAX(0,$K32-$AL32) -> 51091.25 | AO32: =IF($AK32="Y","Cash eligible",IF($I32<>"Y","Excluded by control flag",IF($J32="","No expected close date",IF($X32="","No ship/invoice timing",IF($Y32="","No cash timing",IF($AM32="Y","SO mapping must be resolved","Review required")))))) -> Cash eligible | AP32: =IF($AK32="Y",TEXT($Y32,"yyyy-mm-dd"),"") -> 2026-03-13
A33: 37 | B33: DPS-0037 | C33: 5pk Mini Cologne Kit | D33: DRSQ | E33: SECONDARY | F33: Q3 | G33: Danny Park | H33: Open | I33: Y | K33: 150000 | L33: 0.5 | M33: 75000 | Q33: 150000 | R33: 0.0% | S33: Open | W33: OK | Z33: 0 | AC33: No SO Yet | AD33: 0 | AE33: 150000 | AF33: Low - Missing Timing | AG33: 2026-05-23 | AI33: =IF(OR($H33="Lost",$H33="Dead"),"Lost",IF($I33<>"Y","Excluded",IF($N33<>"","Converted/Partially Converted",IF($J33="","Watchlist","Active")))) -> Watchlist | AJ33: =IF($I33<>"Y","Not Eligible - Excluded",IF(OR($H33="Lost",$H33="Dead"),"Not Eligible - Lost",IF($J33="","Scenario Only - No Close Date",IF($X33="","Scenario Only - No Ship Date",IF($Y33="","Scenario Only - No Cash Date",IF($AM33="Y","Not Eligible - SO Mapping Review","Eligible")))))) -> Scenario Only - No Close Date | AK33: =IF($AJ33="Eligible","Y","N") -> N | AL33: =SUMIFS(SO_Mapping!$F:$F,SO_Mapping!$A:$A,$B33) -> 0 | AM33: =IF(AND($N33<>"",$AL33=0),"Y",IF(ABS($O33-$AL33)>1,"Y","N")) -> N | AN33: =MAX(0,$K33-$AL33) -> 150000 | AO33: =IF($AK33="Y","Cash eligible",IF($I33<>"Y","Excluded by control flag",IF($J33="","No expected close date",IF($X33="","No ship/invoice timing",IF($Y33="","No cash timing",IF($AM33="Y","SO mapping must be resolved","Review required")))))) -> No expected close date | AP33: =IF($AK33="Y",TEXT($Y33,"yyyy-mm-dd"),"")
A34: 38 | B34: DPS-0038 | C34: 100ML OTG Cologne | D34: GET W | E34: TURNKEY | F34: Q3 | G34: Jing Santos | H34: Open | I34: Y | K34: 150000 | L34: 0.5 | M34: 75000 | Q34: 150000 | R34: 0.0% | S34: Open | W34: OK | Z34: 0 | AC34: No SO Yet | AD34: 0 | AE34: 150000 | AF34: Low - Missing Timing | AG34: 2026-05-23 | AI34: =IF(OR($H34="Lost",$H34="Dead"),"Lost",IF($I34<>"Y","Excluded",IF($N34<>"","Converted/Partially Converted",IF($J34="","Watchlist","Active")))) -> Watchlist | AJ34: =IF($I34<>"Y","Not Eligible - Excluded",IF(OR($H34="Lost",$H34="Dead"),"Not Eligible - Lost",IF($J34="","Scenario Only - No Close Date",IF($X34="","Scenario Only - No Ship Date",IF($Y34="","Scenario Only - No Cash Date",IF($AM34="Y","Not Eligible - SO Mapping Review","Eligible")))))) -> Scenario Only - No Close Date | AK34: =IF($AJ34="Eligible","Y","N") -> N | AL34: =SUMIFS(SO_Mapping!$F:$F,SO_Mapping!$A:$A,$B34) -> 0 | AM34: =IF(AND($N34<>"",$AL34=0),"Y",IF(ABS($O34-$AL34)>1,"Y","N")) -> N | AN34: =MAX(0,$K34-$AL34) -> 150000 | AO34: =IF($AK34="Y","Cash eligible",IF($I34<>"Y","Excluded by control flag",IF($J34="","No expected close date",IF($X34="","No ship/invoice timing",IF($Y34="","No cash timing",IF($AM34="Y","SO mapping must be resolved","Review required")))))) -> No expected close date | AP34: =IF($AK34="Y",TEXT($Y34,"yyyy-mm-dd"),"")
A35: 39 | B35: DPS-0039 | C35: Sample Pack - Silk Rinse | D35: CECRED | E35: COPACKING | F35: Q2 | G35: Jackie King | H35: Won | I35: Y | J35: 2026-05-11 | K35: 75000 | L35: 0.9 | M35: 67500 | N35: SO2603, 2604 | O35: 27122 | P35: 2026-05-11 | Q35: 47878 | R35: 36.2% | S35: Partially Converted | W35: OK | X35: 2026-05-11 | Y35: 2026-06-10 | Z35: 0 | AB35: 2026-06-10 | AC35: SO Linked | AD35: 27122 | AE35: 47878 | AF35: High - SO Supported | AG35: 2026-05-23 | AI35: =IF(OR($H35="Lost",$H35="Dead"),"Lost",IF($I35<>"Y","Excluded",IF($N35<>"","Converted/Partially Converted",IF($J35="","Watchlist","Active")))) -> Converted/Partially Converted | AJ35: =IF($I35<>"Y","Not Eligible - Excluded",IF(OR($H35="Lost",$H35="Dead"),"Not Eligible - Lost",IF($J35="","Scenario Only - No Close Date",IF($X35="","Scenario Only - No Ship Date",IF($Y35="","Scenario Only - No Cash Date",IF($AM35="Y","Not Eligible - SO Mapping Review","Eligible")))))) -> Not Eligible - SO Mapping Review | AK35: =IF($AJ35="Eligible","Y","N") -> N | AL35: =SUMIFS(SO_Mapping!$F:$F,SO_Mapping!$A:$A,$B35) -> 0 | AM35: =IF(AND($N35<>"",$AL35=0),"Y",IF(ABS($O35-$AL35)>1,"Y","N")) -> Y | AN35: =MAX(0,$K35-$AL35) -> 75000 | AO35: =IF($AK35="Y","Cash eligible",IF($I35<>"Y","Excluded by control flag",IF($J35="","No expected close date",IF($X35="","No ship/invoice timing",IF($Y35="","No cash timing",IF($AM35="Y","SO mapping must be resolved","Review required")))))) -> SO mapping must be resolved | AP35: =IF($AK35="Y",TEXT($Y35,"yyyy-mm-dd"),"")
A36: 40 | B36: DPS-0040 | C36: Ritual Fragrance Mist | D36: CIRQADIAN | E36: TURNKEY | F36: Q4 | G36: Danny Park | H36: Open | I36: Y | K36: 120000 | L36: 0.5 | M36: 60000 | Q36: 120000 | R36: 0.0% | S36: Open | W36: OK | Z36: 0 | AC36: No SO Yet | AD36: 0 | AE36: 120000 | AF36: Low - Missing Timing | AG36: 2026-05-23 | AI36: =IF(OR($H36="Lost",$H36="Dead"),"Lost",IF($I36<>"Y","Excluded",IF($N36<>"","Converted/Partially Converted",IF($J36="","Watchlist","Active")))) -> Watchlist | AJ36: =IF($I36<>"Y","Not Eligible - Excluded",IF(OR($H36="Lost",$H36="Dead"),"Not Eligible - Lost",IF($J36="","Scenario Only - No Close Date",IF($X36="","Scenario Only - No Ship Date",IF($Y36="","Scenario Only - No Cash Date",IF($AM36="Y","Not Eligible - SO Mapping Review","Eligible")))))) -> Scenario Only - No Close Date | AK36: =IF($AJ36="Eligible","Y","N") -> N | AL36: =SUMIFS(SO_Mapping!$F:$F,SO_Mapping!$A:$A,$B36) -> 0 | AM36: =IF(AND($N36<>"",$AL36=0),"Y",IF(ABS($O36-$AL36)>1,"Y","N")) -> N | AN36: =MAX(0,$K36-$AL36) -> 120000 | AO36: =IF($AK36="Y","Cash eligible",IF($I36<>"Y","Excluded by control flag",IF($J36="","No expected close date",IF($X36="","No ship/invoice timing",IF($Y36="","No cash timing",IF($AM36="Y","SO mapping must be resolved","Review required")))))) -> No expected close date | AP36: =IF($AK36="Y",TEXT($Y36,"yyyy-mm-dd"),"")
A37: 41 | B37: DPS-0041 | C37: SWW - Replenishment | D37: SWW | E37: COPACKING | F37: Q1 | G37: Jackie King | H37: Won | I37: Y | J37: 2026-02-25 | K37: 60000 | L37: 0.85 | M37: 51000 | N37: SO2565 | O37: 61098 | P37: 2026-02-25 | R37: 101.8% | S37: Fully Converted | W37: OK | X37: 2026-02-25 | Y37: 2026-03-27 | Z37: 0 | AB37: 2026-03-27 | AC37: SO Linked | AD37: 61098 | AE37: 0 | AF37: High - SO Supported | AG37: 2026-05-23 | AI37: =IF(OR($H37="Lost",$H37="Dead"),"Lost",IF($I37<>"Y","Excluded",IF($N37<>"","Converted/Partially Converted",IF($J37="","Watchlist","Active")))) -> Converted/Partially Converted | AJ37: =IF($I37<>"Y","Not Eligible - Excluded",IF(OR($H37="Lost",$H37="Dead"),"Not Eligible - Lost",IF($J37="","Scenario Only - No Close Date",IF($X37="","Scenario Only - No Ship Date",IF($Y37="","Scenario Only - No Cash Date",IF($AM37="Y","Not Eligible - SO Mapping Review","Eligible")))))) -> Eligible | AK37: =IF($AJ37="Eligible","Y","N") -> Y | AL37: =SUMIFS(SO_Mapping!$F:$F,SO_Mapping!$A:$A,$B37) -> 61098 | AM37: =IF(AND($N37<>"",$AL37=0),"Y",IF(ABS($O37-$AL37)>1,"Y","N")) -> N | AN37: =MAX(0,$K37-$AL37) -> 0 | AO37: =IF($AK37="Y","Cash eligible",IF($I37<>"Y","Excluded by control flag",IF($J37="","No expected close date",IF($X37="","No ship/invoice timing",IF($Y37="","No cash timing",IF($AM37="Y","SO mapping must be resolved","Review required")))))) -> Cash eligible | AP37: =IF($AK37="Y",TEXT($Y37,"yyyy-mm-dd"),"") -> 2026-03-27
A38: 42 | B38: DPS-0042 | C38: OUAI PET JAR - 250ml | D38: OUAI | E38: PRIMARY | F38: Q4 | G38: Jing Santos | H38: Open | I38: Y | K38: 200000 | L38: 0.25 | M38: 50000 | Q38: 200000 | R38: 0.0% | S38: Open | W38: OK | Z38: 0 | AC38: No SO Yet | AD38: 0 | AE38: 200000 | AF38: Low - Missing Timing | AG38: 2026-05-23 | AI38: =IF(OR($H38="Lost",$H38="Dead"),"Lost",IF($I38<>"Y","Excluded",IF($N38<>"","Converted/Partially Converted",IF($J38="","Watchlist","Active")))) -> Watchlist | AJ38: =IF($I38<>"Y","Not Eligible - Excluded",IF(OR($H38="Lost",$H38="Dead"),"Not Eligible - Lost",IF($J38="","Scenario Only - No Close Date",IF($X38="","Scenario Only - No Ship Date",IF($Y38="","Scenario Only - No Cash Date",IF($AM38="Y","Not Eligible - SO Mapping Review","Eligible")))))) -> Scenario Only - No Close Date | AK38: =IF($AJ38="Eligible","Y","N") -> N | AL38: =SUMIFS(SO_Mapping!$F:$F,SO_Mapping!$A:$A,$B38) -> 0 | AM38: =IF(AND($N38<>"",$AL38=0),"Y",IF(ABS($O38-$AL38)>1,"Y","N")) -> N | AN38: =MAX(0,$K38-$AL38) -> 200000 | AO38: =IF($AK38="Y","Cash eligible",IF($I38<>"Y","Excluded by control flag",IF($J38="","No expected close date",IF($X38="","No ship/invoice timing",IF($Y38="","No cash timing",IF($AM38="Y","SO mapping must be resolved","Review required")))))) -> No expected close date | AP38: =IF($AK38="Y",TEXT($Y38,"yyyy-mm-dd"),"")
A39: 43 | B39: DPS-0043 | C39: MOCKTAIL LINE | D39: BRAIN MD | E39: TURNKEY | F39: Q2 | G39: Jackie King | H39: Open | I39: Y | K39: 200000 | L39: 0.25 | M39: 50000 | Q39: 200000 | R39: 0.0% | S39: Open | W39: OK | Z39: 0 | AC39: No SO Yet | AD39: 0 | AE39: 200000 | AF39: Low - Missing Timing | AG39: 2026-05-23 | AI39: =IF(OR($H39="Lost",$H39="Dead"),"Lost",IF($I39<>"Y","Excluded",IF($N39<>"","Converted/Partially Converted",IF($J39="","Watchlist","Active")))) -> Watchlist | AJ39: =IF($I39<>"Y","Not Eligible - Excluded",IF(OR($H39="Lost",$H39="Dead"),"Not Eligible - Lost",IF($J39="","Scenario Only - No Close Date",IF($X39="","Scenario Only - No Ship Date",IF($Y39="","Scenario Only - No Cash Date",IF($AM39="Y","Not Eligible - SO Mapping Review","Eligible")))))) -> Scenario Only - No Close Date | AK39: =IF($AJ39="Eligible","Y","N") -> N | AL39: =SUMIFS(SO_Mapping!$F:$F,SO_Mapping!$A:$A,$B39) -> 0 | AM39: =IF(AND($N39<>"",$AL39=0),"Y",IF(ABS($O39-$AL39)>1,"Y","N")) -> N | AN39: =MAX(0,$K39-$AL39) -> 200000 | AO39: =IF($AK39="Y","Cash eligible",IF($I39<>"Y","Excluded by control flag",IF($J39="","No expected close date",IF($X39="","No ship/invoice timing",IF($Y39="","No cash timing",IF($AM39="Y","SO mapping must be resolved","Review required")))))) -> No expected close date | AP39: =IF($AK39="Y",TEXT($Y39,"yyyy-mm-dd"),"")
A40: 44 | B40: DPS-0044 | C40: Fiber Pills | D40: MISTR | E40: TURNKEY | F40: Q3 | G40: Jackie King | H40: Open | I40: Y | K40: 50000 | L40: 0.85 | M40: 42500 | Q40: 50000 | R40: 0.0% | S40: Open | W40: OK | Z40: 0 | AC40: No SO Yet | AD40: 0 | AE40: 50000 | AF40: Low - Missing Timing | AG40: 2026-05-23 | AI40: =IF(OR($H40="Lost",$H40="Dead"),"Lost",IF($I40<>"Y","Excluded",IF($N40<>"","Converted/Partially Converted",IF($J40="","Watchlist","Active")))) -> Watchlist | AJ40: =IF($I40<>"Y","Not Eligible - Excluded",IF(OR($H40="Lost",$H40="Dead"),"Not Eligible - Lost",IF($J40="","Scenario Only - No Close Date",IF($X40="","Scenario Only - No Ship Date",IF($Y40="","Scenario Only - No Cash Date",IF($AM40="Y","Not Eligible - SO Mapping Review","Eligible")))))) -> Scenario Only - No Close Date | AK40: =IF($AJ40="Eligible","Y","N") -> N | AL40: =SUMIFS(SO_Mapping!$F:$F,SO_Mapping!$A:$A,$B40) -> 0 | AM40: =IF(AND($N40<>"",$AL40=0),"Y",IF(ABS($O40-$AL40)>1,"Y","N")) -> N | AN40: =MAX(0,$K40-$AL40) -> 50000 | AO40: =IF($AK40="Y","Cash eligible",IF($I40<>"Y","Excluded by control flag",IF($J40="","No expected close date",IF($X40="","No ship/invoice timing",IF($Y40="","No cash timing",IF($AM40="Y","SO mapping must be resolved","Review required")))))) -> No expected close date | AP40: =IF($AK40="Y",TEXT($Y40,"yyyy-mm-dd"),"")
A41: 45 | B41: DPS-0045 | C41: Semen Enhancer Pills | D41: MISTR | E41: TURNKEY | F41: Q3 | G41: Jackie King | H41: Open | I41: Y | K41: 50000 | L41: 0.85 | M41: 42500 | Q41: 50000 | R41: 0.0% | S41: Open | W41: OK | Z41: 0 | AC41: No SO Yet | AD41: 0 | AE41: 50000 | AF41: Low - Missing Timing | AG41: 2026-05-23 | AI41: =IF(OR($H41="Lost",$H41="Dead"),"Lost",IF($I41<>"Y","Excluded",IF($N41<>"","Converted/Partially Converted",IF($J41="","Watchlist","Active")))) -> Watchlist | AJ41: =IF($I41<>"Y","Not Eligible - Excluded",IF(OR($H41="Lost",$H41="Dead"),"Not Eligible - Lost",IF($J41="","Scenario Only - No Close Date",IF($X41="","Scenario Only - No Ship Date",IF($Y41="","Scenario Only - No Cash Date",IF($AM41="Y","Not Eligible - SO Mapping Review","Eligible")))))) -> Scenario Only - No Close Date | AK41: =IF($AJ41="Eligible","Y","N") -> N | AL41: =SUMIFS(SO_Mapping!$F:$F,SO_Mapping!$A:$A,$B41) -> 0 | AM41: =IF(AND($N41<>"",$AL41=0),"Y",IF(ABS($O41-$AL41)>1,"Y","N")) -> N | AN41: =MAX(0,$K41-$AL41) -> 50000 | AO41: =IF($AK41="Y","Cash eligible",IF($I41<>"Y","Excluded by control flag",IF($J41="","No expected close date",IF($X41="","No ship/invoice timing",IF($Y41="","No cash timing",IF($AM41="Y","SO mapping must be resolved","Review required")))))) -> No expected close date | AP41: =IF($AK41="Y",TEXT($Y41,"yyyy-mm-dd"),"")
A42: 46 | B42: DPS-0046 | C42: Rave recovery Pill | D42: MISTR | E42: TURNKEY | F42: Q3 | G42: Jackie King | H42: Open | I42: Y | K42: 50000 | L42: 0.85 | M42: 42500 | Q42: 50000 | R42: 0.0% | S42: Open | W42: OK | Z42: 0 | AC42: No SO Yet | AD42: 0 | AE42: 50000 | AF42: Low - Missing Timing | AG42: 2026-05-23 | AI42: =IF(OR($H42="Lost",$H42="Dead"),"Lost",IF($I42<>"Y","Excluded",IF($N42<>"","Converted/Partially Converted",IF($J42="","Watchlist","Active")))) -> Watchlist | AJ42: =IF($I42<>"Y","Not Eligible - Excluded",IF(OR($H42="Lost",$H42="Dead"),"Not Eligible - Lost",IF($J42="","Scenario Only - No Close Date",IF($X42="","Scenario Only - No Ship Date",IF($Y42="","Scenario Only - No Cash Date",IF($AM42="Y","Not Eligible - SO Mapping Review","Eligible")))))) -> Scenario Only - No Close Date | AK42: =IF($AJ42="Eligible","Y","N") -> N | AL42: =SUMIFS(SO_Mapping!$F:$F,SO_Mapping!$A:$A,$B42) -> 0 | AM42: =IF(AND($N42<>"",$AL42=0),"Y",IF(ABS($O42-$AL42)>1,"Y","N")) -> N | AN42: =MAX(0,$K42-$AL42) -> 50000 | AO42: =IF($AK42="Y","Cash eligible",IF($I42<>"Y","Excluded by control flag",IF($J42="","No expected close date",IF($X42="","No ship/invoice timing",IF($Y42="","No cash timing",IF($AM42="Y","SO mapping must be resolved","Review required")))))) -> No expected close date | AP42: =IF($AK42="Y",TEXT($Y42,"yyyy-mm-dd"),"")
A43: 47 | B43: DPS-0047 | C43: Probiotic Gummy | D43: MISTR | E43: TURNKEY | F43: Q4 | G43: Jackie King | H43: Open | I43: Y | K43: 50000 | L43: 0.85 | M43: 42500 | Q43: 50000 | R43: 0.0% | S43: Open | W43: OK | Z43: 0 | AC43: No SO Yet | AD43: 0 | AE43: 50000 | AF43: Low - Missing Timing | AG43: 2026-05-23 | AI43: =IF(OR($H43="Lost",$H43="Dead"),"Lost",IF($I43<>"Y","Excluded",IF($N43<>"","Converted/Partially Converted",IF($J43="","Watchlist","Active")))) -> Watchlist | AJ43: =IF($I43<>"Y","Not Eligible - Excluded",IF(OR($H43="Lost",$H43="Dead"),"Not Eligible - Lost",IF($J43="","Scenario Only - No Close Date",IF($X43="","Scenario Only - No Ship Date",IF($Y43="","Scenario Only - No Cash Date",IF($AM43="Y","Not Eligible - SO Mapping Review","Eligible")))))) -> Scenario Only - No Close Date | AK43: =IF($AJ43="Eligible","Y","N") -> N | AL43: =SUMIFS(SO_Mapping!$F:$F,SO_Mapping!$A:$A,$B43) -> 0 | AM43: =IF(AND($N43<>"",$AL43=0),"Y",IF(ABS($O43-$AL43)>1,"Y","N")) -> N | AN43: =MAX(0,$K43-$AL43) -> 50000 | AO43: =IF($AK43="Y","Cash eligible",IF($I43<>"Y","Excluded by control flag",IF($J43="","No expected close date",IF($X43="","No ship/invoice timing",IF($Y43="","No cash timing",IF($AM43="Y","SO mapping must be resolved","Review required")))))) -> No expected close date | AP43: =IF($AK43="Y",TEXT($Y43,"yyyy-mm-dd"),"")
A44: 48 | B44: DPS-0048 | C44: OUIA PP Jar 250ml | D44: OUAI | E44: PRIMARY | F44: Q4 | G44: Jing Santos | H44: Open | I44: Y | K44: 150000 | L44: 0.25 | M44: 37500 | Q44: 150000 | R44: 0.0% | S44: Open | W44: OK | Z44: 0 | AC44: No SO Yet | AD44: 0 | AE44: 150000 | AF44: Low - Missing Timing | AG44: 2026-05-23 | AI44: =IF(OR($H44="Lost",$H44="Dead"),"Lost",IF($I44<>"Y","Excluded",IF($N44<>"","Converted/Partially Converted",IF($J44="","Watchlist","Active")))) -> Watchlist | AJ44: =IF($I44<>"Y","Not Eligible - Excluded",IF(OR($H44="Lost",$H44="Dead"),"Not Eligible - Lost",IF($J44="","Scenario Only - No Close Date",IF($X44="","Scenario Only - No Ship Date",IF($Y44="","Scenario Only - No Cash Date",IF($AM44="Y","Not Eligible - SO Mapping Review","Eligible")))))) -> Scenario Only - No Close Date | AK44: =IF($AJ44="Eligible","Y","N") -> N | AL44: =SUMIFS(SO_Mapping!$F:$F,SO_Mapping!$A:$A,$B44) -> 0 | AM44: =IF(AND($N44<>"",$AL44=0),"Y",IF(ABS($O44-$AL44)>1,"Y","N")) -> N | AN44: =MAX(0,$K44-$AL44) -> 150000 | AO44: =IF($AK44="Y","Cash eligible",IF($I44<>"Y","Excluded by control flag",IF($J44="","No expected close date",IF($X44="","No ship/invoice timing",IF($Y44="","No cash timing",IF($AM44="Y","SO mapping must be resolved","Review required")))))) -> No expected close date | AP44: =IF($AK44="Y",TEXT($Y44,"yyyy-mm-dd"),"")
A45: 49 | B45: DPS-0049 | C45: TRAVEL CASE - Replenishment | D45: DRSQ | E45: SOFT GOODS | F45: Q4 | G45: Danny Park | H45: Open | I45: Y | K45: 50000 | L45: 0.75 | M45: 37500 | Q45: 50000 | R45: 0.0% | S45: Open | W45: OK | Z45: 0 | AC45: No SO Yet | AD45: 0 | AE45: 50000 | AF45: Low - Missing Timing | AG45: 2026-05-23 | AI45: =IF(OR($H45="Lost",$H45="Dead"),"Lost",IF($I45<>"Y","Excluded",IF($N45<>"","Converted/Partially Converted",IF($J45="","Watchlist","Active")))) -> Watchlist | AJ45: =IF($I45<>"Y","Not Eligible - Excluded",IF(OR($H45="Lost",$H45="Dead"),"Not Eligible - Lost",IF($J45="","Scenario Only - No Close Date",IF($X45="","Scenario Only - No Ship Date",IF($Y45="","Scenario Only - No Cash Date",IF($AM45="Y","Not Eligible - SO Mapping Review","Eligible")))))) -> Scenario Only - No Close Date | AK45: =IF($AJ45="Eligible","Y","N") -> N | AL45: =SUMIFS(SO_Mapping!$F:$F,SO_Mapping!$A:$A,$B45) -> 0 | AM45: =IF(AND($N45<>"",$AL45=0),"Y",IF(ABS($O45-$AL45)>1,"Y","N")) -> N | AN45: =MAX(0,$K45-$AL45) -> 50000 | AO45: =IF($AK45="Y","Cash eligible",IF($I45<>"Y","Excluded by control flag",IF($J45="","No expected close date",IF($X45="","No ship/invoice timing",IF($Y45="","No cash timing",IF($AM45="Y","SO mapping must be resolved","Review required")))))) -> No expected close date | AP45: =IF($AK45="Y",TEXT($Y45,"yyyy-mm-dd"),"")
A46: 50 | B46: DPS-0050 | C46: LUBE | D46: MISTR | E46: TURNKEY | F46: Q3 | G46: Jackie King | H46: Open | I46: Y | K46: 75000 | L46: 0.5 | M46: 37500 | Q46: 75000 | R46: 0.0% | S46: Open | W46: OK | Z46: 0 | AC46: No SO Yet | AD46: 0 | AE46: 75000 | AF46: Low - Missing Timing | AG46: 2026-05-23 | AI46: =IF(OR($H46="Lost",$H46="Dead"),"Lost",IF($I46<>"Y","Excluded",IF($N46<>"","Converted/Partially Converted",IF($J46="","Watchlist","Active")))) -> Watchlist | AJ46: =IF($I46<>"Y","Not Eligible - Excluded",IF(OR($H46="Lost",$H46="Dead"),"Not Eligible - Lost",IF($J46="","Scenario Only - No Close Date",IF($X46="","Scenario Only - No Ship Date",IF($Y46="","Scenario Only - No Cash Date",IF($AM46="Y","Not Eligible - SO Mapping Review","Eligible")))))) -> Scenario Only - No Close Date | AK46: =IF($AJ46="Eligible","Y","N") -> N | AL46: =SUMIFS(SO_Mapping!$F:$F,SO_Mapping!$A:$A,$B46) -> 0 | AM46: =IF(AND($N46<>"",$AL46=0),"Y",IF(ABS($O46-$AL46)>1,"Y","N")) -> N | AN46: =MAX(0,$K46-$AL46) -> 75000 | AO46: =IF($AK46="Y","Cash eligible",IF($I46<>"Y","Excluded by control flag",IF($J46="","No expected close date",IF($X46="","No ship/invoice timing",IF($Y46="","No cash timing",IF($AM46="Y","SO mapping must be resolved","Review required")))))) -> No expected close date | AP46: =IF($AK46="Y",TEXT($Y46,"yyyy-mm-dd"),"")
A47: 51 | B47: DPS-0051 | C47: Pattern - Replenishment | D47: PATTERN | E47: PRIMARY | F47: Q1 | G47: Jing Santos | H47: Won | I47: Y | J47: 2026-01-01 | K47: 40000 | L47: 0.9 | M47: 36000 | N47: SO2505 | O47: 40275 | P47: 2026-01-01 | R47: 100.7% | S47: Fully Converted | W47: OK | X47: 2026-01-01 | Y47: 2026-01-31 | Z47: 0 | AB47: 2026-01-31 | AC47: SO Linked | AD47: 40275 | AE47: 0 | AF47: High - SO Supported | AG47: 2026-05-23 | AI47: =IF(OR($H47="Lost",$H47="Dead"),"Lost",IF($I47<>"Y","Excluded",IF($N47<>"","Converted/Partially Converted",IF($J47="","Watchlist","Active")))) -> Converted/Partially Converted | AJ47: =IF($I47<>"Y","Not Eligible - Excluded",IF(OR($H47="Lost",$H47="Dead"),"Not Eligible - Lost",IF($J47="","Scenario Only - No Close Date",IF($X47="","Scenario Only - No Ship Date",IF($Y47="","Scenario Only - No Cash Date",IF($AM47="Y","Not Eligible - SO Mapping Review","Eligible")))))) -> Eligible | AK47: =IF($AJ47="Eligible","Y","N") -> Y | AL47: =SUMIFS(SO_Mapping!$F:$F,SO_Mapping!$A:$A,$B47) -> 40275 | AM47: =IF(AND($N47<>"",$AL47=0),"Y",IF(ABS($O47-$AL47)>1,"Y","N")) -> N | AN47: =MAX(0,$K47-$AL47) -> 0 | AO47: =IF($AK47="Y","Cash eligible",IF($I47<>"Y","Excluded by control flag",IF($J47="","No expected close date",IF($X47="","No ship/invoice timing",IF($Y47="","No cash timing",IF($AM47="Y","SO mapping must be resolved","Review required")))))) -> Cash eligible | AP47: =IF($AK47="Y",TEXT($Y47,"yyyy-mm-dd"),"") -> 2026-01-31
A48: 52 | B48: DPS-0052 | C48: TRAVEL CASE - Replenishment | D48: DRSQ | E48: SOFT GOODS | F48: Q1 | G48: Danny Park | H48: Won | I48: Y | J48: 2026-01-01 | K48: 46450 | L48: 0.75 | M48: 34838 | N48: SO2523 | O48: 46450 | P48: 2026-01-01 | R48: 100.0% | S48: Fully Converted | W48: OK | X48: 2026-01-01 | Y48: 2026-01-31 | Z48: 0 | AB48: 2026-01-31 | AC48: SO Linked | AD48: 46450 | AE48: 0 | AF48: High - SO Supported | AG48: 2026-05-23 | AI48: =IF(OR($H48="Lost",$H48="Dead"),"Lost",IF($I48<>"Y","Excluded",IF($N48<>"","Converted/Partially Converted",IF($J48="","Watchlist","Active")))) -> Converted/Partially Converted | AJ48: =IF($I48<>"Y","Not Eligible - Excluded",IF(OR($H48="Lost",$H48="Dead"),"Not Eligible - Lost",IF($J48="","Scenario Only - No Close Date",IF($X48="","Scenario Only - No Ship Date",IF($Y48="","Scenario Only - No Cash Date",IF($AM48="Y","Not Eligible - SO Mapping Review","Eligible")))))) -> Eligible | AK48: =IF($AJ48="Eligible","Y","N") -> Y | AL48: =SUMIFS(SO_Mapping!$F:$F,SO_Mapping!$A:$A,$B48) -> 46450 | AM48: =IF(AND($N48<>"",$AL48=0),"Y",IF(ABS($O48-$AL48)>1,"Y","N")) -> N | AN48: =MAX(0,$K48-$AL48) -> 0 | AO48: =IF($AK48="Y","Cash eligible",IF($I48<>"Y","Excluded by control flag",IF($J48="","No expected close date",IF($X48="","No ship/invoice timing",IF($Y48="","No cash timing",IF($AM48="Y","SO mapping must be resolved","Review required")))))) -> Cash eligible | AP48: =IF($AK48="Y",TEXT($Y48,"yyyy-mm-dd"),"") -> 2026-01-31
A49: 53 | B49: DPS-0053 | C49: Sample Pack - Silk Rinse | D49: CECRED | E49: COPACKING | F49: Q1 | G49: Jackie King | H49: Won | I49: Y | J49: 2026-01-01 | K49: 30000 | L49: 0.9 | M49: 27000 | N49: SO2510 | O49: 63164 | P49: 2026-01-01 | R49: 210.5% | S49: Fully Converted | W49: Review SO over pipeline | X49: 2026-01-01 | Y49: 2026-01-31 | Z49: 0 | AB49: 2026-01-31 | AC49: SO Linked | AD49: 63164 | AE49: 0 | AF49: Do Not Use - Data Issue | AG49: 2026-05-23 | AI49: =IF(OR($H49="Lost",$H49="Dead"),"Lost",IF($I49<>"Y","Excluded",IF($N49<>"","Converted/Partially Converted",IF($J49="","Watchlist","Active")))) -> Converted/Partially Converted | AJ49: =IF($I49<>"Y","Not Eligible - Excluded",IF(OR($H49="Lost",$H49="Dead"),"Not Eligible - Lost",IF($J49="","Scenario Only - No Close Date",IF($X49="","Scenario Only - No Ship Date",IF($Y49="","Scenario Only - No Cash Date",IF($AM49="Y","Not Eligible - SO Mapping Review","Eligible")))))) -> Eligible | AK49: =IF($AJ49="Eligible","Y","N") -> Y | AL49: =SUMIFS(SO_Mapping!$F:$F,SO_Mapping!$A:$A,$B49) -> 63164 | AM49: =IF(AND($N49<>"",$AL49=0),"Y",IF(ABS($O49-$AL49)>1,"Y","N")) -> N | AN49: =MAX(0,$K49-$AL49) -> 0 | AO49: =IF($AK49="Y","Cash eligible",IF($I49<>"Y","Excluded by control flag",IF($J49="","No expected close date",IF($X49="","No ship/invoice timing",IF($Y49="","No cash timing",IF($AM49="Y","SO mapping must be resolved","Review required")))))) -> Cash eligible | AP49: =IF($AK49="Y",TEXT($Y49,"yyyy-mm-dd"),"") -> 2026-01-31
A50: 54 | B50: DPS-0054 | C50: Sample Pack - Silk Rinse | D50: CECRED | E50: COPACKING | F50: Q3 | G50: Jackie King | H50: Open | I50: Y | K50: 30000 | L50: 0.9 | M50: 27000 | Q50: 30000 | R50: 0.0% | S50: Open | W50: OK | Z50: 0 | AC50: No SO Yet | AD50: 0 | AE50: 30000 | AF50: Low - Missing Timing | AG50: 2026-05-23 | AI50: =IF(OR($H50="Lost",$H50="Dead"),"Lost",IF($I50<>"Y","Excluded",IF($N50<>"","Converted/Partially Converted",IF($J50="","Watchlist","Active")))) -> Watchlist | AJ50: =IF($I50<>"Y","Not Eligible - Excluded",IF(OR($H50="Lost",$H50="Dead"),"Not Eligible - Lost",IF($J50="","Scenario Only - No Close Date",IF($X50="","Scenario Only - No Ship Date",IF($Y50="","Scenario Only - No Cash Date",IF($AM50="Y","Not Eligible - SO Mapping Review","Eligible")))))) -> Scenario Only - No Close Date | AK50: =IF($AJ50="Eligible","Y","N") -> N | AL50: =SUMIFS(SO_Mapping!$F:$F,SO_Mapping!$A:$A,$B50) -> 0 | AM50: =IF(AND($N50<>"",$AL50=0),"Y",IF(ABS($O50-$AL50)>1,"Y","N")) -> N | AN50: =MAX(0,$K50-$AL50) -> 30000 | AO50: =IF($AK50="Y","Cash eligible",IF($I50<>"Y","Excluded by control flag",IF($J50="","No expected close date",IF($X50="","No ship/invoice timing",IF($Y50="","No cash timing",IF($AM50="Y","SO mapping must be resolved","Review required")))))) -> No expected close date | AP50: =IF($AK50="Y",TEXT($Y50,"yyyy-mm-dd"),"")
A51: 55 | B51: DPS-0055 | C51: Sample Pack - Silk Rinse | D51: CECRED | E51: COPACKING | F51: Q4 | G51: Jackie King | H51: Open | I51: Y | K51: 30000 | L51: 0.9 | M51: 27000 | Q51: 30000 | R51: 0.0% | S51: Open | W51: OK | Z51: 0 | AC51: No SO Yet | AD51: 0 | AE51: 30000 | AF51: Low - Missing Timing | AG51: 2026-05-23 | AI51: =IF(OR($H51="Lost",$H51="Dead"),"Lost",IF($I51<>"Y","Excluded",IF($N51<>"","Converted/Partially Converted",IF($J51="","Watchlist","Active")))) -> Watchlist | AJ51: =IF($I51<>"Y","Not Eligible - Excluded",IF(OR($H51="Lost",$H51="Dead"),"Not Eligible - Lost",IF($J51="","Scenario Only - No Close Date",IF($X51="","Scenario Only - No Ship Date",IF($Y51="","Scenario Only - No Cash Date",IF($AM51="Y","Not Eligible - SO Mapping Review","Eligible")))))) -> Scenario Only - No Close Date | AK51: =IF($AJ51="Eligible","Y","N") -> N | AL51: =SUMIFS(SO_Mapping!$F:$F,SO_Mapping!$A:$A,$B51) -> 0 | AM51: =IF(AND($N51<>"",$AL51=0),"Y",IF(ABS($O51-$AL51)>1,"Y","N")) -> N | AN51: =MAX(0,$K51-$AL51) -> 30000 | AO51: =IF($AK51="Y","Cash eligible",IF($I51<>"Y","Excluded by control flag",IF($J51="","No expected close date",IF($X51="","No ship/invoice timing",IF($Y51="","No cash timing",IF($AM51="Y","SO mapping must be resolved","Review required")))))) -> No expected close date | AP51: =IF($AK51="Y",TEXT($Y51,"yyyy-mm-dd"),"")
A52: 56 | B52: DPS-0056 | C52: Kids Hydration | D52: HEROLYTE | E52: TURNKEY | F52: Q1 | G52: Jackie King | H52: Lost | I52: Y | K52: 30000 | L52: 0.9 | M52: 27000 | Q52: 30000 | R52: 0.0% | S52: Lost | W52: OK | Z52: 0 | AC52: No SO Yet | AD52: 0 | AE52: 30000 | AF52: Low - Missing Timing | AG52: 2026-05-23 | AI52: =IF(OR($H52="Lost",$H52="Dead"),"Lost",IF($I52<>"Y","Excluded",IF($N52<>"","Converted/Partially Converted",IF($J52="","Watchlist","Active")))) -> Lost | AJ52: =IF($I52<>"Y","Not Eligible - Excluded",IF(OR($H52="Lost",$H52="Dead"),"Not Eligible - Lost",IF($J52="","Scenario Only - No Close Date",IF($X52="","Scenario Only - No Ship Date",IF($Y52="","Scenario Only - No Cash Date",IF($AM52="Y","Not Eligible - SO Mapping Review","Eligible")))))) -> Not Eligible - Lost | AK52: =IF($AJ52="Eligible","Y","N") -> N | AL52: =SUMIFS(SO_Mapping!$F:$F,SO_Mapping!$A:$A,$B52) -> 0 | AM52: =IF(AND($N52<>"",$AL52=0),"Y",IF(ABS($O52-$AL52)>1,"Y","N")) -> N | AN52: =MAX(0,$K52-$AL52) -> 30000 | AO52: =IF($AK52="Y","Cash eligible",IF($I52<>"Y","Excluded by control flag",IF($J52="","No expected close date",IF($X52="","No ship/invoice timing",IF($Y52="","No cash timing",IF($AM52="Y","SO mapping must be resolved","Review required")))))) -> No expected close date | AP52: =IF($AK52="Y",TEXT($Y52,"yyyy-mm-dd"),"")
A53: 57 | B53: DPS-0057 | C53: Kids Hydration | D53: HEROLYTE | E53: TURNKEY | F53: Q3 | G53: Jackie King | H53: Open | I53: Y | K53: 30000 | L53: 0.9 | M53: 27000 | Q53: 30000 | R53: 0.0% | S53: Open | W53: OK | Z53: 0 | AC53: No SO Yet | AD53: 0 | AE53: 30000 | AF53: Low - Missing Timing | AG53: 2026-05-23 | AI53: =IF(OR($H53="Lost",$H53="Dead"),"Lost",IF($I53<>"Y","Excluded",IF($N53<>"","Converted/Partially Converted",IF($J53="","Watchlist","Active")))) -> Watchlist | AJ53: =IF($I53<>"Y","Not Eligible - Excluded",IF(OR($H53="Lost",$H53="Dead"),"Not Eligible - Lost",IF($J53="","Scenario Only - No Close Date",IF($X53="","Scenario Only - No Ship Date",IF($Y53="","Scenario Only - No Cash Date",IF($AM53="Y","Not Eligible - SO Mapping Review","Eligible")))))) -> Scenario Only - No Close Date | AK53: =IF($AJ53="Eligible","Y","N") -> N | AL53: =SUMIFS(SO_Mapping!$F:$F,SO_Mapping!$A:$A,$B53) -> 0 | AM53: =IF(AND($N53<>"",$AL53=0),"Y",IF(ABS($O53-$AL53)>1,"Y","N")) -> N | AN53: =MAX(0,$K53-$AL53) -> 30000 | AO53: =IF($AK53="Y","Cash eligible",IF($I53<>"Y","Excluded by control flag",IF($J53="","No expected close date",IF($X53="","No ship/invoice timing",IF($Y53="","No cash timing",IF($AM53="Y","SO mapping must be resolved","Review required")))))) -> No expected close date | AP53: =IF($AK53="Y",TEXT($Y53,"yyyy-mm-dd"),"")
A54: 58 | B54: DPS-0058 | C54: OUAI PET JAR - 100ml | D54: OUAI | E54: PRIMARY | F54: Q4 | G54: Jing Santos | H54: Open | I54: Y | K54: 105000 | L54: 0.25 | M54: 26250 | Q54: 105000 | R54: 0.0% | S54: Open | W54: OK | Z54: 0 | AC54: No SO Yet | AD54: 0 | AE54: 105000 | AF54: Low - Missing Timing | AG54: 2026-05-23 | AI54: =IF(OR($H54="Lost",$H54="Dead"),"Lost",IF($I54<>"Y","Excluded",IF($N54<>"","Converted/Partially Converted",IF($J54="","Watchlist","Active")))) -> Watchlist | AJ54: =IF($I54<>"Y","Not Eligible - Excluded",IF(OR($H54="Lost",$H54="Dead"),"Not Eligible - Lost",IF($J54="","Scenario Only - No Close Date",IF($X54="","Scenario Only - No Ship Date",IF($Y54="","Scenario Only - No Cash Date",IF($AM54="Y","Not Eligible - SO Mapping Review","Eligible")))))) -> Scenario Only - No Close Date | AK54: =IF($AJ54="Eligible","Y","N") -> N | AL54: =SUMIFS(SO_Mapping!$F:$F,SO_Mapping!$A:$A,$B54) -> 0 | AM54: =IF(AND($N54<>"",$AL54=0),"Y",IF(ABS($O54-$AL54)>1,"Y","N")) -> N | AN54: =MAX(0,$K54-$AL54) -> 105000 | AO54: =IF($AK54="Y","Cash eligible",IF($I54<>"Y","Excluded by control flag",IF($J54="","No expected close date",IF($X54="","No ship/invoice timing",IF($Y54="","No cash timing",IF($AM54="Y","SO mapping must be resolved","Review required")))))) -> No expected close date | AP54: =IF($AK54="Y",TEXT($Y54,"yyyy-mm-dd"),"")
A55: 59 | B55: DPS-0059 | C55: OUIA PP Jar 100ml | D55: OUAI | E55: PRIMARY | F55: Q4 | G55: Jing Santos | H55: Open | I55: Y | K55: 105000 | L55: 0.25 | M55: 26250 | Q55: 105000 | R55: 0.0% | S55: Open | W55: OK | Z55: 0 | AC55: No SO Yet | AD55: 0 | AE55: 105000 | AF55: Low - Missing Timing | AG55: 2026-05-23 | AI55: =IF(OR($H55="Lost",$H55="Dead"),"Lost",IF($I55<>"Y","Excluded",IF($N55<>"","Converted/Partially Converted",IF($J55="","Watchlist","Active")))) -> Watchlist | AJ55: =IF($I55<>"Y","Not Eligible - Excluded",IF(OR($H55="Lost",$H55="Dead"),"Not Eligible - Lost",IF($J55="","Scenario Only - No Close Date",IF($X55="","Scenario Only - No Ship Date",IF($Y55="","Scenario Only - No Cash Date",IF($AM55="Y","Not Eligible - SO Mapping Review","Eligible")))))) -> Scenario Only - No Close Date | AK55: =IF($AJ55="Eligible","Y","N") -> N | AL55: =SUMIFS(SO_Mapping!$F:$F,SO_Mapping!$A:$A,$B55) -> 0 | AM55: =IF(AND($N55<>"",$AL55=0),"Y",IF(ABS($O55-$AL55)>1,"Y","N")) -> N | AN55: =MAX(0,$K55-$AL55) -> 105000 | AO55: =IF($AK55="Y","Cash eligible",IF($I55<>"Y","Excluded by control flag",IF($J55="","No expected close date",IF($X55="","No ship/invoice timing",IF($Y55="","No cash timing",IF($AM55="Y","SO mapping must be resolved","Review required")))))) -> No expected close date | AP55: =IF($AK55="Y",TEXT($Y55,"yyyy-mm-dd"),"")
A56: 60 | B56: DPS-0060 | C56: GET W - 15ml Mini Oval Deostick | D56: GET W | E56: PRIMARY | F56: Q2 | G56: Jing Santos | H56: Open | I56: Y | K56: 50000 | L56: 0.5 | M56: 25000 | Q56: 50000 | R56: 0.0% | S56: Open | W56: OK | Z56: 0 | AC56: No SO Yet | AD56: 0 | AE56: 50000 | AF56: Low - Missing Timing | AG56: 2026-05-23 | AI56: =IF(OR($H56="Lost",$H56="Dead"),"Lost",IF($I56<>"Y","Excluded",IF($N56<>"","Converted/Partially Converted",IF($J56="","Watchlist","Active")))) -> Watchlist | AJ56: =IF($I56<>"Y","Not Eligible - Excluded",IF(OR($H56="Lost",$H56="Dead"),"Not Eligible - Lost",IF($J56="","Scenario Only - No Close Date",IF($X56="","Scenario Only - No Ship Date",IF($Y56="","Scenario Only - No Cash Date",IF($AM56="Y","Not Eligible - SO Mapping Review","Eligible")))))) -> Scenario Only - No Close Date | AK56: =IF($AJ56="Eligible","Y","N") -> N | AL56: =SUMIFS(SO_Mapping!$F:$F,SO_Mapping!$A:$A,$B56) -> 0 | AM56: =IF(AND($N56<>"",$AL56=0),"Y",IF(ABS($O56-$AL56)>1,"Y","N")) -> N | AN56: =MAX(0,$K56-$AL56) -> 50000 | AO56: =IF($AK56="Y","Cash eligible",IF($I56<>"Y","Excluded by control flag",IF($J56="","No expected close date",IF($X56="","No ship/invoice timing",IF($Y56="","No cash timing",IF($AM56="Y","SO mapping must be resolved","Review required")))))) -> No expected close date | AP56: =IF($AK56="Y",TEXT($Y56,"yyyy-mm-dd"),"")
A57: 61 | B57: DPS-0061 | C57: MISTR - SACHETS | D57: MISTR | E57: SECONDARY | F57: Q3 | G57: Jackie King | H57: Open | I57: Y | K57: 50000 | L57: 0.5 | M57: 25000 | Q57: 50000 | R57: 0.0% | S57: Open | W57: OK | Z57: 0 | AC57: No SO Yet | AD57: 0 | AE57: 50000 | AF57: Low - Missing Timing | AG57: 2026-05-23 | AI57: =IF(OR($H57="Lost",$H57="Dead"),"Lost",IF($I57<>"Y","Excluded",IF($N57<>"","Converted/Partially Converted",IF($J57="","Watchlist","Active")))) -> Watchlist | AJ57: =IF($I57<>"Y","Not Eligible - Excluded",IF(OR($H57="Lost",$H57="Dead"),"Not Eligible - Lost",IF($J57="","Scenario Only - No Close Date",IF($X57="","Scenario Only - No Ship Date",IF($Y57="","Scenario Only - No Cash Date",IF($AM57="Y","Not Eligible - SO Mapping Review","Eligible")))))) -> Scenario Only - No Close Date | AK57: =IF($AJ57="Eligible","Y","N") -> N | AL57: =SUMIFS(SO_Mapping!$F:$F,SO_Mapping!$A:$A,$B57) -> 0 | AM57: =IF(AND($N57<>"",$AL57=0),"Y",IF(ABS($O57-$AL57)>1,"Y","N")) -> N | AN57: =MAX(0,$K57-$AL57) -> 50000 | AO57: =IF($AK57="Y","Cash eligible",IF($I57<>"Y","Excluded by control flag",IF($J57="","No expected close date",IF($X57="","No ship/invoice timing",IF($Y57="","No cash timing",IF($AM57="Y","SO mapping must be resolved","Review required")))))) -> No expected close date | AP57: =IF($AK57="Y",TEXT($Y57,"yyyy-mm-dd"),"")
A58: 62 | B58: DPS-0062 | C58: Emi Jay x DedCool Collab | D58: EMI JAY | E58: PRIMARY | F58: Q2 | G58: Jing Santos | H58: Open | I58: Y | K58: 23000 | L58: 1 | M58: 23000 | Q58: 23000 | R58: 0.0% | S58: Open | W58: OK | Z58: 0 | AC58: No SO Yet | AD58: 0 | AE58: 23000 | AF58: Low - Missing Timing | AG58: 2026-05-23 | AI58: =IF(OR($H58="Lost",$H58="Dead"),"Lost",IF($I58<>"Y","Excluded",IF($N58<>"","Converted/Partially Converted",IF($J58="","Watchlist","Active")))) -> Watchlist | AJ58: =IF($I58<>"Y","Not Eligible - Excluded",IF(OR($H58="Lost",$H58="Dead"),"Not Eligible - Lost",IF($J58="","Scenario Only - No Close Date",IF($X58="","Scenario Only - No Ship Date",IF($Y58="","Scenario Only - No Cash Date",IF($AM58="Y","Not Eligible - SO Mapping Review","Eligible")))))) -> Scenario Only - No Close Date | AK58: =IF($AJ58="Eligible","Y","N") -> N | AL58: =SUMIFS(SO_Mapping!$F:$F,SO_Mapping!$A:$A,$B58) -> 0 | AM58: =IF(AND($N58<>"",$AL58=0),"Y",IF(ABS($O58-$AL58)>1,"Y","N")) -> N | AN58: =MAX(0,$K58-$AL58) -> 23000 | AO58: =IF($AK58="Y","Cash eligible",IF($I58<>"Y","Excluded by control flag",IF($J58="","No expected close date",IF($X58="","No ship/invoice timing",IF($Y58="","No cash timing",IF($AM58="Y","SO mapping must be resolved","Review required")))))) -> No expected close date | AP58: =IF($AK58="Y",TEXT($Y58,"yyyy-mm-dd"),"")
A59: 63 | B59: DPS-0063 | C59: Pattern Body - 200ml All Over Body Balm Jars/Caps | D59: PATTERN | E59: PRIMARY | F59: Q1 | G59: Jing Santos | H59: Lost | I59: Y | K59: 25000 | L59: 0.9 | M59: 22500 | Q59: 25000 | R59: 0.0% | S59: Lost | W59: OK | Z59: 0 | AC59: No SO Yet | AD59: 0 | AE59: 25000 | AF59: Low - Missing Timing | AG59: 2026-05-23 | AI59: =IF(OR($H59="Lost",$H59="Dead"),"Lost",IF($I59<>"Y","Excluded",IF($N59<>"","Converted/Partially Converted",IF($J59="","Watchlist","Active")))) -> Lost | AJ59: =IF($I59<>"Y","Not Eligible - Excluded",IF(OR($H59="Lost",$H59="Dead"),"Not Eligible - Lost",IF($J59="","Scenario Only - No Close Date",IF($X59="","Scenario Only - No Ship Date",IF($Y59="","Scenario Only - No Cash Date",IF($AM59="Y","Not Eligible - SO Mapping Review","Eligible")))))) -> Not Eligible - Lost | AK59: =IF($AJ59="Eligible","Y","N") -> N | AL59: =SUMIFS(SO_Mapping!$F:$F,SO_Mapping!$A:$A,$B59) -> 0 | AM59: =IF(AND($N59<>"",$AL59=0),"Y",IF(ABS($O59-$AL59)>1,"Y","N")) -> N | AN59: =MAX(0,$K59-$AL59) -> 25000 | AO59: =IF($AK59="Y","Cash eligible",IF($I59<>"Y","Excluded by control flag",IF($J59="","No expected close date",IF($X59="","No ship/invoice timing",IF($Y59="","No cash timing",IF($AM59="Y","SO mapping must be resolved","Review required")))))) -> No expected close date | AP59: =IF($AK59="Y",TEXT($Y59,"yyyy-mm-dd"),"")
A60: 64 | B60: DPS-0064 | C60: NewULife - Replenishment | D60: NewULife | E60: COPACKING | F60: Q2 | G60: Jackie King | H60: Open | I60: Y | K60: 25000 | L60: 0.9 | M60: 22500 | Q60: 25000 | R60: 0.0% | S60: Open | W60: OK | Z60: 0 | AC60: No SO Yet | AD60: 0 | AE60: 25000 | AF60: Low - Missing Timing | AG60: 2026-05-23 | AI60: =IF(OR($H60="Lost",$H60="Dead"),"Lost",IF($I60<>"Y","Excluded",IF($N60<>"","Converted/Partially Converted",IF($J60="","Watchlist","Active")))) -> Watchlist | AJ60: =IF($I60<>"Y","Not Eligible - Excluded",IF(OR($H60="Lost",$H60="Dead"),"Not Eligible - Lost",IF($J60="","Scenario Only - No Close Date",IF($X60="","Scenario Only - No Ship Date",IF($Y60="","Scenario Only - No Cash Date",IF($AM60="Y","Not Eligible - SO Mapping Review","Eligible")))))) -> Scenario Only - No Close Date | AK60: =IF($AJ60="Eligible","Y","N") -> N | AL60: =SUMIFS(SO_Mapping!$F:$F,SO_Mapping!$A:$A,$B60) -> 0 | AM60: =IF(AND($N60<>"",$AL60=0),"Y",IF(ABS($O60-$AL60)>1,"Y","N")) -> N | AN60: =MAX(0,$K60-$AL60) -> 25000 | AO60: =IF($AK60="Y","Cash eligible",IF($I60<>"Y","Excluded by control flag",IF($J60="","No expected close date",IF($X60="","No ship/invoice timing",IF($Y60="","No cash timing",IF($AM60="Y","SO mapping must be resolved","Review required")))))) -> No expected close date | AP60: =IF($AK60="Y",TEXT($Y60,"yyyy-mm-dd"),"")
A61: 65 | B61: DPS-0065 | C61: NewULife - Replenishment | D61: NewULife | E61: COPACKING | F61: Q3 | G61: Jackie King | H61: Open | I61: Y | K61: 25000 | L61: 0.9 | M61: 22500 | Q61: 25000 | R61: 0.0% | S61: Open | W61: OK | Z61: 0 | AC61: No SO Yet | AD61: 0 | AE61: 25000 | AF61: Low - Missing Timing | AG61: 2026-05-23 | AI61: =IF(OR($H61="Lost",$H61="Dead"),"Lost",IF($I61<>"Y","Excluded",IF($N61<>"","Converted/Partially Converted",IF($J61="","Watchlist","Active")))) -> Watchlist | AJ61: =IF($I61<>"Y","Not Eligible - Excluded",IF(OR($H61="Lost",$H61="Dead"),"Not Eligible - Lost",IF($J61="","Scenario Only - No Close Date",IF($X61="","Scenario Only - No Ship Date",IF($Y61="","Scenario Only - No Cash Date",IF($AM61="Y","Not Eligible - SO Mapping Review","Eligible")))))) -> Scenario Only - No Close Date | AK61: =IF($AJ61="Eligible","Y","N") -> N | AL61: =SUMIFS(SO_Mapping!$F:$F,SO_Mapping!$A:$A,$B61) -> 0 | AM61: =IF(AND($N61<>"",$AL61=0),"Y",IF(ABS($O61-$AL61)>1,"Y","N")) -> N | AN61: =MAX(0,$K61-$AL61) -> 25000 | AO61: =IF($AK61="Y","Cash eligible",IF($I61<>"Y","Excluded by control flag",IF($J61="","No expected close date",IF($X61="","No ship/invoice timing",IF($Y61="","No cash timing",IF($AM61="Y","SO mapping must be resolved","Review required")))))) -> No expected close date | AP61: =IF($AK61="Y",TEXT($Y61,"yyyy-mm-dd"),"")
... A71: 111 | B71: DPS-0111 | C71: Nemah - Minis for Target kits | D71: Nemah | E71: PRIMARY | F71: Q4 | G71: Jing Santos | H71: Open | I71: Y | K71: 25000 | L71: 0.9 | M71: 22500 | Q71: 25000 | R71: 0.0% | S71: Open | W71: OK | Z71: 0 | AC71: No SO Yet | AD71: 0 | AE71: 25000 | AF71: Low - Missing Timing | AG71: 2026-05-23 | AI71: =IF(OR($H71="Lost",$H71="Dead"),"Lost",IF($I71<>"Y","Excluded",IF($N71<>"","Converted/Partially Converted",IF($J71="","Watchlist","Active")))) -> Watchlist | AJ71: =IF($I71<>"Y","Not Eligible - Excluded",IF(OR($H71="Lost",$H71="Dead"),"Not Eligible - Lost",IF($J71="","Scenario Only - No Close Date",IF($X71="","Scenario Only - No Ship Date",IF($Y71="","Scenario Only - No Cash Date",IF($AM71="Y","Not Eligible - SO Mapping Review","Eligible")))))) -> Scenario Only - No Close Date | AK71: =IF($AJ71="Eligible","Y","N") -> N | AL71: =SUMIFS(SO_Mapping!$F:$F,SO_Mapping!$A:$A,$B71) -> 0 | AM71: =IF(AND($N71<>"",$AL71=0),"Y",IF(ABS($O71-$AL71)>1,"Y","N")) -> N | AN71: =MAX(0,$K71-$AL71) -> 25000 | AO71: =IF($AK71="Y","Cash eligible",IF($I71<>"Y","Excluded by control flag",IF($J71="","No expected close date",IF($X71="","No ship/invoice timing",IF($Y71="","No cash timing",IF($AM71="Y","SO mapping must be resolved","Review required")))))) -> No expected close date | AP71: =IF($AK71="Y",TEXT($Y71,"yyyy-mm-dd"),"")
A72: 71 | B72: DPS-0071 | C72: Sachet | D72: GOLDENHIPPO | E72: TURNKEY | F72: Q2 | G72: Danny Park | H72: Won | I72: Y | J72: 2026-03-17 | K72: 22000 | L72: 1 | M72: 22000 | N72: SO2571 | O72: 29000 | P72: 2026-03-17 | R72: 131.8% | S72: Fully Converted | W72: Review SO over pipeline | X72: 2026-03-17 | Y72: 2026-04-16 | Z72: 0 | AB72: 2026-04-16 | AC72: SO Linked | AD72: 29000 | AE72: 0 | AF72: Do Not Use - Data Issue | AG72: 2026-05-23 | AI72: =IF(OR($H72="Lost",$H72="Dead"),"Lost",IF($I72<>"Y","Excluded",IF($N72<>"","Converted/Partially Converted",IF($J72="","Watchlist","Active")))) -> Converted/Partially Converted | AJ72: =IF($I72<>"Y","Not Eligible - Excluded",IF(OR($H72="Lost",$H72="Dead"),"Not Eligible - Lost",IF($J72="","Scenario Only - No Close Date",IF($X72="","Scenario Only - No Ship Date",IF($Y72="","Scenario Only - No Cash Date",IF($AM72="Y","Not Eligible - SO Mapping Review","Eligible")))))) -> Eligible | AK72: =IF($AJ72="Eligible","Y","N") -> Y | AL72: =SUMIFS(SO_Mapping!$F:$F,SO_Mapping!$A:$A,$B72) -> 29000 | AM72: =IF(AND($N72<>"",$AL72=0),"Y",IF(ABS($O72-$AL72)>1,"Y","N")) -> N | AN72: =MAX(0,$K72-$AL72) -> 0 | AO72: =IF($AK72="Y","Cash eligible",IF($I72<>"Y","Excluded by control flag",IF($J72="","No expected close date",IF($X72="","No ship/invoice timing",IF($Y72="","No cash timing",IF($AM72="Y","SO mapping must be resolved","Review required")))))) -> Cash eligible | AP72: =IF($AK72="Y",TEXT($Y72,"yyyy-mm-dd"),"") -> 2026-04-16
A73: 72 | B73: DPS-0072 | C73: Nemah - 50ml Firming Body Serum - Kit Size | D73: Nemah | E73: PRIMARY | F73: Q4 | G73: Jing Santos | H73: Open | I73: Y | K73: 25000 | L73: 0.75 | M73: 18750 | Q73: 25000 | R73: 0.0% | S73: Open | W73: OK | Z73: 0 | AC73: No SO Yet | AD73: 0 | AE73: 25000 | AF73: Low - Missing Timing | AG73: 2026-05-23 | AI73: =IF(OR($H73="Lost",$H73="Dead"),"Lost",IF($I73<>"Y","Excluded",IF($N73<>"","Converted/Partially Converted",IF($J73="","Watchlist","Active")))) -> Watchlist | AJ73: =IF($I73<>"Y","Not Eligible - Excluded",IF(OR($H73="Lost",$H73="Dead"),"Not Eligible - Lost",IF($J73="","Scenario Only - No Close Date",IF($X73="","Scenario Only - No Ship Date",IF($Y73="","Scenario Only - No Cash Date",IF($AM73="Y","Not Eligible - SO Mapping Review","Eligible")))))) -> Scenario Only - No Close Date | AK73: =IF($AJ73="Eligible","Y","N") -> N | AL73: =SUMIFS(SO_Mapping!$F:$F,SO_Mapping!$A:$A,$B73) -> 0 | AM73: =IF(AND($N73<>"",$AL73=0),"Y",IF(ABS($O73-$AL73)>1,"Y","N")) -> N | AN73: =MAX(0,$K73-$AL73) -> 25000 | AO73: =IF($AK73="Y","Cash eligible",IF($I73<>"Y","Excluded by control flag",IF($J73="","No expected close date",IF($X73="","No ship/invoice timing",IF($Y73="","No cash timing",IF($AM73="Y","SO mapping must be resolved","Review required")))))) -> No expected close date | AP73: =IF($AK73="Y",TEXT($Y73,"yyyy-mm-dd"),"")
A74: 73 | B74: DPS-0073 | C74: Nemah - 400ml Body Wash | D74: Nemah | E74: PRIMARY | F74: Q4 | G74: Jing Santos | H74: Open | I74: Y | K74: 25000 | L74: 0.75 | M74: 18750 | Q74: 25000 | R74: 0.0% | S74: Open | W74: OK | Z74: 0 | AC74: No SO Yet | AD74: 0 | AE74: 25000 | AF74: Low - Missing Timing | AG74: 2026-05-23 | AI74: =IF(OR($H74="Lost",$H74="Dead"),"Lost",IF($I74<>"Y","Excluded",IF($N74<>"","Converted/Partially Converted",IF($J74="","Watchlist","Active")))) -> Watchlist | AJ74: =IF($I74<>"Y","Not Eligible - Excluded",IF(OR($H74="Lost",$H74="Dead"),"Not Eligible - Lost",IF($J74="","Scenario Only - No Close Date",IF($X74="","Scenario Only - No Ship Date",IF($Y74="","Scenario Only - No Cash Date",IF($AM74="Y","Not Eligible - SO Mapping Review","Eligible")))))) -> Scenario Only - No Close Date | AK74: =IF($AJ74="Eligible","Y","N") -> N | AL74: =SUMIFS(SO_Mapping!$F:$F,SO_Mapping!$A:$A,$B74) -> 0 | AM74: =IF(AND($N74<>"",$AL74=0),"Y",IF(ABS($O74-$AL74)>1,"Y","N")) -> N | AN74: =MAX(0,$K74-$AL74) -> 25000 | AO74: =IF($AK74="Y","Cash eligible",IF($I74<>"Y","Excluded by control flag",IF($J74="","No expected close date",IF($X74="","No ship/invoice timing",IF($Y74="","No cash timing",IF($AM74="Y","SO mapping must be resolved","Review required")))))) -> No expected close date | AP74: =IF($AK74="Y",TEXT($Y74,"yyyy-mm-dd"),"")
A75: 74 | B75: DPS-0074 | C75: Nemah - 120ml Foaming Face Wash | D75: Nemah | E75: PRIMARY | F75: Q4 | G75: Jing Santos | H75: Open | I75: Y | K75: 25000 | L75: 0.75 | M75: 18750 | Q75: 25000 | R75: 0.0% | S75: Open | W75: OK | Z75: 0 | AC75: No SO Yet | AD75: 0 | AE75: 25000 | AF75: Low - Missing Timing | AG75: 2026-05-23 | AI75: =IF(OR($H75="Lost",$H75="Dead"),"Lost",IF($I75<>"Y","Excluded",IF($N75<>"","Converted/Partially Converted",IF($J75="","Watchlist","Active")))) -> Watchlist | AJ75: =IF($I75<>"Y","Not Eligible - Excluded",IF(OR($H75="Lost",$H75="Dead"),"Not Eligible - Lost",IF($J75="","Scenario Only - No Close Date",IF($X75="","Scenario Only - No Ship Date",IF($Y75="","Scenario Only - No Cash Date",IF($AM75="Y","Not Eligible - SO Mapping Review","Eligible")))))) -> Scenario Only - No Close Date | AK75: =IF($AJ75="Eligible","Y","N") -> N | AL75: =SUMIFS(SO_Mapping!$F:$F,SO_Mapping!$A:$A,$B75) -> 0 | AM75: =IF(AND($N75<>"",$AL75=0),"Y",IF(ABS($O75-$AL75)>1,"Y","N")) -> N | AN75: =MAX(0,$K75-$AL75) -> 25000 | AO75: =IF($AK75="Y","Cash eligible",IF($I75<>"Y","Excluded by control flag",IF($J75="","No expected close date",IF($X75="","No ship/invoice timing",IF($Y75="","No cash timing",IF($AM75="Y","SO mapping must be resolved","Review required")))))) -> No expected close date | AP75: =IF($AK75="Y",TEXT($Y75,"yyyy-mm-dd"),"")
A76: 75 | B76: DPS-0075 | C76: Nemah - 30ml Vitamin C Serum - Full Size | D76: Nemah | E76: PRIMARY | F76: Q4 | G76: Jing Santos | H76: Open | I76: Y | K76: 25000 | L76: 0.75 | M76: 18750 | Q76: 25000 | R76: 0.0% | S76: Open | W76: OK | Z76: 0 | AC76: No SO Yet | AD76: 0 | AE76: 25000 | AF76: Low - Missing Timing | AG76: 2026-05-23 | AI76: =IF(OR($H76="Lost",$H76="Dead"),"Lost",IF($I76<>"Y","Excluded",IF($N76<>"","Converted/Partially Converted",IF($J76="","Watchlist","Active")))) -> Watchlist | AJ76: =IF($I76<>"Y","Not Eligible - Excluded",IF(OR($H76="Lost",$H76="Dead"),"Not Eligible - Lost",IF($J76="","Scenario Only - No Close Date",IF($X76="","Scenario Only - No Ship Date",IF($Y76="","Scenario Only - No Cash Date",IF($AM76="Y","Not Eligible - SO Mapping Review","Eligible")))))) -> Scenario Only - No Close Date | AK76: =IF($AJ76="Eligible","Y","N") -> N | AL76: =SUMIFS(SO_Mapping!$F:$F,SO_Mapping!$A:$A,$B76) -> 0 | AM76: =IF(AND($N76<>"",$AL76=0),"Y",IF(ABS($O76-$AL76)>1,"Y","N")) -> N | AN76: =MAX(0,$K76-$AL76) -> 25000 | AO76: =IF($AK76="Y","Cash eligible",IF($I76<>"Y","Excluded by control flag",IF($J76="","No expected close date",IF($X76="","No ship/invoice timing",IF($Y76="","No cash timing",IF($AM76="Y","SO mapping must be resolved","Review required")))))) -> No expected close date | AP76: =IF($AK76="Y",TEXT($Y76,"yyyy-mm-dd"),"")
A77: 76 | B77: DPS-0076 | C77: 150ml Body Serum | D77: Nemah | E77: PRIMARY | F77: Q2 | G77: Jing Santos | H77: Won | I77: Y | J77: 2026-04-20 | K77: 25000 | L77: 0.75 | M77: 18750 | N77: SO2591, SO2615 | O77: 60568 | P77: 2026-04-20 | R77: 242.3% | S77: Fully Converted | W77: Review SO over pipeline | X77: 2026-04-20 | Y77: 2026-05-20 | Z77: 0 | AB77: 2026-05-20 | AC77: SO Linked | AD77: 60568 | AE77: 0 | AF77: Do Not Use - Data Issue | AG77: 2026-05-23 | AI77: =IF(OR($H77="Lost",$H77="Dead"),"Lost",IF($I77<>"Y","Excluded",IF($N77<>"","Converted/Partially Converted",IF($J77="","Watchlist","Active")))) -> Converted/Partially Converted | AJ77: =IF($I77<>"Y","Not Eligible - Excluded",IF(OR($H77="Lost",$H77="Dead"),"Not Eligible - Lost",IF($J77="","Scenario Only - No Close Date",IF($X77="","Scenario Only - No Ship Date",IF($Y77="","Scenario Only - No Cash Date",IF($AM77="Y","Not Eligible - SO Mapping Review","Eligible")))))) -> Not Eligible - SO Mapping Review | AK77: =IF($AJ77="Eligible","Y","N") -> N | AL77: =SUMIFS(SO_Mapping!$F:$F,SO_Mapping!$A:$A,$B77) -> 0 | AM77: =IF(AND($N77<>"",$AL77=0),"Y",IF(ABS($O77-$AL77)>1,"Y","N")) -> Y | AN77: =MAX(0,$K77-$AL77) -> 25000 | AO77: =IF($AK77="Y","Cash eligible",IF($I77<>"Y","Excluded by control flag",IF($J77="","No expected close date",IF($X77="","No ship/invoice timing",IF($Y77="","No cash timing",IF($AM77="Y","SO mapping must be resolved","Review required")))))) -> SO mapping must be resolved | AP77: =IF($AK77="Y",TEXT($Y77,"yyyy-mm-dd"),"")
A78: 77 | B78: DPS-0077 | C78: 400ml Body Lotion | D78: Nemah | E78: PRIMARY | F78: Q2 | G78: Jing Santos | H78: Open | I78: Y | K78: 25000 | L78: 0.75 | M78: 18750 | Q78: 25000 | R78: 0.0% | S78: Open | W78: OK | Z78: 0 | AC78: No SO Yet | AD78: 0 | AE78: 25000 | AF78: Low - Missing Timing | AG78: 2026-05-23 | AI78: =IF(OR($H78="Lost",$H78="Dead"),"Lost",IF($I78<>"Y","Excluded",IF($N78<>"","Converted/Partially Converted",IF($J78="","Watchlist","Active")))) -> Watchlist | AJ78: =IF($I78<>"Y","Not Eligible - Excluded",IF(OR($H78="Lost",$H78="Dead"),"Not Eligible - Lost",IF($J78="","Scenario Only - No Close Date",IF($X78="","Scenario Only - No Ship Date",IF($Y78="","Scenario Only - No Cash Date",IF($AM78="Y","Not Eligible - SO Mapping Review","Eligible")))))) -> Scenario Only - No Close Date | AK78: =IF($AJ78="Eligible","Y","N") -> N | AL78: =SUMIFS(SO_Mapping!$F:$F,SO_Mapping!$A:$A,$B78) -> 0 | AM78: =IF(AND($N78<>"",$AL78=0),"Y",IF(ABS($O78-$AL78)>1,"Y","N")) -> N | AN78: =MAX(0,$K78-$AL78) -> 25000 | AO78: =IF($AK78="Y","Cash eligible",IF($I78<>"Y","Excluded by control flag",IF($J78="","No expected close date",IF($X78="","No ship/invoice timing",IF($Y78="","No cash timing",IF($AM78="Y","SO mapping must be resolved","Review required")))))) -> No expected close date | AP78: =IF($AK78="Y",TEXT($Y78,"yyyy-mm-dd"),"")
A79: 78 | B79: DPS-0078 | C79: 50ml Facial Serum | D79: Nemah | E79: PRIMARY | F79: Q3 | G79: Jing Santos | H79: Open | I79: Y | K79: 25000 | L79: 0.75 | M79: 18750 | Q79: 25000 | R79: 0.0% | S79: Open | W79: OK | Z79: 0 | AC79: No SO Yet | AD79: 0 | AE79: 25000 | AF79: Low - Missing Timing | AG79: 2026-05-23 | AI79: =IF(OR($H79="Lost",$H79="Dead"),"Lost",IF($I79<>"Y","Excluded",IF($N79<>"","Converted/Partially Converted",IF($J79="","Watchlist","Active")))) -> Watchlist | AJ79: =IF($I79<>"Y","Not Eligible - Excluded",IF(OR($H79="Lost",$H79="Dead"),"Not Eligible - Lost",IF($J79="","Scenario Only - No Close Date",IF($X79="","Scenario Only - No Ship Date",IF($Y79="","Scenario Only - No Cash Date",IF($AM79="Y","Not Eligible - SO Mapping Review","Eligible")))))) -> Scenario Only - No Close Date | AK79: =IF($AJ79="Eligible","Y","N") -> N | AL79: =SUMIFS(SO_Mapping!$F:$F,SO_Mapping!$A:$A,$B79) -> 0 | AM79: =IF(AND($N79<>"",$AL79=0),"Y",IF(ABS($O79-$AL79)>1,"Y","N")) -> N | AN79: =MAX(0,$K79-$AL79) -> 25000 | AO79: =IF($AK79="Y","Cash eligible",IF($I79<>"Y","Excluded by control flag",IF($J79="","No expected close date",IF($X79="","No ship/invoice timing",IF($Y79="","No cash timing",IF($AM79="Y","SO mapping must be resolved","Review required")))))) -> No expected close date | AP79: =IF($AK79="Y",TEXT($Y79,"yyyy-mm-dd"),"")
A80: 79 | B80: DPS-0079 | C80: 2oz Hand Sanitizer | D80: Nemah | E80: PRIMARY | F80: Q4 | G80: Jing Santos | H80: Open | I80: Y | K80: 25000 | L80: 0.75 | M80: 18750 | Q80: 25000 | R80: 0.0% | S80: Open | W80: OK | Z80: 0 | AC80: No SO Yet | AD80: 0 | AE80: 25000 | AF80: Low - Missing Timing | AG80: 2026-05-23 | AI80: =IF(OR($H80="Lost",$H80="Dead"),"Lost",IF($I80<>"Y","Excluded",IF($N80<>"","Converted/Partially Converted",IF($J80="","Watchlist","Active")))) -> Watchlist | AJ80: =IF($I80<>"Y","Not Eligible - Excluded",IF(OR($H80="Lost",$H80="Dead"),"Not Eligible - Lost",IF($J80="","Scenario Only - No Close Date",IF($X80="","Scenario Only - No Ship Date",IF($Y80="","Scenario Only - No Cash Date",IF($AM80="Y","Not Eligible - SO Mapping Review","Eligible")))))) -> Scenario Only - No Close Date | AK80: =IF($AJ80="Eligible","Y","N") -> N | AL80: =SUMIFS(SO_Mapping!$F:$F,SO_Mapping!$A:$A,$B80) -> 0 | AM80: =IF(AND($N80<>"",$AL80=0),"Y",IF(ABS($O80-$AL80)>1,"Y","N")) -> N | AN80: =MAX(0,$K80-$AL80) -> 25000 | AO80: =IF($AK80="Y","Cash eligible",IF($I80<>"Y","Excluded by control flag",IF($J80="","No expected close date",IF($X80="","No ship/invoice timing",IF($Y80="","No cash timing",IF($AM80="Y","SO mapping must be resolved","Review required")))))) -> No expected close date | AP80: =IF($AK80="Y",TEXT($Y80,"yyyy-mm-dd"),"")
A81: 80 | B81: DPS-0080 | C81: Pattern Body - 3oz Body Wash-Palo Santo | D81: PATTERN | E81: PRIMARY | F81: Q4 | G81: Jing Santos | H81: Open | I81: Y | K81: 25000 | L81: 0.75 | M81: 18750 | Q81: 25000 | R81: 0.0% | S81: Open | W81: OK | Z81: 0 | AC81: No SO Yet | AD81: 0 | AE81: 25000 | AF81: Low - Missing Timing | AG81: 2026-05-23 | AI81: =IF(OR($H81="Lost",$H81="Dead"),"Lost",IF($I81<>"Y","Excluded",IF($N81<>"","Converted/Partially Converted",IF($J81="","Watchlist","Active")))) -> Watchlist | AJ81: =IF($I81<>"Y","Not Eligible - Excluded",IF(OR($H81="Lost",$H81="Dead"),"Not Eligible - Lost",IF($J81="","Scenario Only - No Close Date",IF($X81="","Scenario Only - No Ship Date",IF($Y81="","Scenario Only - No Cash Date",IF($AM81="Y","Not Eligible - SO Mapping Review","Eligible")))))) -> Scenario Only - No Close Date | AK81: =IF($AJ81="Eligible","Y","N") -> N | AL81: =SUMIFS(SO_Mapping!$F:$F,SO_Mapping!$A:$A,$B81) -> 0 | AM81: =IF(AND($N81<>"",$AL81=0),"Y",IF(ABS($O81-$AL81)>1,"Y","N")) -> N | AN81: =MAX(0,$K81-$AL81) -> 25000 | AO81: =IF($AK81="Y","Cash eligible",IF($I81<>"Y","Excluded by control flag",IF($J81="","No expected close date",IF($X81="","No ship/invoice timing",IF($Y81="","No cash timing",IF($AM81="Y","SO mapping must be resolved","Review required")))))) -> No expected close date | AP81: =IF($AK81="Y",TEXT($Y81,"yyyy-mm-dd"),"")
A82: 81 | B82: DPS-0081 | C82: Pattern Body - 3oz Body Wash-Indigo Rain | D82: PATTERN | E82: PRIMARY | F82: Q4 | G82: Jing Santos | H82: Open | I82: Y | K82: 25000 | L82: 0.75 | M82: 18750 | Q82: 25000 | R82: 0.0% | S82: Open | W82: OK | Z82: 0 | AC82: No SO Yet | AD82: 0 | AE82: 25000 | AF82: Low - Missing Timing | AG82: 2026-05-23 | AI82: =IF(OR($H82="Lost",$H82="Dead"),"Lost",IF($I82<>"Y","Excluded",IF($N82<>"","Converted/Partially Converted",IF($J82="","Watchlist","Active")))) -> Watchlist | AJ82: =IF($I82<>"Y","Not Eligible - Excluded",IF(OR($H82="Lost",$H82="Dead"),"Not Eligible - Lost",IF($J82="","Scenario Only - No Close Date",IF($X82="","Scenario Only - No Ship Date",IF($Y82="","Scenario Only - No Cash Date",IF($AM82="Y","Not Eligible - SO Mapping Review","Eligible")))))) -> Scenario Only - No Close Date | AK82: =IF($AJ82="Eligible","Y","N") -> N | AL82: =SUMIFS(SO_Mapping!$F:$F,SO_Mapping!$A:$A,$B82) -> 0 | AM82: =IF(AND($N82<>"",$AL82=0),"Y",IF(ABS($O82-$AL82)>1,"Y","N")) -> N | AN82: =MAX(0,$K82-$AL82) -> 25000 | AO82: =IF($AK82="Y","Cash eligible",IF($I82<>"Y","Excluded by control flag",IF($J82="","No expected close date",IF($X82="","No ship/invoice timing",IF($Y82="","No cash timing",IF($AM82="Y","SO mapping must be resolved","Review required")))))) -> No expected close date | AP82: =IF($AK82="Y",TEXT($Y82,"yyyy-mm-dd"),"")
A83: 82 | B83: DPS-0082 | C83: Pattern Body - 3oz Body Cream-Palo Santo | D83: PATTERN | E83: PRIMARY | F83: Q4 | G83: Jing Santos | H83: Open | I83: Y | K83: 25000 | L83: 0.75 | M83: 18750 | Q83: 25000 | R83: 0.0% | S83: Open | W83: OK | Z83: 0 | AC83: No SO Yet | AD83: 0 | AE83: 25000 | AF83: Low - Missing Timing | AG83: 2026-05-23 | AI83: =IF(OR($H83="Lost",$H83="Dead"),"Lost",IF($I83<>"Y","Excluded",IF($N83<>"","Converted/Partially Converted",IF($J83="","Watchlist","Active")))) -> Watchlist | AJ83: =IF($I83<>"Y","Not Eligible - Excluded",IF(OR($H83="Lost",$H83="Dead"),"Not Eligible - Lost",IF($J83="","Scenario Only - No Close Date",IF($X83="","Scenario Only - No Ship Date",IF($Y83="","Scenario Only - No Cash Date",IF($AM83="Y","Not Eligible - SO Mapping Review","Eligible")))))) -> Scenario Only - No Close Date | AK83: =IF($AJ83="Eligible","Y","N") -> N | AL83: =SUMIFS(SO_Mapping!$F:$F,SO_Mapping!$A:$A,$B83) -> 0 | AM83: =IF(AND($N83<>"",$AL83=0),"Y",IF(ABS($O83-$AL83)>1,"Y","N")) -> N | AN83: =MAX(0,$K83-$AL83) -> 25000 | AO83: =IF($AK83="Y","Cash eligible",IF($I83<>"Y","Excluded by control flag",IF($J83="","No expected close date",IF($X83="","No ship/invoice timing",IF($Y83="","No cash timing",IF($AM83="Y","SO mapping must be resolved","Review required")))))) -> No expected close date | AP83: =IF($AK83="Y",TEXT($Y83,"yyyy-mm-dd"),"")
A84: 83 | B84: DPS-0083 | C84: Pattern Body - 3oz Body Cream-Indigo Rain | D84: PATTERN | E84: PRIMARY | F84: Q4 | G84: Jing Santos | H84: Open | I84: Y | K84: 25000 | L84: 0.75 | M84: 18750 | Q84: 25000 | R84: 0.0% | S84: Open | W84: OK | Z84: 0 | AC84: No SO Yet | AD84: 0 | AE84: 25000 | AF84: Low - Missing Timing | AG84: 2026-05-23 | AI84: =IF(OR($H84="Lost",$H84="Dead"),"Lost",IF($I84<>"Y","Excluded",IF($N84<>"","Converted/Partially Converted",IF($J84="","Watchlist","Active")))) -> Watchlist | AJ84: =IF($I84<>"Y","Not Eligible - Excluded",IF(OR($H84="Lost",$H84="Dead"),"Not Eligible - Lost",IF($J84="","Scenario Only - No Close Date",IF($X84="","Scenario Only - No Ship Date",IF($Y84="","Scenario Only - No Cash Date",IF($AM84="Y","Not Eligible - SO Mapping Review","Eligible")))))) -> Scenario Only - No Close Date | AK84: =IF($AJ84="Eligible","Y","N") -> N | AL84: =SUMIFS(SO_Mapping!$F:$F,SO_Mapping!$A:$A,$B84) -> 0 | AM84: =IF(AND($N84<>"",$AL84=0),"Y",IF(ABS($O84-$AL84)>1,"Y","N")) -> N | AN84: =MAX(0,$K84-$AL84) -> 25000 | AO84: =IF($AK84="Y","Cash eligible",IF($I84<>"Y","Excluded by control flag",IF($J84="","No expected close date",IF($X84="","No ship/invoice timing",IF($Y84="","No cash timing",IF($AM84="Y","SO mapping must be resolved","Review required")))))) -> No expected close date | AP84: =IF($AK84="Y",TEXT($Y84,"yyyy-mm-dd"),"")
A85: 84 | B85: DPS-0084 | C85: Pattern Body - 3oz Body Scrub-Palo Santo | D85: PATTERN | E85: PRIMARY | F85: Q4 | G85: Jing Santos | H85: Open | I85: Y | K85: 25000 | L85: 0.75 | M85: 18750 | Q85: 25000 | R85: 0.0% | S85: Open | W85: OK | Z85: 0 | AC85: No SO Yet | AD85: 0 | AE85: 25000 | AF85: Low - Missing Timing | AG85: 2026-05-23 | AI85: =IF(OR($H85="Lost",$H85="Dead"),"Lost",IF($I85<>"Y","Excluded",IF($N85<>"","Converted/Partially Converted",IF($J85="","Watchlist","Active")))) -> Watchlist | AJ85: =IF($I85<>"Y","Not Eligible - Excluded",IF(OR($H85="Lost",$H85="Dead"),"Not Eligible - Lost",IF($J85="","Scenario Only - No Close Date",IF($X85="","Scenario Only - No Ship Date",IF($Y85="","Scenario Only - No Cash Date",IF($AM85="Y","Not Eligible - SO Mapping Review","Eligible")))))) -> Scenario Only - No Close Date | AK85: =IF($AJ85="Eligible","Y","N") -> N | AL85: =SUMIFS(SO_Mapping!$F:$F,SO_Mapping!$A:$A,$B85) -> 0 | AM85: =IF(AND($N85<>"",$AL85=0),"Y",IF(ABS($O85-$AL85)>1,"Y","N")) -> N | AN85: =MAX(0,$K85-$AL85) -> 25000 | AO85: =IF($AK85="Y","Cash eligible",IF($I85<>"Y","Excluded by control flag",IF($J85="","No expected close date",IF($X85="","No ship/invoice timing",IF($Y85="","No cash timing",IF($AM85="Y","SO mapping must be resolved","Review required")))))) -> No expected close date | AP85: =IF($AK85="Y",TEXT($Y85,"yyyy-mm-dd"),"")
A86: 85 | B86: DPS-0085 | C86: Pattern Body - 3oz Body SCrub-Indigo Rain | D86: PATTERN | E86: PRIMARY | F86: Q4 | G86: Jing Santos | H86: Open | I86: Y | K86: 25000 | L86: 0.75 | M86: 18750 | Q86: 25000 | R86: 0.0% | S86: Open | W86: OK | Z86: 0 | AC86: No SO Yet | AD86: 0 | AE86: 25000 | AF86: Low - Missing Timing | AG86: 2026-05-23 | AI86: =IF(OR($H86="Lost",$H86="Dead"),"Lost",IF($I86<>"Y","Excluded",IF($N86<>"","Converted/Partially Converted",IF($J86="","Watchlist","Active")))) -> Watchlist | AJ86: =IF($I86<>"Y","Not Eligible - Excluded",IF(OR($H86="Lost",$H86="Dead"),"Not Eligible - Lost",IF($J86="","Scenario Only - No Close Date",IF($X86="","Scenario Only - No Ship Date",IF($Y86="","Scenario Only - No Cash Date",IF($AM86="Y","Not Eligible - SO Mapping Review","Eligible")))))) -> Scenario Only - No Close Date | AK86: =IF($AJ86="Eligible","Y","N") -> N | AL86: =SUMIFS(SO_Mapping!$F:$F,SO_Mapping!$A:$A,$B86) -> 0 | AM86: =IF(AND($N86<>"",$AL86=0),"Y",IF(ABS($O86-$AL86)>1,"Y","N")) -> N | AN86: =MAX(0,$K86-$AL86) -> 25000 | AO86: =IF($AK86="Y","Cash eligible",IF($I86<>"Y","Excluded by control flag",IF($J86="","No expected close date",IF($X86="","No ship/invoice timing",IF($Y86="","No cash timing",IF($AM86="Y","SO mapping must be resolved","Review required")))))) -> No expected close date | AP86: =IF($AK86="Y",TEXT($Y86,"yyyy-mm-dd"),"")
A87: 86 | B87: DPS-0086 | C87: Pattern Body - 200ml Body Serum | D87: PATTERN | E87: PRIMARY | F87: Q2 | G87: Jing Santos | H87: Won | I87: Y | J87: 2026-02-10 | K87: 20000 | L87: 0.9 | M87: 18000 | N87: so2556 | O87: 16374 | P87: 2026-02-10 | Q87: 3626 | R87: 81.9% | S87: Partially Converted | W87: OK | X87: 2026-02-10 | Y87: 2026-03-12 | Z87: 0 | AB87: 2026-03-12 | AC87: SO Linked | AD87: 16374 | AE87: 3626 | AF87: High - SO Supported | AG87: 2026-05-23 | AI87: =IF(OR($H87="Lost",$H87="Dead"),"Lost",IF($I87<>"Y","Excluded",IF($N87<>"","Converted/Partially Converted",IF($J87="","Watchlist","Active")))) -> Converted/Partially Converted | AJ87: =IF($I87<>"Y","Not Eligible - Excluded",IF(OR($H87="Lost",$H87="Dead"),"Not Eligible - Lost",IF($J87="","Scenario Only - No Close Date",IF($X87="","Scenario Only - No Ship Date",IF($Y87="","Scenario Only - No Cash Date",IF($AM87="Y","Not Eligible - SO Mapping Review","Eligible")))))) -> Eligible | AK87: =IF($AJ87="Eligible","Y","N") -> Y | AL87: =SUMIFS(SO_Mapping!$F:$F,SO_Mapping!$A:$A,$B87) -> 16374 | AM87: =IF(AND($N87<>"",$AL87=0),"Y",IF(ABS($O87-$AL87)>1,"Y","N")) -> N | AN87: =MAX(0,$K87-$AL87) -> 3626 | AO87: =IF($AK87="Y","Cash eligible",IF($I87<>"Y","Excluded by control flag",IF($J87="","No expected close date",IF($X87="","No ship/invoice timing",IF($Y87="","No cash timing",IF($AM87="Y","SO mapping must be resolved","Review required")))))) -> Cash eligible | AP87: =IF($AK87="Y",TEXT($Y87,"yyyy-mm-dd"),"") -> 2026-03-12
A88: 87 | B88: DPS-0087 | C88: Pattern Body - 200ml Post Shave Oil | D88: PATTERN | E88: PRIMARY | F88: Q1 | G88: Jing Santos | H88: Lost | I88: Y | K88: 20000 | L88: 0.9 | M88: 18000 | Q88: 20000 | R88: 0.0% | S88: Lost | W88: OK | Z88: 0 | AC88: No SO Yet | AD88: 0 | AE88: 20000 | AF88: Low - Missing Timing | AG88: 2026-05-23 | AI88: =IF(OR($H88="Lost",$H88="Dead"),"Lost",IF($I88<>"Y","Excluded",IF($N88<>"","Converted/Partially Converted",IF($J88="","Watchlist","Active")))) -> Lost | AJ88: =IF($I88<>"Y","Not Eligible - Excluded",IF(OR($H88="Lost",$H88="Dead"),"Not Eligible - Lost",IF($J88="","Scenario Only - No Close Date",IF($X88="","Scenario Only - No Ship Date",IF($Y88="","Scenario Only - No Cash Date",IF($AM88="Y","Not Eligible - SO Mapping Review","Eligible")))))) -> Not Eligible - Lost | AK88: =IF($AJ88="Eligible","Y","N") -> N | AL88: =SUMIFS(SO_Mapping!$F:$F,SO_Mapping!$A:$A,$B88) -> 0 | AM88: =IF(AND($N88<>"",$AL88=0),"Y",IF(ABS($O88-$AL88)>1,"Y","N")) -> N | AN88: =MAX(0,$K88-$AL88) -> 20000 | AO88: =IF($AK88="Y","Cash eligible",IF($I88<>"Y","Excluded by control flag",IF($J88="","No expected close date",IF($X88="","No ship/invoice timing",IF($Y88="","No cash timing",IF($AM88="Y","SO mapping must be resolved","Review required")))))) -> No expected close date | AP88: =IF($AK88="Y",TEXT($Y88,"yyyy-mm-dd"),"")
A89: 88 | B89: DPS-0088 | C89: Pattern Body - 150ml Juicy Water Mist | D89: PATTERN | E89: PRIMARY | F89: Q1 | G89: Jing Santos | H89: Lost | I89: Y | K89: 20000 | L89: 0.9 | M89: 18000 | Q89: 20000 | R89: 0.0% | S89: Lost | W89: OK | Z89: 0 | AC89: No SO Yet | AD89: 0 | AE89: 20000 | AF89: Low - Missing Timing | AG89: 2026-05-23 | AI89: =IF(OR($H89="Lost",$H89="Dead"),"Lost",IF($I89<>"Y","Excluded",IF($N89<>"","Converted/Partially Converted",IF($J89="","Watchlist","Active")))) -> Lost | AJ89: =IF($I89<>"Y","Not Eligible - Excluded",IF(OR($H89="Lost",$H89="Dead"),"Not Eligible - Lost",IF($J89="","Scenario Only - No Close Date",IF($X89="","Scenario Only - No Ship Date",IF($Y89="","Scenario Only - No Cash Date",IF($AM89="Y","Not Eligible - SO Mapping Review","Eligible")))))) -> Not Eligible - Lost | AK89: =IF($AJ89="Eligible","Y","N") -> N | AL89: =SUMIFS(SO_Mapping!$F:$F,SO_Mapping!$A:$A,$B89) -> 0 | AM89: =IF(AND($N89<>"",$AL89=0),"Y",IF(ABS($O89-$AL89)>1,"Y","N")) -> N | AN89: =MAX(0,$K89-$AL89) -> 20000 | AO89: =IF($AK89="Y","Cash eligible",IF($I89<>"Y","Excluded by control flag",IF($J89="","No expected close date",IF($X89="","No ship/invoice timing",IF($Y89="","No cash timing",IF($AM89="Y","SO mapping must be resolved","Review required")))))) -> No expected close date | AP89: =IF($AK89="Y",TEXT($Y89,"yyyy-mm-dd"),"")
A90: 89 | B90: DPS-0089 | C90: Power Mask | D90: EPICUREN | E90: TURNKEY | F90: Q4 | G90: Jackie King | H90: Open | I90: Y | K90: 20000 | L90: 0.9 | M90: 18000 | Q90: 20000 | R90: 0.0% | S90: Open | W90: OK | Z90: 0 | AC90: No SO Yet | AD90: 0 | AE90: 20000 | AF90: Low - Missing Timing | AG90: 2026-05-23 | AI90: =IF(OR($H90="Lost",$H90="Dead"),"Lost",IF($I90<>"Y","Excluded",IF($N90<>"","Converted/Partially Converted",IF($J90="","Watchlist","Active")))) -> Watchlist | AJ90: =IF($I90<>"Y","Not Eligible - Excluded",IF(OR($H90="Lost",$H90="Dead"),"Not Eligible - Lost",IF($J90="","Scenario Only - No Close Date",IF($X90="","Scenario Only - No Ship Date",IF($Y90="","Scenario Only - No Cash Date",IF($AM90="Y","Not Eligible - SO Mapping Review","Eligible")))))) -> Scenario Only - No Close Date | AK90: =IF($AJ90="Eligible","Y","N") -> N | AL90: =SUMIFS(SO_Mapping!$F:$F,SO_Mapping!$A:$A,$B90) -> 0 | AM90: =IF(AND($N90<>"",$AL90=0),"Y",IF(ABS($O90-$AL90)>1,"Y","N")) -> N | AN90: =MAX(0,$K90-$AL90) -> 20000 | AO90: =IF($AK90="Y","Cash eligible",IF($I90<>"Y","Excluded by control flag",IF($J90="","No expected close date",IF($X90="","No ship/invoice timing",IF($Y90="","No cash timing",IF($AM90="Y","SO mapping must be resolved","Review required")))))) -> No expected close date | AP90: =IF($AK90="Y",TEXT($Y90,"yyyy-mm-dd"),"")
A91: 90 | B91: DPS-0090 | C91: GET W - 75ml Deostick | D91: GET W | E91: PRIMARY | F91: Q4 | G91: Jing Santos | H91: Open | I91: Y | K91: 65000 | L91: 0.25 | M91: 16250 | Q91: 65000 | R91: 0.0% | S91: Open | W91: OK | Z91: 0 | AC91: No SO Yet | AD91: 0 | AE91: 65000 | AF91: Low - Missing Timing | AG91: 2026-05-23 | AI91: =IF(OR($H91="Lost",$H91="Dead"),"Lost",IF($I91<>"Y","Excluded",IF($N91<>"","Converted/Partially Converted",IF($J91="","Watchlist","Active")))) -> Watchlist | AJ91: =IF($I91<>"Y","Not Eligible - Excluded",IF(OR($H91="Lost",$H91="Dead"),"Not Eligible - Lost",IF($J91="","Scenario Only - No Close Date",IF($X91="","Scenario Only - No Ship Date",IF($Y91="","Scenario Only - No Cash Date",IF($AM91="Y","Not Eligible - SO Mapping Review","Eligible")))))) -> Scenario Only - No Close Date | AK91: =IF($AJ91="Eligible","Y","N") -> N | AL91: =SUMIFS(SO_Mapping!$F:$F,SO_Mapping!$A:$A,$B91) -> 0 | AM91: =IF(AND($N91<>"",$AL91=0),"Y",IF(ABS($O91-$AL91)>1,"Y","N")) -> N | AN91: =MAX(0,$K91-$AL91) -> 65000 | AO91: =IF($AK91="Y","Cash eligible",IF($I91<>"Y","Excluded by control flag",IF($J91="","No expected close date",IF($X91="","No ship/invoice timing",IF($Y91="","No cash timing",IF($AM91="Y","SO mapping must be resolved","Review required")))))) -> No expected close date | AP91: =IF($AK91="Y",TEXT($Y91,"yyyy-mm-dd"),"")
A92: 91 | B92: DPS-0091 | C92: NewULife - Replenishment | D92: NewULife | E92: COPACKING | F92: Q1 | G92: Jackie King | H92: Won | I92: Y | J92: 2026-01-01 | K92: 18000 | L92: 0.9 | M92: 16200 | N92: SO2388 | O92: 18207 | P92: 2026-01-01 | R92: 101.2% | S92: Fully Converted | W92: OK | X92: 2026-01-01 | Y92: 2026-01-31 | Z92: 0 | AB92: 2026-01-31 | AC92: SO Linked | AD92: 18207 | AE92: 0 | AF92: High - SO Supported | AG92: 2026-05-23 | AI92: =IF(OR($H92="Lost",$H92="Dead"),"Lost",IF($I92<>"Y","Excluded",IF($N92<>"","Converted/Partially Converted",IF($J92="","Watchlist","Active")))) -> Converted/Partially Converted | AJ92: =IF($I92<>"Y","Not Eligible - Excluded",IF(OR($H92="Lost",$H92="Dead"),"Not Eligible - Lost",IF($J92="","Scenario Only - No Close Date",IF($X92="","Scenario Only - No Ship Date",IF($Y92="","Scenario Only - No Cash Date",IF($AM92="Y","Not Eligible - SO Mapping Review","Eligible")))))) -> Eligible | AK92: =IF($AJ92="Eligible","Y","N") -> Y | AL92: =SUMIFS(SO_Mapping!$F:$F,SO_Mapping!$A:$A,$B92) -> 18207 | AM92: =IF(AND($N92<>"",$AL92=0),"Y",IF(ABS($O92-$AL92)>1,"Y","N")) -> N | AN92: =MAX(0,$K92-$AL92) -> 0 | AO92: =IF($AK92="Y","Cash eligible",IF($I92<>"Y","Excluded by control flag",IF($J92="","No expected close date",IF($X92="","No ship/invoice timing",IF($Y92="","No cash timing",IF($AM92="Y","SO mapping must be resolved","Review required")))))) -> Cash eligible | AP92: =IF($AK92="Y",TEXT($Y92,"yyyy-mm-dd"),"") -> 2026-01-31
A93: 92 | B93: DPS-0092 | C93: 50ml Hypochlorous Acid Spray | D93: Nemah | E93: PRIMARY | F93: Q3 | G93: Jing Santos | H93: Open | I93: Y | K93: 20000 | L93: 0.75 | M93: 15000 | Q93: 20000 | R93: 0.0% | S93: Open | W93: OK | Z93: 0 | AC93: No SO Yet | AD93: 0 | AE93: 20000 | AF93: Low - Missing Timing | AG93: 2026-05-23 | AI93: =IF(OR($H93="Lost",$H93="Dead"),"Lost",IF($I93<>"Y","Excluded",IF($N93<>"","Converted/Partially Converted",IF($J93="","Watchlist","Active")))) -> Watchlist | AJ93: =IF($I93<>"Y","Not Eligible - Excluded",IF(OR($H93="Lost",$H93="Dead"),"Not Eligible - Lost",IF($J93="","Scenario Only - No Close Date",IF($X93="","Scenario Only - No Ship Date",IF($Y93="","Scenario Only - No Cash Date",IF($AM93="Y","Not Eligible - SO Mapping Review","Eligible")))))) -> Scenario Only - No Close Date | AK93: =IF($AJ93="Eligible","Y","N") -> N | AL93: =SUMIFS(SO_Mapping!$F:$F,SO_Mapping!$A:$A,$B93) -> 0 | AM93: =IF(AND($N93<>"",$AL93=0),"Y",IF(ABS($O93-$AL93)>1,"Y","N")) -> N | AN93: =MAX(0,$K93-$AL93) -> 20000 | AO93: =IF($AK93="Y","Cash eligible",IF($I93<>"Y","Excluded by control flag",IF($J93="","No expected close date",IF($X93="","No ship/invoice timing",IF($Y93="","No cash timing",IF($AM93="Y","SO mapping must be resolved","Review required")))))) -> No expected close date | AP93: =IF($AK93="Y",TEXT($Y93,"yyyy-mm-dd"),"")
A94: 93 | B94: DPS-0093 | C94: Pattern Body - 3oz Mini Body Scrub Jars/Caps | D94: PATTERN | E94: PRIMARY | F94: Q1 | G94: Jing Santos | H94: Lost | I94: Y | K94: 13000 | L94: 0.9 | M94: 11700 | Q94: 13000 | R94: 0.0% | S94: Lost | W94: OK | Z94: 0 | AC94: No SO Yet | AD94: 0 | AE94: 13000 | AF94: Low - Missing Timing | AG94: 2026-05-23 | AI94: =IF(OR($H94="Lost",$H94="Dead"),"Lost",IF($I94<>"Y","Excluded",IF($N94<>"","Converted/Partially Converted",IF($J94="","Watchlist","Active")))) -> Lost | AJ94: =IF($I94<>"Y","Not Eligible - Excluded",IF(OR($H94="Lost",$H94="Dead"),"Not Eligible - Lost",IF($J94="","Scenario Only - No Close Date",IF($X94="","Scenario Only - No Ship Date",IF($Y94="","Scenario Only - No Cash Date",IF($AM94="Y","Not Eligible - SO Mapping Review","Eligible")))))) -> Not Eligible - Lost | AK94: =IF($AJ94="Eligible","Y","N") -> N | AL94: =SUMIFS(SO_Mapping!$F:$F,SO_Mapping!$A:$A,$B94) -> 0 | AM94: =IF(AND($N94<>"",$AL94=0),"Y",IF(ABS($O94-$AL94)>1,"Y","N")) -> N | AN94: =MAX(0,$K94-$AL94) -> 13000 | AO94: =IF($AK94="Y","Cash eligible",IF($I94<>"Y","Excluded by control flag",IF($J94="","No expected close date",IF($X94="","No ship/invoice timing",IF($Y94="","No cash timing",IF($AM94="Y","SO mapping must be resolved","Review required")))))) -> No expected close date | AP94: =IF($AK94="Y",TEXT($Y94,"yyyy-mm-dd"),"")
A95: 94 | B95: DPS-0094 | C95: Pattern Body - 3oz Mini Body Cream Jars/Caps | D95: PATTERN | E95: PRIMARY | F95: Q1 | G95: Jing Santos | H95: Lost | I95: Y | K95: 13000 | L95: 0.9 | M95: 11700 | Q95: 13000 | R95: 0.0% | S95: Lost | W95: OK | Z95: 0 | AC95: No SO Yet | AD95: 0 | AE95: 13000 | AF95: Low - Missing Timing | AG95: 2026-05-23 | AI95: =IF(OR($H95="Lost",$H95="Dead"),"Lost",IF($I95<>"Y","Excluded",IF($N95<>"","Converted/Partially Converted",IF($J95="","Watchlist","Active")))) -> Lost | AJ95: =IF($I95<>"Y","Not Eligible - Excluded",IF(OR($H95="Lost",$H95="Dead"),"Not Eligible - Lost",IF($J95="","Scenario Only - No Close Date",IF($X95="","Scenario Only - No Ship Date",IF($Y95="","Scenario Only - No Cash Date",IF($AM95="Y","Not Eligible - SO Mapping Review","Eligible")))))) -> Not Eligible - Lost | AK95: =IF($AJ95="Eligible","Y","N") -> N | AL95: =SUMIFS(SO_Mapping!$F:$F,SO_Mapping!$A:$A,$B95) -> 0 | AM95: =IF(AND($N95<>"",$AL95=0),"Y",IF(ABS($O95-$AL95)>1,"Y","N")) -> N | AN95: =MAX(0,$K95-$AL95) -> 13000 | AO95: =IF($AK95="Y","Cash eligible",IF($I95<>"Y","Excluded by control flag",IF($J95="","No expected close date",IF($X95="","No ship/invoice timing",IF($Y95="","No cash timing",IF($AM95="Y","SO mapping must be resolved","Review required")))))) -> No expected close date | AP95: =IF($AK95="Y",TEXT($Y95,"yyyy-mm-dd"),"")
A96: 95 | B96: DPS-0095 | C96: 100ml Toothpaste | D96: 3E | E96: PRIMARY | F96: Q3 | G96: Jing Santos | H96: Open | I96: Y | K96: 20000 | L96: 0.5 | M96: 10000 | Q96: 20000 | R96: 0.0% | S96: Open | W96: OK | Z96: 0 | AC96: No SO Yet | AD96: 0 | AE96: 20000 | AF96: Low - Missing Timing | AG96: 2026-05-23 | AI96: =IF(OR($H96="Lost",$H96="Dead"),"Lost",IF($I96<>"Y","Excluded",IF($N96<>"","Converted/Partially Converted",IF($J96="","Watchlist","Active")))) -> Watchlist | AJ96: =IF($I96<>"Y","Not Eligible - Excluded",IF(OR($H96="Lost",$H96="Dead"),"Not Eligible - Lost",IF($J96="","Scenario Only - No Close Date",IF($X96="","Scenario Only - No Ship Date",IF($Y96="","Scenario Only - No Cash Date",IF($AM96="Y","Not Eligible - SO Mapping Review","Eligible")))))) -> Scenario Only - No Close Date | AK96: =IF($AJ96="Eligible","Y","N") -> N | AL96: =SUMIFS(SO_Mapping!$F:$F,SO_Mapping!$A:$A,$B96) -> 0 | AM96: =IF(AND($N96<>"",$AL96=0),"Y",IF(ABS($O96-$AL96)>1,"Y","N")) -> N | AN96: =MAX(0,$K96-$AL96) -> 20000 | AO96: =IF($AK96="Y","Cash eligible",IF($I96<>"Y","Excluded by control flag",IF($J96="","No expected close date",IF($X96="","No ship/invoice timing",IF($Y96="","No cash timing",IF($AM96="Y","SO mapping must be resolved","Review required")))))) -> No expected close date | AP96: =IF($AK96="Y",TEXT($Y96,"yyyy-mm-dd"),"")
A97: 96 | B97: DPS-0096 | C97: 30ml Serum | D97: 3E | E97: PRIMARY | F97: Q3 | G97: Jing Santos | H97: Open | I97: Y | K97: 20000 | L97: 0.5 | M97: 10000 | Q97: 20000 | R97: 0.0% | S97: Open | W97: OK | Z97: 0 | AC97: No SO Yet | AD97: 0 | AE97: 20000 | AF97: Low - Missing Timing | AG97: 2026-05-23 | AI97: =IF(OR($H97="Lost",$H97="Dead"),"Lost",IF($I97<>"Y","Excluded",IF($N97<>"","Converted/Partially Converted",IF($J97="","Watchlist","Active")))) -> Watchlist | AJ97: =IF($I97<>"Y","Not Eligible - Excluded",IF(OR($H97="Lost",$H97="Dead"),"Not Eligible - Lost",IF($J97="","Scenario Only - No Close Date",IF($X97="","Scenario Only - No Ship Date",IF($Y97="","Scenario Only - No Cash Date",IF($AM97="Y","Not Eligible - SO Mapping Review","Eligible")))))) -> Scenario Only - No Close Date | AK97: =IF($AJ97="Eligible","Y","N") -> N | AL97: =SUMIFS(SO_Mapping!$F:$F,SO_Mapping!$A:$A,$B97) -> 0 | AM97: =IF(AND($N97<>"",$AL97=0),"Y",IF(ABS($O97-$AL97)>1,"Y","N")) -> N | AN97: =MAX(0,$K97-$AL97) -> 20000 | AO97: =IF($AK97="Y","Cash eligible",IF($I97<>"Y","Excluded by control flag",IF($J97="","No expected close date",IF($X97="","No ship/invoice timing",IF($Y97="","No cash timing",IF($AM97="Y","SO mapping must be resolved","Review required")))))) -> No expected close date | AP97: =IF($AK97="Y",TEXT($Y97,"yyyy-mm-dd"),"")
A98: 97 | B98: DPS-0097 | C98: 50ml Aura Hair Mist | D98: EMI JAY | E98: PRIMARY | F98: Q2 | G98: Jing Santos | H98: Open | I98: Y | K98: 10000 | L98: 0.8 | M98: 8000 | Q98: 10000 | R98: 0.0% | S98: Open | W98: OK | Z98: 0 | AC98: No SO Yet | AD98: 0 | AE98: 10000 | AF98: Low - Missing Timing | AG98: 2026-05-23 | AI98: =IF(OR($H98="Lost",$H98="Dead"),"Lost",IF($I98<>"Y","Excluded",IF($N98<>"","Converted/Partially Converted",IF($J98="","Watchlist","Active")))) -> Watchlist | AJ98: =IF($I98<>"Y","Not Eligible - Excluded",IF(OR($H98="Lost",$H98="Dead"),"Not Eligible - Lost",IF($J98="","Scenario Only - No Close Date",IF($X98="","Scenario Only - No Ship Date",IF($Y98="","Scenario Only - No Cash Date",IF($AM98="Y","Not Eligible - SO Mapping Review","Eligible")))))) -> Scenario Only - No Close Date | AK98: =IF($AJ98="Eligible","Y","N") -> N | AL98: =SUMIFS(SO_Mapping!$F:$F,SO_Mapping!$A:$A,$B98) -> 0 | AM98: =IF(AND($N98<>"",$AL98=0),"Y",IF(ABS($O98-$AL98)>1,"Y","N")) -> N | AN98: =MAX(0,$K98-$AL98) -> 10000 | AO98: =IF($AK98="Y","Cash eligible",IF($I98<>"Y","Excluded by control flag",IF($J98="","No expected close date",IF($X98="","No ship/invoice timing",IF($Y98="","No cash timing",IF($AM98="Y","SO mapping must be resolved","Review required")))))) -> No expected close date | AP98: =IF($AK98="Y",TEXT($Y98,"yyyy-mm-dd"),"")
A99: 98 | B99: DPS-0098 | C99: 15ml Aura Hair Mist | D99: EMI JAY | E99: PRIMARY | F99: Q2 | G99: Jing Santos | H99: Open | I99: Y | K99: 10000 | L99: 0.8 | M99: 8000 | Q99: 10000 | R99: 0.0% | S99: Open | W99: OK | Z99: 0 | AC99: No SO Yet | AD99: 0 | AE99: 10000 | AF99: Low - Missing Timing | AG99: 2026-05-23 | AI99: =IF(OR($H99="Lost",$H99="Dead"),"Lost",IF($I99<>"Y","Excluded",IF($N99<>"","Converted/Partially Converted",IF($J99="","Watchlist","Active")))) -> Watchlist | AJ99: =IF($I99<>"Y","Not Eligible - Excluded",IF(OR($H99="Lost",$H99="Dead"),"Not Eligible - Lost",IF($J99="","Scenario Only - No Close Date",IF($X99="","Scenario Only - No Ship Date",IF($Y99="","Scenario Only - No Cash Date",IF($AM99="Y","Not Eligible - SO Mapping Review","Eligible")))))) -> Scenario Only - No Close Date | AK99: =IF($AJ99="Eligible","Y","N") -> N | AL99: =SUMIFS(SO_Mapping!$F:$F,SO_Mapping!$A:$A,$B99) -> 0 | AM99: =IF(AND($N99<>"",$AL99=0),"Y",IF(ABS($O99-$AL99)>1,"Y","N")) -> N | AN99: =MAX(0,$K99-$AL99) -> 10000 | AO99: =IF($AK99="Y","Cash eligible",IF($I99<>"Y","Excluded by control flag",IF($J99="","No expected close date",IF($X99="","No ship/invoice timing",IF($Y99="","No cash timing",IF($AM99="Y","SO mapping must be resolved","Review required")))))) -> No expected close date | AP99: =IF($AK99="Y",TEXT($Y99,"yyyy-mm-dd"),"")
A100: 99 | B100: DPS-0099 | C100: 50ml Hair & Body Mist Bottle/Pump | D100: EMI JAY | E100: PRIMARY | F100: Q2 | G100: Jing Santos | H100: Won | I100: Y | J100: 2026-04-20 | K100: 10000 | L100: 0.75 | M100: 7500 | N100: SO2592 | O100: 44550 | P100: 2026-04-20 | R100: 445.5% | S100: Fully Converted | W100: Review SO over pipeline | X100: 2026-04-20 | Y100: 2026-05-20 | Z100: 0 | AB100: 2026-05-20 | AC100: SO Linked | AD100: 44550 | AE100: 0 | AF100: Do Not Use - Data Issue | AG100: 2026-05-23 | AI100: =IF(OR($H100="Lost",$H100="Dead"),"Lost",IF($I100<>"Y","Excluded",IF($N100<>"","Converted/Partially Converted",IF($J100="","Watchlist","Active")))) -> Converted/Partially Converted | AJ100: =IF($I100<>"Y","Not Eligible - Excluded",IF(OR($H100="Lost",$H100="Dead"),"Not Eligible - Lost",IF($J100="","Scenario Only - No Close Date",IF($X100="","Scenario Only - No Ship Date",IF($Y100="","Scenario Only - No Cash Date",IF($AM100="Y","Not Eligible - SO Mapping Review","Eligible")))))) -> Eligible | AK100: =IF($AJ100="Eligible","Y","N") -> Y | AL100: =SUMIFS(SO_Mapping!$F:$F,SO_Mapping!$A:$A,$B100) -> 44550 | AM100: =IF(AND($N100<>"",$AL100=0),"Y",IF(ABS($O100-$AL100)>1,"Y","N")) -> N | AN100: =MAX(0,$K100-$AL100) -> 0 | AO100: =IF($AK100="Y","Cash eligible",IF($I100<>"Y","Excluded by control flag",IF($J100="","No expected close date",IF($X100="","No ship/invoice timing",IF($Y100="","No cash timing",IF($AM100="Y","SO mapping must be resolved","Review required")))))) -> Cash eligible | AP100: =IF($AK100="Y",TEXT($Y100,"yyyy-mm-dd"),"") -> 2026-05-20
A101: 100 | B101: DPS-0100 | C101: MISTR - SACHETS | D101: MISTR | E101: SECONDARY | F101: Q2 | G101: Jackie King | H101: Won | I101: Y | J101: 2026-03-25 | K101: 15000 | L101: 0.5 | M101: 7500 | N101: SO2579, SO2614 | O101: 14295.51 | Q101: 704 | R101: 95.3% | S101: Partially Converted | W101: OK | X101: 2026-03-25 | Y101: 2026-04-24 | Z101: 0 | AB101: 2026-04-24 | AC101: SO Linked | AD101: 14295.51 | AE101: 704.49 | AF101: High - SO Supported | AG101: 2026-05-23 | AI101: =IF(OR($H101="Lost",$H101="Dead"),"Lost",IF($I101<>"Y","Excluded",IF($N101<>"","Converted/Partially Converted",IF($J101="","Watchlist","Active")))) -> Converted/Partially Converted | AJ101: =IF($I101<>"Y","Not Eligible - Excluded",IF(OR($H101="Lost",$H101="Dead"),"Not Eligible - Lost",IF($J101="","Scenario Only - No Close Date",IF($X101="","Scenario Only - No Ship Date",IF($Y101="","Scenario Only - No Cash Date",IF($AM101="Y","Not Eligible - SO Mapping Review","Eligible")))))) -> Not Eligible - SO Mapping Review | AK101: =IF($AJ101="Eligible","Y","N") -> N | AL101: =SUMIFS(SO_Mapping!$F:$F,SO_Mapping!$A:$A,$B101) -> 0 | AM101: =IF(AND($N101<>"",$AL101=0),"Y",IF(ABS($O101-$AL101)>1,"Y","N")) -> Y | AN101: =MAX(0,$K101-$AL101) -> 15000 | AO101: =IF($AK101="Y","Cash eligible",IF($I101<>"Y","Excluded by control flag",IF($J101="","No expected close date",IF($X101="","No ship/invoice timing",IF($Y101="","No cash timing",IF($AM101="Y","SO mapping must be resolved","Review required")))))) -> SO mapping must be resolved | AP101: =IF($AK101="Y",TEXT($Y101,"yyyy-mm-dd"),"")
A102: 101 | B102: DPS-0101 | C102: Multi-Surface Cleaner | D102: SPRAE | E102: PRIMARY | F102: Q4 | G102: Jing Santos | H102: Open | I102: Y | K102: 10000 | L102: 0.25 | M102: 2500 | Q102: 10000 | R102: 0.0% | S102: Open | W102: OK | Z102: 0 | AC102: No SO Yet | AD102: 0 | AE102: 10000 | AF102: Low - Missing Timing | AG102: 2026-05-23 | AI102: =IF(OR($H102="Lost",$H102="Dead"),"Lost",IF($I102<>"Y","Excluded",IF($N102<>"","Converted/Partially Converted",IF($J102="","Watchlist","Active")))) -> Watchlist | AJ102: =IF($I102<>"Y","Not Eligible - Excluded",IF(OR($H102="Lost",$H102="Dead"),"Not Eligible - Lost",IF($J102="","Scenario Only - No Close Date",IF($X102="","Scenario Only - No Ship Date",IF($Y102="","Scenario Only - No Cash Date",IF($AM102="Y","Not Eligible - SO Mapping Review","Eligible")))))) -> Scenario Only - No Close Date | AK102: =IF($AJ102="Eligible","Y","N") -> N | AL102: =SUMIFS(SO_Mapping!$F:$F,SO_Mapping!$A:$A,$B102) -> 0 | AM102: =IF(AND($N102<>"",$AL102=0),"Y",IF(ABS($O102-$AL102)>1,"Y","N")) -> N | AN102: =MAX(0,$K102-$AL102) -> 10000 | AO102: =IF($AK102="Y","Cash eligible",IF($I102<>"Y","Excluded by control flag",IF($J102="","No expected close date",IF($X102="","No ship/invoice timing",IF($Y102="","No cash timing",IF($AM102="Y","SO mapping must be resolved","Review required")))))) -> No expected close date | AP102: =IF($AK102="Y",TEXT($Y102,"yyyy-mm-dd"),"")
A103: 102 | B103: DPS-0102 | C103: Stove Top Cleaner | D103: SPRAE | E103: PRIMARY | F103: Q4 | G103: Jing Santos | H103: Open | I103: Y | K103: 10000 | L103: 0.25 | M103: 2500 | Q103: 10000 | R103: 0.0% | S103: Open | W103: OK | Z103: 0 | AC103: No SO Yet | AD103: 0 | AE103: 10000 | AF103: Low - Missing Timing | AG103: 2026-05-23 | AI103: =IF(OR($H103="Lost",$H103="Dead"),"Lost",IF($I103<>"Y","Excluded",IF($N103<>"","Converted/Partially Converted",IF($J103="","Watchlist","Active")))) -> Watchlist | AJ103: =IF($I103<>"Y","Not Eligible - Excluded",IF(OR($H103="Lost",$H103="Dead"),"Not Eligible - Lost",IF($J103="","Scenario Only - No Close Date",IF($X103="","Scenario Only - No Ship Date",IF($Y103="","Scenario Only - No Cash Date",IF($AM103="Y","Not Eligible - SO Mapping Review","Eligible")))))) -> Scenario Only - No Close Date | AK103: =IF($AJ103="Eligible","Y","N") -> N | AL103: =SUMIFS(SO_Mapping!$F:$F,SO_Mapping!$A:$A,$B103) -> 0 | AM103: =IF(AND($N103<>"",$AL103=0),"Y",IF(ABS($O103-$AL103)>1,"Y","N")) -> N | AN103: =MAX(0,$K103-$AL103) -> 10000 | AO103: =IF($AK103="Y","Cash eligible",IF($I103<>"Y","Excluded by control flag",IF($J103="","No expected close date",IF($X103="","No ship/invoice timing",IF($Y103="","No cash timing",IF($AM103="Y","SO mapping must be resolved","Review required")))))) -> No expected close date | AP103: =IF($AK103="Y",TEXT($Y103,"yyyy-mm-dd"),"")
A104: 103 | B104: DPS-0103 | C104: Bathroom Cleaner | D104: SPRAE | E104: PRIMARY | F104: Q4 | G104: Jing Santos | H104: Open | I104: Y | K104: 10000 | L104: 0.25 | M104: 2500 | Q104: 10000 | R104: 0.0% | S104: Open | W104: OK | Z104: 0 | AC104: No SO Yet | AD104: 0 | AE104: 10000 | AF104: Low - Missing Timing | AG104: 2026-05-23 | AI104: =IF(OR($H104="Lost",$H104="Dead"),"Lost",IF($I104<>"Y","Excluded",IF($N104<>"","Converted/Partially Converted",IF($J104="","Watchlist","Active")))) -> Watchlist | AJ104: =IF($I104<>"Y","Not Eligible - Excluded",IF(OR($H104="Lost",$H104="Dead"),"Not Eligible - Lost",IF($J104="","Scenario Only - No Close Date",IF($X104="","Scenario Only - No Ship Date",IF($Y104="","Scenario Only - No Cash Date",IF($AM104="Y","Not Eligible - SO Mapping Review","Eligible")))))) -> Scenario Only - No Close Date | AK104: =IF($AJ104="Eligible","Y","N") -> N | AL104: =SUMIFS(SO_Mapping!$F:$F,SO_Mapping!$A:$A,$B104) -> 0 | AM104: =IF(AND($N104<>"",$AL104=0),"Y",IF(ABS($O104-$AL104)>1,"Y","N")) -> N | AN104: =MAX(0,$K104-$AL104) -> 10000 | AO104: =IF($AK104="Y","Cash eligible",IF($I104<>"Y","Excluded by control flag",IF($J104="","No expected close date",IF($X104="","No ship/invoice timing",IF($Y104="","No cash timing",IF($AM104="Y","SO mapping must be resolved","Review required")))))) -> No expected close date | AP104: =IF($AK104="Y",TEXT($Y104,"yyyy-mm-dd"),"")
A105: 104 | B105: DPS-0104 | C105: Room Spray | D105: SPRAE | E105: PRIMARY | F105: Q4 | G105: Jing Santos | H105: Open | I105: Y | K105: 10000 | L105: 0.25 | M105: 2500 | Q105: 10000 | R105: 0.0% | S105: Open | W105: OK | Z105: 0 | AC105: No SO Yet | AD105: 0 | AE105: 10000 | AF105: Low - Missing Timing | AG105: 2026-05-23 | AI105: =IF(OR($H105="Lost",$H105="Dead"),"Lost",IF($I105<>"Y","Excluded",IF($N105<>"","Converted/Partially Converted",IF($J105="","Watchlist","Active")))) -> Watchlist | AJ105: =IF($I105<>"Y","Not Eligible - Excluded",IF(OR($H105="Lost",$H105="Dead"),"Not Eligible - Lost",IF($J105="","Scenario Only - No Close Date",IF($X105="","Scenario Only - No Ship Date",IF($Y105="","Scenario Only - No Cash Date",IF($AM105="Y","Not Eligible - SO Mapping Review","Eligible")))))) -> Scenario Only - No Close Date | AK105: =IF($AJ105="Eligible","Y","N") -> N | AL105: =SUMIFS(SO_Mapping!$F:$F,SO_Mapping!$A:$A,$B105) -> 0 | AM105: =IF(AND($N105<>"",$AL105=0),"Y",IF(ABS($O105-$AL105)>1,"Y","N")) -> N | AN105: =MAX(0,$K105-$AL105) -> 10000 | AO105: =IF($AK105="Y","Cash eligible",IF($I105<>"Y","Excluded by control flag",IF($J105="","No expected close date",IF($X105="","No ship/invoice timing",IF($Y105="","No cash timing",IF($AM105="Y","SO mapping must be resolved","Review required")))))) -> No expected close date | AP105: =IF($AK105="Y",TEXT($Y105,"yyyy-mm-dd"),"")
A106: 105 | B106: DPS-0105 | C106: 100ml Body Spray | D106: Practical Alchemy | E106: PRIMARY | F106: Q3 | G106: Jing Santos | H106: Open | I106: Y | K106: 10000 | L106: 0.25 | M106: 2500 | Q106: 10000 | R106: 0.0% | S106: Open | W106: OK | Z106: 0 | AC106: No SO Yet | AD106: 0 | AE106: 10000 | AF106: Low - Missing Timing | AG106: 2026-05-23 | AI106: =IF(OR($H106="Lost",$H106="Dead"),"Lost",IF($I106<>"Y","Excluded",IF($N106<>"","Converted/Partially Converted",IF($J106="","Watchlist","Active")))) -> Watchlist | AJ106: =IF($I106<>"Y","Not Eligible - Excluded",IF(OR($H106="Lost",$H106="Dead"),"Not Eligible - Lost",IF($J106="","Scenario Only - No Close Date",IF($X106="","Scenario Only - No Ship Date",IF($Y106="","Scenario Only - No Cash Date",IF($AM106="Y","Not Eligible - SO Mapping Review","Eligible")))))) -> Scenario Only - No Close Date | AK106: =IF($AJ106="Eligible","Y","N") -> N | AL106: =SUMIFS(SO_Mapping!$F:$F,SO_Mapping!$A:$A,$B106) -> 0 | AM106: =IF(AND($N106<>"",$AL106=0),"Y",IF(ABS($O106-$AL106)>1,"Y","N")) -> N | AN106: =MAX(0,$K106-$AL106) -> 10000 | AO106: =IF($AK106="Y","Cash eligible",IF($I106<>"Y","Excluded by control flag",IF($J106="","No expected close date",IF($X106="","No ship/invoice timing",IF($Y106="","No cash timing",IF($AM106="Y","SO mapping must be resolved","Review required")))))) -> No expected close date | AP106: =IF($AK106="Y",TEXT($Y106,"yyyy-mm-dd"),"")
A107: 106 | B107: DPS-0106 | C107: 15ml Deostick | D107: Practical Alchemy | E107: PRIMARY | F107: Q3 | G107: Jing Santos | H107: Open | I107: Y | K107: 10000 | L107: 0.25 | M107: 2500 | Q107: 10000 | R107: 0.0% | S107: Open | W107: OK | Z107: 0 | AC107: No SO Yet | AD107: 0 | AE107: 10000 | AF107: Low - Missing Timing | AG107: 2026-05-23 | AI107: =IF(OR($H107="Lost",$H107="Dead"),"Lost",IF($I107<>"Y","Excluded",IF($N107<>"","Converted/Partially Converted",IF($J107="","Watchlist","Active")))) -> Watchlist | AJ107: =IF($I107<>"Y","Not Eligible - Excluded",IF(OR($H107="Lost",$H107="Dead"),"Not Eligible - Lost",IF($J107="","Scenario Only - No Close Date",IF($X107="","Scenario Only - No Ship Date",IF($Y107="","Scenario Only - No Cash Date",IF($AM107="Y","Not Eligible - SO Mapping Review","Eligible")))))) -> Scenario Only - No Close Date | AK107: =IF($AJ107="Eligible","Y","N") -> N | AL107: =SUMIFS(SO_Mapping!$F:$F,SO_Mapping!$A:$A,$B107) -> 0 | AM107: =IF(AND($N107<>"",$AL107=0),"Y",IF(ABS($O107-$AL107)>1,"Y","N")) -> N | AN107: =MAX(0,$K107-$AL107) -> 10000 | AO107: =IF($AK107="Y","Cash eligible",IF($I107<>"Y","Excluded by control flag",IF($J107="","No expected close date",IF($X107="","No ship/invoice timing",IF($Y107="","No cash timing",IF($AM107="Y","SO mapping must be resolved","Review required")))))) -> No expected close date | AP107: =IF($AK107="Y",TEXT($Y107,"yyyy-mm-dd"),"")
A108: 3 | B108: DPS-0003 | C108: HYDRATION - 5 SKUs | D108: HANX | E108: TURNKEY | F108: Q4 | G108: Jackie King | H108: Open | I108: Y | J108: 2026-01-01 | K108: 2000000 | L108: 0 | Q108: 2000000 | R108: 0.0% | S108: Open | T108: STALE | W108: OK | X108: 2026-01-01 | Y108: 2026-01-31 | Z108: 0 | AB108: 2026-01-31 | AC108: No SO Yet | AD108: 0 | AE108: 2000000 | AF108: Medium - Pipeline Date Only | AG108: 2026-05-23 | AI108: =IF(OR($H108="Lost",$H108="Dead"),"Lost",IF($I108<>"Y","Excluded",IF($N108<>"","Converted/Partially Converted",IF($J108="","Watchlist","Active")))) -> Active | AJ108: =IF($I108<>"Y","Not Eligible - Excluded",IF(OR($H108="Lost",$H108="Dead"),"Not Eligible - Lost",IF($J108="","Scenario Only - No Close Date",IF($X108="","Scenario Only - No Ship Date",IF($Y108="","Scenario Only - No Cash Date",IF($AM108="Y","Not Eligible - SO Mapping Review","Eligible")))))) -> Eligible | AK108: =IF($AJ108="Eligible","Y","N") -> Y | AL108: =SUMIFS(SO_Mapping!$F:$F,SO_Mapping!$A:$A,$B108) -> 0 | AM108: =IF(AND($N108<>"",$AL108=0),"Y",IF(ABS($O108-$AL108)>1,"Y","N")) -> N | AN108: =MAX(0,$K108-$AL108) -> 2000000 | AO108: =IF($AK108="Y","Cash eligible",IF($I108<>"Y","Excluded by control flag",IF($J108="","No expected close date",IF($X108="","No ship/invoice timing",IF($Y108="","No cash timing",IF($AM108="Y","SO mapping must be resolved","Review required")))))) -> Cash eligible | AP108: =IF($AK108="Y",TEXT($Y108,"yyyy-mm-dd"),"") -> 2026-01-31
A109: 8 | B109: DPS-0008 | C109: HYDRATION - 5 SKUs | D109: HANX | E109: TURNKEY | F109: Q3 | G109: Jackie King | H109: Open | I109: Y | J109: 2026-01-01 | K109: 1000000 | L109: 0 | Q109: 1000000 | R109: 0.0% | S109: Open | T109: STALE | W109: OK | X109: 2026-01-01 | Y109: 2026-01-31 | Z109: 0 | AB109: 2026-01-31 | AC109: No SO Yet | AD109: 0 | AE109: 1000000 | AF109: Medium - Pipeline Date Only | AG109: 2026-05-23 | AI109: =IF(OR($H109="Lost",$H109="Dead"),"Lost",IF($I109<>"Y","Excluded",IF($N109<>"","Converted/Partially Converted",IF($J109="","Watchlist","Active")))) -> Active | AJ109: =IF($I109<>"Y","Not Eligible - Excluded",IF(OR($H109="Lost",$H109="Dead"),"Not Eligible - Lost",IF($J109="","Scenario Only - No Close Date",IF($X109="","Scenario Only - No Ship Date",IF($Y109="","Scenario Only - No Cash Date",IF($AM109="Y","Not Eligible - SO Mapping Review","Eligible")))))) -> Eligible | AK109: =IF($AJ109="Eligible","Y","N") -> Y | AL109: =SUMIFS(SO_Mapping!$F:$F,SO_Mapping!$A:$A,$B109) -> 0 | AM109: =IF(AND($N109<>"",$AL109=0),"Y",IF(ABS($O109-$AL109)>1,"Y","N")) -> N | AN109: =MAX(0,$K109-$AL109) -> 1000000 | AO109: =IF($AK109="Y","Cash eligible",IF($I109<>"Y","Excluded by control flag",IF($J109="","No expected close date",IF($X109="","No ship/invoice timing",IF($Y109="","No cash timing",IF($AM109="Y","SO mapping must be resolved","Review required")))))) -> Cash eligible | AP109: =IF($AK109="Y",TEXT($Y109,"yyyy-mm-dd"),"") -> 2026-01-31
...

Sheet SO_Mapping
A1: Deal ID | B1: SO Number | C1: SO Status Text | D1: Source SO Amount | E1: Allocation % | F1: Allocated SO Amount | G1: Legacy Aggregate Approved SO Amount | H1: Allocation Review Required | I1: Notes
A2: DPS-0002 | B2: SO2599 | C2: Legacy listed | F2: =IF(OR($D2="",$E2=""),0,$D2*$E2) -> 0 | G2: 2672706 | H2: Y | I2: Multiple SOs listed; requires SO source amount/allocation before liquidity feed.
A3: DPS-0002 | B3: SO2597 | C3: Legacy listed | F3: =IF(OR($D3="",$E3=""),0,$D3*$E3) -> 0 | G3: 2672706 | H3: Y | I3: Multiple SOs listed; requires SO source amount/allocation before liquidity feed.
A4: DPS-0002 | B4: SO2598 | C4: Legacy listed | F4: =IF(OR($D4="",$E4=""),0,$D4*$E4) -> 0 | G4: 2672706 | H4: Y | I4: Multiple SOs listed; requires SO source amount/allocation before liquidity feed.
A5: DPS-0002 | B5: SO2608 | C5: Legacy listed | F5: =IF(OR($D5="",$E5=""),0,$D5*$E5) -> 0 | G5: 2672706 | H5: Y | I5: Multiple SOs listed; requires SO source amount/allocation before liquidity feed.
A6: DPS-0002 | B6: SO2609 | C6: Legacy listed | F6: =IF(OR($D6="",$E6=""),0,$D6*$E6) -> 0 | G6: 2672706 | H6: Y | I6: Multiple SOs listed; requires SO source amount/allocation before liquidity feed.
A7: DPS-0002 | B7: SO2610 | C7: Legacy listed | F7: =IF(OR($D7="",$E7=""),0,$D7*$E7) -> 0 | G7: 2672706 | H7: Y | I7: Multiple SOs listed; requires SO source amount/allocation before liquidity feed.
A8: DPS-0002 | B8: SO2611 | C8: Legacy listed | F8: =IF(OR($D8="",$E8=""),0,$D8*$E8) -> 0 | G8: 2672706 | H8: Y | I8: Multiple SOs listed; requires SO source amount/allocation before liquidity feed.
A9: DPS-0002 | B9: SO2612 | C9: Legacy listed | F9: =IF(OR($D9="",$E9=""),0,$D9*$E9) -> 0 | G9: 2672706 | H9: Y | I9: Multiple SOs listed; requires SO source amount/allocation before liquidity feed.
A10: DPS-0002 | B10: SO2613 | C10: Legacy listed | F10: =IF(OR($D10="",$E10=""),0,$D10*$E10) -> 0 | G10: 2672706 | H10: Y | I10: Multiple SOs listed; requires SO source amount/allocation before liquidity feed.
A11: DPS-0004 | B11: SO2601 | C11: Legacy listed | F11: =IF(OR($D11="",$E11=""),0,$D11*$E11) -> 0 | G11: 290080 | H11: Y | I11: Multiple SOs listed; requires SO source amount/allocation before liquidity feed.
A12: DPS-0004 | B12: SO2602 | C12: Legacy listed | F12: =IF(OR($D12="",$E12=""),0,$D12*$E12) -> 0 | G12: 290080 | H12: Y | I12: Multiple SOs listed; requires SO source amount/allocation before liquidity feed.
A13: DPS-0005 | B13: SO2563 | C13: Invoiced/Open per legacy note | F13: =IF(OR($D13="",$E13=""),0,$D13*$E13) -> 0 | G13: 1114750 | H13: Y | I13: Multiple SOs listed; requires SO source amount/allocation before liquidity feed.
... A25: DPS-0011 | B25: SO2551 | C25: Invoiced/Open per legacy note | F25: =IF(OR($D25="",$E25=""),0,$D25*$E25) -> 0 | G25: 65518 | H25: Y | I25: Multiple SOs listed; requires SO source amount/allocation before liquidity feed.
A26: DPS-0012 | B26: SO2554 | C26: Legacy listed | D26: 280000 | E26: 1 | F26: =IF(OR($D26="",$E26=""),0,$D26*$E26) -> 280000 | G26: 280000 | H26: N | I26: Single SO legacy amount used; verify against SO source.
A27: DPS-0013 | B27: SO2528 | C27: Legacy listed | F27: =IF(OR($D27="",$E27=""),0,$D27*$E27) -> 0 | G27: 380572 | H27: Y | I27: Multiple SOs listed; requires SO source amount/allocation before liquidity feed.
A28: DPS-0013 | B28: SO2492 | C28: Legacy listed | F28: =IF(OR($D28="",$E28=""),0,$D28*$E28) -> 0 | G28: 380572 | H28: Y | I28: Multiple SOs listed; requires SO source amount/allocation before liquidity feed.
A29: DPS-0013 | B29: SO2508 | C29: Legacy listed | F29: =IF(OR($D29="",$E29=""),0,$D29*$E29) -> 0 | G29: 380572 | H29: Y | I29: Multiple SOs listed; requires SO source amount/allocation before liquidity feed.
A30: DPS-0017 | B30: SO2605 | C30: Legacy listed | D30: 104760 | E30: 1 | F30: =IF(OR($D30="",$E30=""),0,$D30*$E30) -> 104760 | G30: 104760 | H30: N | I30: Single SO legacy amount used; verify against SO source.
A31: DPS-0018 | B31: SO2588 | C31: Legacy listed | D31: 88161 | E31: 1 | F31: =IF(OR($D31="",$E31=""),0,$D31*$E31) -> 88161 | G31: 88161 | H31: N | I31: Single SO legacy amount used; verify against SO source.
A32: DPS-0022 | B32: SO2604 | C32: Legacy listed | D32: 69832 | E32: 1 | F32: =IF(OR($D32="",$E32=""),0,$D32*$E32) -> 69832 | G32: 69832 | H32: N | I32: Single SO legacy amount used; verify against SO source.
A33: DPS-0024 | B33: SO2527 | C33: Legacy listed | F33: =IF(OR($D33="",$E33=""),0,$D33*$E33) -> 0 | G33: 235494 | H33: Y | I33: Multiple SOs listed; requires SO source amount/allocation before liquidity feed.
A34: DPS-0024 | B34: SO2578 | C34: Legacy listed | F34: =IF(OR($D34="",$E34=""),0,$D34*$E34) -> 0 | G34: 235494 | H34: Y | I34: Multiple SOs listed; requires SO source amount/allocation before liquidity feed.
A35: DPS-0024 | B35: SO2580 | C35: Legacy listed | F35: =IF(OR($D35="",$E35=""),0,$D35*$E35) -> 0 | G35: 235494 | H35: Y | I35: Multiple SOs listed; requires SO source amount/allocation before liquidity feed.
A36: DPS-0024 | B36: SO2581 | C36: Legacy listed | F36: =IF(OR($D36="",$E36=""),0,$D36*$E36) -> 0 | G36: 235494 | H36: Y | I36: Multiple SOs listed; requires SO source amount/allocation before liquidity feed.
A37: DPS-0024 | B37: SO2582 | C37: Legacy listed | F37: =IF(OR($D37="",$E37=""),0,$D37*$E37) -> 0 | G37: 235494 | H37: Y | I37: Multiple SOs listed; requires SO source amount/allocation before liquidity feed.
A38: DPS-0025 | B38: SO2538 | C38: Legacy listed | D38: 149215 | E38: 1 | F38: =IF(OR($D38="",$E38=""),0,$D38*$E38) -> 149215 | G38: 149215 | H38: N | I38: Single SO legacy amount used; verify against SO source.
A39: DPS-0027 | B39: SO2525 | C39: Legacy listed | F39: =IF(OR($D39="",$E39=""),0,$D39*$E39) -> 0 | G39: 129603 | H39: Y | I39: Multiple SOs listed; requires SO source amount/allocation before liquidity feed.
A40: DPS-0027 | B40: SO2511 | C40: Legacy listed | F40: =IF(OR($D40="",$E40=""),0,$D40*$E40) -> 0 | G40: 129603 | H40: Y | I40: Multiple SOs listed; requires SO source amount/allocation before liquidity feed.
A41: DPS-0032 | B41: SO2509 | C41: Legacy listed | F41: =IF(OR($D41="",$E41=""),0,$D41*$E41) -> 0 | G41: 102846.84 | H41: Y | I41: Multiple SOs listed; requires SO source amount/allocation before liquidity feed.
A42: DPS-0032 | B42: SO2566 | C42: Legacy listed | F42: =IF(OR($D42="",$E42=""),0,$D42*$E42) -> 0 | G42: 102846.84 | H42: Y | I42: Multiple SOs listed; requires SO source amount/allocation before liquidity feed.
A43: DPS-0036 | B43: SO2560 | C43: Legacy listed | D43: 33908.75 | E43: 1 | F43: =IF(OR($D43="",$E43=""),0,$D43*$E43) -> 33908.75 | G43: 33908.75 | H43: N | I43: Single SO legacy amount used; verify against SO source.
A44: DPS-0039 | B44: SO2603 | C44: Legacy listed | F44: =IF(OR($D44="",$E44=""),0,$D44*$E44) -> 0 | G44: 27122 | H44: Y | I44: Multiple SOs listed; requires SO source amount/allocation before liquidity feed.
A45: DPS-0039 | B45: SO2604 | C45: Legacy listed | F45: =IF(OR($D45="",$E45=""),0,$D45*$E45) -> 0 | G45: 27122 | H45: Y | I45: Multiple SOs listed; requires SO source amount/allocation before liquidity feed.
A46: DPS-0041 | B46: SO2565 | C46: Legacy listed | D46: 61098 | E46: 1 | F46: =IF(OR($D46="",$E46=""),0,$D46*$E46) -> 61098 | G46: 61098 | H46: N | I46: Single SO legacy amount used; verify against SO source.
A47: DPS-0051 | B47: SO2505 | C47: Legacy listed | D47: 40275 | E47: 1 | F47: =IF(OR($D47="",$E47=""),0,$D47*$E47) -> 40275 | G47: 40275 | H47: N | I47: Single SO legacy amount used; verify against SO source.
A48: DPS-0052 | B48: SO2523 | C48: Legacy listed | D48: 46450 | E48: 1 | F48: =IF(OR($D48="",$E48=""),0,$D48*$E48) -> 46450 | G48: 46450 | H48: N | I48: Single SO legacy amount used; verify against SO source.
A49: DPS-0053 | B49: SO2510 | C49: Legacy listed | D49: 63164 | E49: 1 | F49: =IF(OR($D49="",$E49=""),0,$D49*$E49) -> 63164 | G49: 63164 | H49: N | I49: Single SO legacy amount used; verify against SO source.
A50: DPS-0071 | B50: SO2571 | C50: Legacy listed | D50: 29000 | E50: 1 | F50: =IF(OR($D50="",$E50=""),0,$D50*$E50) -> 29000 | G50: 29000 | H50: N | I50: Single SO legacy amount used; verify against SO source.
A51: DPS-0076 | B51: SO2591 | C51: Legacy listed | F51: =IF(OR($D51="",$E51=""),0,$D51*$E51) -> 0 | G51: 60568 | H51: Y | I51: Multiple SOs listed; requires SO source amount/allocation before liquidity feed.
A52: DPS-0076 | B52: SO2615 | C52: Legacy listed | F52: =IF(OR($D52="",$E52=""),0,$D52*$E52) -> 0 | G52: 60568 | H52: Y | I52: Multiple SOs listed; requires SO source amount/allocation before liquidity feed.
A53: DPS-0086 | B53: SO2556 | C53: Legacy listed | D53: 16374 | E53: 1 | F53: =IF(OR($D53="",$E53=""),0,$D53*$E53) -> 16374 | G53: 16374 | H53: N | I53: Single SO legacy amount used; verify against SO source.
A54: DPS-0091 | B54: SO2388 | C54: Legacy listed | D54: 18207 | E54: 1 | F54: =IF(OR($D54="",$E54=""),0,$D54*$E54) -> 18207 | G54: 18207 | H54: N | I54: Single SO legacy amount used; verify against SO source.
A55: DPS-0099 | B55: SO2592 | C55: Legacy listed | D55: 44550 | E55: 1 | F55: =IF(OR($D55="",$E55=""),0,$D55*$E55) -> 44550 | G55: 44550 | H55: N | I55: Single SO legacy amount used; verify against SO source.
A56: DPS-0100 | B56: SO2579 | C56: Legacy listed | F56: =IF(OR($D56="",$E56=""),0,$D56*$E56) -> 0 | G56: 14295.51 | H56: Y | I56: Multiple SOs listed; requires SO source amount/allocation before liquidity feed.
A57: DPS-0100 | B57: SO2614 | C57: Legacy listed | F57: =IF(OR($D57="",$E57=""),0,$D57*$E57) -> 0 | G57: 14295.51 | H57: Y | I57: Multiple SOs listed; requires SO source amount/allocation before liquidity feed.

Sheet SO_Source
A1: SO Number | B1: Customer | C1: SO Date | D1: Expected Ship/Invoice Date | E1: SO Amount | F1: Invoiced Amount | G1: Open Amount | H1: Status | I1: Linked Deal ID | J1: Source File/Export Date | K1: Notes
A2: SO2599 | I2: DPS-0002 | K2: Populate from NetSuite SO export
A3: SO2597 | I3: DPS-0002 | K3: Populate from NetSuite SO export
A4: SO2598 | I4: DPS-0002 | K4: Populate from NetSuite SO export
A5: SO2608 | I5: DPS-0002 | K5: Populate from NetSuite SO export
A6: SO2609 | I6: DPS-0002 | K6: Populate from NetSuite SO export
A7: SO2610 | I7: DPS-0002 | K7: Populate from NetSuite SO export
A8: SO2611 | I8: DPS-0002 | K8: Populate from NetSuite SO export
A9: SO2612 | I9: DPS-0002 | K9: Populate from NetSuite SO export
A10: SO2613 | I10: DPS-0002 | K10: Populate from NetSuite SO export
A11: SO2601 | I11: DPS-0004 | K11: Populate from NetSuite SO export
A12: SO2602 | I12: DPS-0004 | K12: Populate from NetSuite SO export
A13: SO2563 | I13: DPS-0005 | K13: Populate from NetSuite SO export
... A56: SO2614 | I56: DPS-0100 | K56: Populate from NetSuite SO export

Sheet Cash_Eligibility
A1: Deal ID | B1: Customer | C1: Sales Rep | D1: Pipeline Amount | E1: Expected Close Date | F1: Expected Ship/Invoice Date | G1: Expected Cash Date | H1: Pipeline Visibility | I1: Cash Forecast Eligibility | J1: Liquidity Feed Eligible | K1: Mapped SO Amount | L1: SO Mapping Review Required | M1: Remaining Pipeline - Mapping Safe | N1: Eligibility Reason
A2: =Pipeline_Control!B2 -> DPS-0002 | B2: =Pipeline_Control!D2 -> SDJ | C2: =Pipeline_Control!G2 -> Danny Park | D2: =Pipeline_Control!K2 -> 3000000 | E2: =Pipeline_Control!J2 -> 2026-04-30 | F2: =Pipeline_Control!X2 -> 2026-04-30 | G2: =Pipeline_Control!Y2 -> 2026-05-30 | H2: =Pipeline_Control!AI2 -> Converted/Partially Converted | I2: =Pipeline_Control!AJ2 -> Not Eligible - SO Mapping Review | J2: =Pipeline_Control!AK2 -> N | K2: =Pipeline_Control!AL2 -> 0 | L2: =Pipeline_Control!AM2 -> Y | M2: =Pipeline_Control!AN2 -> 3000000 | N2: =Pipeline_Control!AO2 -> SO mapping must be resolved
A3: =Pipeline_Control!B3 -> DPS-0004 | B3: =Pipeline_Control!D3 -> SDJ | C3: =Pipeline_Control!G3 -> Danny Park | D3: =Pipeline_Control!K3 -> 1560000 | E3: =Pipeline_Control!J3 -> 2026-05-06 | F3: =Pipeline_Control!X3 -> 2026-05-06 | G3: =Pipeline_Control!Y3 -> 2026-06-05 | H3: =Pipeline_Control!AI3 -> Converted/Partially Converted | I3: =Pipeline_Control!AJ3 -> Not Eligible - SO Mapping Review | J3: =Pipeline_Control!AK3 -> N | K3: =Pipeline_Control!AL3 -> 0 | L3: =Pipeline_Control!AM3 -> Y | M3: =Pipeline_Control!AN3 -> 1560000 | N3: =Pipeline_Control!AO3 -> SO mapping must be resolved
A4: =Pipeline_Control!B4 -> DPS-0005 | B4: =Pipeline_Control!D4 -> SDJ | C4: =Pipeline_Control!G4 -> Danny Park | D4: =Pipeline_Control!K4 -> 1500000 | E4: =Pipeline_Control!J4 -> 2026-02-25 | F4: =Pipeline_Control!X4 -> 2026-02-25 | G4: =Pipeline_Control!Y4 -> 2026-03-27 | H4: =Pipeline_Control!AI4 -> Converted/Partially Converted | I4: =Pipeline_Control!AJ4 -> Not Eligible - SO Mapping Review | J4: =Pipeline_Control!AK4 -> N | K4: =Pipeline_Control!AL4 -> 0 | L4: =Pipeline_Control!AM4 -> Y | M4: =Pipeline_Control!AN4 -> 1500000 | N4: =Pipeline_Control!AO4 -> SO mapping must be resolved
A5: =Pipeline_Control!B5 -> DPS-0006 | B5: =Pipeline_Control!D5 -> SDJ | C5: =Pipeline_Control!G5 -> Danny Park | D5: =Pipeline_Control!K5 -> 1150000 | E5: =Pipeline_Control!J5 -> 2026-01-15 | F5: =Pipeline_Control!X5 -> 2026-01-15 | G5: =Pipeline_Control!Y5 -> 2026-02-14 | H5: =Pipeline_Control!AI5 -> Converted/Partially Converted | I5: =Pipeline_Control!AJ5 -> Not Eligible - SO Mapping Review | J5: =Pipeline_Control!AK5 -> N | K5: =Pipeline_Control!AL5 -> 0 | L5: =Pipeline_Control!AM5 -> Y | M5: =Pipeline_Control!AN5 -> 1150000 | N5: =Pipeline_Control!AO5 -> SO mapping must be resolved
A6: =Pipeline_Control!B6 -> DPS-0007 | B6: =Pipeline_Control!D6 -> SDJ | C6: =Pipeline_Control!G6 -> Danny Park | D6: =Pipeline_Control!K6 -> 1100000 | E6: =Pipeline_Control!J6 -> 0 | F6: =Pipeline_Control!X6 -> 0 | G6: =Pipeline_Control!Y6 -> 0 | H6: =Pipeline_Control!AI6 -> Watchlist | I6: =Pipeline_Control!AJ6 -> Scenario Only - No Close Date | J6: =Pipeline_Control!AK6 -> N | K6: =Pipeline_Control!AL6 -> 0 | L6: =Pipeline_Control!AM6 -> N | M6: =Pipeline_Control!AN6 -> 1100000 | N6: =Pipeline_Control!AO6 -> No expected close date
A7: =Pipeline_Control!B7 -> DPS-0009 | B7: =Pipeline_Control!D7 -> SDJ | C7: =Pipeline_Control!G7 -> Danny Park | D7: =Pipeline_Control!K7 -> 500000 | E7: =Pipeline_Control!J7 -> 0 | F7: =Pipeline_Control!X7 -> 0 | G7: =Pipeline_Control!Y7 -> 0 | H7: =Pipeline_Control!AI7 -> Watchlist | I7: =Pipeline_Control!AJ7 -> Scenario Only - No Close Date | J7: =Pipeline_Control!AK7 -> N | K7: =Pipeline_Control!AL7 -> 0 | L7: =Pipeline_Control!AM7 -> N | M7: =Pipeline_Control!AN7 -> 500000 | N7: =Pipeline_Control!AO7 -> No expected close date
A8: =Pipeline_Control!B8 -> DPS-0011 | B8: =Pipeline_Control!D8 -> SDJ | C8: =Pipeline_Control!G8 -> Danny Park | D8: =Pipeline_Control!K8 -> 500000 | E8: =Pipeline_Control!J8 -> 2026-04-28 | F8: =Pipeline_Control!X8 -> 2026-04-28 | G8: =Pipeline_Control!Y8 -> 2026-05-28 | H8: =Pipeline_Control!AI8 -> Converted/Partially Converted | I8: =Pipeline_Control!AJ8 -> Not Eligible - SO Mapping Review | J8: =Pipeline_Control!AK8 -> N | K8: =Pipeline_Control!AL8 -> 0 | L8: =Pipeline_Control!AM8 -> Y | M8: =Pipeline_Control!AN8 -> 500000 | N8: =Pipeline_Control!AO8 -> SO mapping must be resolved
A9: =Pipeline_Control!B9 -> DPS-0012 | B9: =Pipeline_Control!D9 -> TOWER 28 | C9: =Pipeline_Control!G9 -> Jackie King | D9: =Pipeline_Control!K9 -> 275000 | E9: =Pipeline_Control!J9 -> 2026-02-09 | F9: =Pipeline_Control!X9 -> 2026-02-09 | G9: =Pipeline_Control!Y9 -> 2026-03-11 | H9: =Pipeline_Control!AI9 -> Converted/Partially Converted | I9: =Pipeline_Control!AJ9 -> Eligible | J9: =Pipeline_Control!AK9 -> Y | K9: =Pipeline_Control!AL9 -> 280000 | L9: =Pipeline_Control!AM9 -> N | M9: =Pipeline_Control!AN9 -> 0 | N9: =Pipeline_Control!AO9 -> Cash eligible
A10: =Pipeline_Control!B10 -> DPS-0013 | B10: =Pipeline_Control!D10 -> RO | C10: =Pipeline_Control!G10 -> Jing Santos | D10: =Pipeline_Control!K10 -> 300000 | E10: =Pipeline_Control!J10 -> 2026-01-08 | F10: =Pipeline_Control!X10 -> 2026-01-08 | G10: =Pipeline_Control!Y10 -> 2026-02-07 | H10: =Pipeline_Control!AI10 -> Converted/Partially Converted | I10: =Pipeline_Control!AJ10 -> Not Eligible - SO Mapping Review | J10: =Pipeline_Control!AK10 -> N | K10: =Pipeline_Control!AL10 -> 0 | L10: =Pipeline_Control!AM10 -> Y | M10: =Pipeline_Control!AN10 -> 300000 | N10: =Pipeline_Control!AO10 -> SO mapping must be resolved
A11: =Pipeline_Control!B11 -> DPS-0014 | B11: =Pipeline_Control!D11 -> HAVEN HEALTH | C11: =Pipeline_Control!G11 -> Jackie King | D11: =Pipeline_Control!K11 -> 340000 | E11: =Pipeline_Control!J11 -> 0 | F11: =Pipeline_Control!X11 -> 0 | G11: =Pipeline_Control!Y11 -> 0 | H11: =Pipeline_Control!AI11 -> Watchlist | I11: =Pipeline_Control!AJ11 -> Scenario Only - No Close Date | J11: =Pipeline_Control!AK11 -> N | K11: =Pipeline_Control!AL11 -> 0 | L11: =Pipeline_Control!AM11 -> N | M11: =Pipeline_Control!AN11 -> 340000 | N11: =Pipeline_Control!AO11 -> No expected close date
A12: =Pipeline_Control!B12 -> DPS-0015 | B12: =Pipeline_Control!D12 -> SDJ | C12: =Pipeline_Control!G12 -> Danny Park | D12: =Pipeline_Control!K12 -> 300000 | E12: =Pipeline_Control!J12 -> 0 | F12: =Pipeline_Control!X12 -> 0 | G12: =Pipeline_Control!Y12 -> 0 | H12: =Pipeline_Control!AI12 -> Watchlist | I12: =Pipeline_Control!AJ12 -> Scenario Only - No Close Date | J12: =Pipeline_Control!AK12 -> N | K12: =Pipeline_Control!AL12 -> 0 | L12: =Pipeline_Control!AM12 -> N | M12: =Pipeline_Control!AN12 -> 300000 | N12: =Pipeline_Control!AO12 -> No expected close date
A13: =Pipeline_Control!B13 -> DPS-0016 | B13: =Pipeline_Control!D13 -> PATTERN | C13: =Pipeline_Control!G13 -> Jing Santos | D13: =Pipeline_Control!K13 -> 300000 | E13: =Pipeline_Control!J13 -> 0 | F13: =Pipeline_Control!X13 -> 0 | G13: =Pipeline_Control!Y13 -> 0 | H13: =Pipeline_Control!AI13 -> Watchlist | I13: =Pipeline_Control!AJ13 -> Scenario Only - No Close Date | J13: =Pipeline_Control!AK13 -> N | K13: =Pipeline_Control!AL13 -> 0 | L13: =Pipeline_Control!AM13 -> N | M13: =Pipeline_Control!AN13 -> 300000 | N13: =Pipeline_Control!AO13 -> No expected close date
... A111: =Pipeline_Control!B111 -> DPS-0112 | B111: =Pipeline_Control!D111 -> 0 | C111: =Pipeline_Control!G111 -> 0 | D111: =Pipeline_Control!K111 -> 0 | E111: =Pipeline_Control!J111 -> 0 | F111: =Pipeline_Control!X111 -> 0 | G111: =Pipeline_Control!Y111 -> 0 | H111: =Pipeline_Control!AI111 -> Watchlist | I111: =Pipeline_Control!AJ111 -> Scenario Only - No Close Date | J111: =Pipeline_Control!AK111 -> N | K111: =Pipeline_Control!AL111 -> 0 | L111: =Pipeline_Control!AM111 -> N | M111: =Pipeline_Control!AN111 -> 0 | N111: =Pipeline_Control!AO111 -> No expected close date

Sheet Cash_Bridge
A1: Week Start | B1: Week End | C1: Eligible Pipeline Cash | D1: Scenario Only Pipeline | E1: Mapped SO Cash | F1: Notes
A2: 46160 | B2: =A2+6 -> 46166 | C2: =SUMIFS(Cash_Eligibility!$M:$M,Cash_Eligibility!$I:$I,"Eligible",Cash_Eligibility!$G:$G,">="&A2,Cash_Eligibility!$G:$G,"<="&B2) -> 0 | D2: =SUMIFS(Cash_Eligibility!$M:$M,Cash_Eligibility!$I:$I,"Scenario*",Cash_Eligibility!$G:$G,">="&A2,Cash_Eligibility!$G:$G,"<="&B2) -> 0 | F2: Preview only; liquidity workbook tie-out required.
A3: 46167 | B3: =A3+6 -> 46173 | C3: =SUMIFS(Cash_Eligibility!$M:$M,Cash_Eligibility!$I:$I,"Eligible",Cash_Eligibility!$G:$G,">="&A3,Cash_Eligibility!$G:$G,"<="&B3) -> 0 | D3: =SUMIFS(Cash_Eligibility!$M:$M,Cash_Eligibility!$I:$I,"Scenario*",Cash_Eligibility!$G:$G,">="&A3,Cash_Eligibility!$G:$G,"<="&B3) -> 0 | F3: Preview only; liquidity workbook tie-out required.
A4: 46174 | B4: =A4+6 -> 46180 | C4: =SUMIFS(Cash_Eligibility!$M:$M,Cash_Eligibility!$I:$I,"Eligible",Cash_Eligibility!$G:$G,">="&A4,Cash_Eligibility!$G:$G,"<="&B4) -> 0 | D4: =SUMIFS(Cash_Eligibility!$M:$M,Cash_Eligibility!$I:$I,"Scenario*",Cash_Eligibility!$G:$G,">="&A4,Cash_Eligibility!$G:$G,"<="&B4) -> 0 | F4: Preview only; liquidity workbook tie-out required.
A5: 46181 | B5: =A5+6 -> 46187 | C5: =SUMIFS(Cash_Eligibility!$M:$M,Cash_Eligibility!$I:$I,"Eligible",Cash_Eligibility!$G:$G,">="&A5,Cash_Eligibility!$G:$G,"<="&B5) -> 0 | D5: =SUMIFS(Cash_Eligibility!$M:$M,Cash_Eligibility!$I:$I,"Scenario*",Cash_Eligibility!$G:$G,">="&A5,Cash_Eligibility!$G:$G,"<="&B5) -> 0 | F5: Preview only; liquidity workbook tie-out required.
A6: 46188 | B6: =A6+6 -> 46194 | C6: =SUMIFS(Cash_Eligibility!$M:$M,Cash_Eligibility!$I:$I,"Eligible",Cash_Eligibility!$G:$G,">="&A6,Cash_Eligibility!$G:$G,"<="&B6) -> 0 | D6: =SUMIFS(Cash_Eligibility!$M:$M,Cash_Eligibility!$I:$I,"Scenario*",Cash_Eligibility!$G:$G,">="&A6,Cash_Eligibility!$G:$G,"<="&B6) -> 0 | F6: Preview only; liquidity workbook tie-out required.
A7: 46195 | B7: =A7+6 -> 46201 | C7: =SUMIFS(Cash_Eligibility!$M:$M,Cash_Eligibility!$I:$I,"Eligible",Cash_Eligibility!$G:$G,">="&A7,Cash_Eligibility!$G:$G,"<="&B7) -> 0 | D7: =SUMIFS(Cash_Eligibility!$M:$M,Cash_Eligibility!$I:$I,"Scenario*",Cash_Eligibility!$G:$G,">="&A7,Cash_Eligibility!$G:$G,"<="&B7) -> 0 | F7: Preview only; liquidity workbook tie-out required.
A8: 46202 | B8: =A8+6 -> 46208 | C8: =SUMIFS(Cash_Eligibility!$M:$M,Cash_Eligibility!$I:$I,"Eligible",Cash_Eligibility!$G:$G,">="&A8,Cash_Eligibility!$G:$G,"<="&B8) -> 0 | D8: =SUMIFS(Cash_Eligibility!$M:$M,Cash_Eligibility!$I:$I,"Scenario*",Cash_Eligibility!$G:$G,">="&A8,Cash_Eligibility!$G:$G,"<="&B8) -> 0 | F8: Preview only; liquidity workbook tie-out required.
A9: 46209 | B9: =A9+6 -> 46215 | C9: =SUMIFS(Cash_Eligibility!$M:$M,Cash_Eligibility!$I:$I,"Eligible",Cash_Eligibility!$G:$G,">="&A9,Cash_Eligibility!$G:$G,"<="&B9) -> 0 | D9: =SUMIFS(Cash_Eligibility!$M:$M,Cash_Eligibility!$I:$I,"Scenario*",Cash_Eligibility!$G:$G,">="&A9,Cash_Eligibility!$G:$G,"<="&B9) -> 0 | F9: Preview only; liquidity workbook tie-out required.
A10: 46216 | B10: =A10+6 -> 46222 | C10: =SUMIFS(Cash_Eligibility!$M:$M,Cash_Eligibility!$I:$I,"Eligible",Cash_Eligibility!$G:$G,">="&A10,Cash_Eligibility!$G:$G,"<="&B10) -> 0 | D10: =SUMIFS(Cash_Eligibility!$M:$M,Cash_Eligibility!$I:$I,"Scenario*",Cash_Eligibility!$G:$G,">="&A10,Cash_Eligibility!$G:$G,"<="&B10) -> 0 | F10: Preview only; liquidity workbook tie-out required.
A11: 46223 | B11: =A11+6 -> 46229 | C11: =SUMIFS(Cash_Eligibility!$M:$M,Cash_Eligibility!$I:$I,"Eligible",Cash_Eligibility!$G:$G,">="&A11,Cash_Eligibility!$G:$G,"<="&B11) -> 0 | D11: =SUMIFS(Cash_Eligibility!$M:$M,Cash_Eligibility!$I:$I,"Scenario*",Cash_Eligibility!$G:$G,">="&A11,Cash_Eligibility!$G:$G,"<="&B11) -> 0 | F11: Preview only; liquidity workbook tie-out required.
A12: 46230 | B12: =A12+6 -> 46236 | C12: =SUMIFS(Cash_Eligibility!$M:$M,Cash_Eligibility!$I:$I,"Eligible",Cash_Eligibility!$G:$G,">="&A12,Cash_Eligibility!$G:$G,"<="&B12) -> 0 | D12: =SUMIFS(Cash_Eligibility!$M:$M,Cash_Eligibility!$I:$I,"Scenario*",Cash_Eligibility!$G:$G,">="&A12,Cash_Eligibility!$G:$G,"<="&B12) -> 0 | F12: Preview only; liquidity workbook tie-out required.
A13: 46237 | B13: =A13+6 -> 46243 | C13: =SUMIFS(Cash_Eligibility!$M:$M,Cash_Eligibility!$I:$I,"Eligible",Cash_Eligibility!$G:$G,">="&A13,Cash_Eligibility!$G:$G,"<="&B13) -> 0 | D13: =SUMIFS(Cash_Eligibility!$M:$M,Cash_Eligibility!$I:$I,"Scenario*",Cash_Eligibility!$G:$G,">="&A13,Cash_Eligibility!$G:$G,"<="&B13) -> 0 | F13: Preview only; liquidity workbook tie-out required.
... A27: 46335 | B27: =A27+6 -> 46341 | C27: =SUMIFS(Cash_Eligibility!$M:$M,Cash_Eligibility!$I:$I,"Eligible",Cash_Eligibility!$G:$G,">="&A27,Cash_Eligibility!$G:$G,"<="&B27) -> 0 | D27: =SUMIFS(Cash_Eligibility!$M:$M,Cash_Eligibility!$I:$I,"Scenario*",Cash_Eligibility!$G:$G,">="&A27,Cash_Eligibility!$G:$G,"<="&B27) -> 0 | F27: Preview only; liquidity workbook tie-out required.

Sheet App_Readiness_Checks
A1: Check | B1: Value | C1: Pass Condition | D1: Severity | E1: Owner Notes
A2: Total Deals | B2: =COUNTA(Pipeline_Control!$B$2:$B$111) -> 110 | C2: Info | D2: Info
A3: Deals Missing Expected Close Date | B3: =COUNTBLANK(Pipeline_Control!$J$2:$J$111) -> 82 | C3: Must be reviewed before cash feed | D3: High | E3: No-date deals should remain Scenario Only / Not Eligible.
A4: Liquidity Eligible Deals | B4: =COUNTIF(Pipeline_Control!$AK$2:$AK$111,"Y") -> 16 | C4: Only defensible rows should feed liquidity | D4: High
A5: SO Mapping Review Required | B5: =COUNTIF(Pipeline_Control!$AM$2:$AM$111,"Y") -> 12 | C5: Must be 0 before SO-based liquidity feed | D5: Critical | E5: Many-to-many SO matching must be resolved.
A6: Mapping Rows Needing Allocation | B6: =COUNTIF(SO_Mapping!$H$2:$H$57,"Y") -> 42 | C6: Must be 0 before liquidity tie-in | D6: Critical | E6: Populate SO_Source and allocation %.
A7: Included But Not Cash Eligible | B7: =COUNTIFS(Pipeline_Control!$I$2:$I$111,"Y",Pipeline_Control!$AK$2:$AK$111,"N") -> 94 | C7: Expected during review | D7: Warning | E7: These stay in dashboard, not cash forecast.
A8: Duplicate Deal IDs | B8: =SUMPRODUCT(--(Pipeline_Control!$B$2:$B$111<>""),--(COUNTIF(Pipeline_Control!$B$2:$B$111,Pipeline_Control!$B$2:$B$111)>1)) -> 0 | C8: Should be 0 | D8: High

Sheet Lookups
A1: Deal Status | B1: Include Flag | C1: Pipeline Visibility | D1: Cash Forecast Eligibility | E1: Timing Confidence | F1: Mapping Review
A2: Open | B2: Y | C2: Active | D2: Eligible | E2: High - SO Supported | F2: Y
A3: Won | B3: N | C3: Watchlist | D3: Scenario Only - No Close Date | E3: Medium - Manual Timing | F3: N
A4: Lost | C4: Converted/Partially Converted | D4: Scenario Only - No Ship Date | E4: Low - No Timing
A5: Dormant | C5: Excluded | D5: Scenario Only - No Cash Date
A6: Dead | C6: Lost | D6: Not Eligible - SO Mapping Review
D7: Not Eligible - Excluded
D8: Not Eligible - Lost

Sheet Dashboard
A1: DPS Pipeline → Streamlit Readiness Dashboard
A2: Metric | B2: Value | C2: Interpretation | D2: Action
A3: Total Deals | B3: =App_Readiness_Checks!B2 -> 110 | C3: Pipeline rows loaded
A4: Missing Close Date | B4: =App_Readiness_Checks!B3 -> 82 | C4: Visibility only; not cash-ready | D4: Review timing or leave as Scenario Only
A5: Liquidity Eligible Deals | B5: =App_Readiness_Checks!B4 -> 16 | C5: Rows allowed to feed cash preview | D5: Must be conservative
A6: SO Mapping Review Required | B6: =App_Readiness_Checks!B5 -> 12 | C6: Blocks liquidity tie-in | D6: Resolve with SO_Source + SO_Mapping
A7: Mapping Rows Needing Allocation | B7: =App_Readiness_Checks!B6 -> 42 | C7: Many-to-many SO issue | D7: Populate actual SO amounts/allocation %
A8: Included But Not Cash Eligible | B8: =App_Readiness_Checks!B7 -> 94 | C8: Good warning bucket | D8: Do not feed into liquidity
A10: Architecture | B10: Pipeline_Control + SO_Source + SO_Mapping → Cash_Eligibility → Cash_Bridge
A11: Hard Rule | B11: No expected close/cash date and no resolved SO mapping = no liquidity feed.
